Workbook

Sheet Sheet1
B1: xxx | C1: M2访谈数据/Assumption
B2: xxx | C2: 引用数据
B3: xxx | C3: 计算所得数据

Sheet >现货情境下
B1: xxx | C1: M2访谈数据/Assumption
B2: xxx | C2: 引用数据
B3: xxx | C3: 计算所得数据
D6: h1: 峰有多高由发电量/负荷缺口来决定的（True） | N6: h1: 谷有多低是风光占比决定的（False）
D7: 各省用电量（亿千瓦时） | N7: 各省风光装机量（万千瓦）
B8: 现货开展 | C8: Sum-Ranking 理论峰谷价差高 | D8: 倒RANKING - 发电量 | E8: 省份 | F8: 22年3月电网代购峰谷价差 | G8: 22年4月电网代购峰谷价差 | H8: 2021年各省用电量（亿千瓦时） | I8: 2021年各省GDP（亿元） | J8: 2021年kWh: GDP（kWh/元） | K8: 2021用电量占全国比重 | L8: 2025年 | M8: 2030年 | N8: RANKING-光伏发电占比 | O8: 省份 | P8: 2021年各区域风光总装机量 | Q8: 2021年各区域风光占电源总装机比重 | R8: 2021光伏发电量占本地区电力供应比重% | S8: 2025年
B9: 第一批 | C9: =(D9+N9)^(1/2) -> 7.4161985 | D9: 30 | E9: 广东省 | F9: 0.9545999 | G9: 0.9952 | H9: 7866.63 | I9: 124369.67 | J9: =H9/I9 -> 0.063251997 | K9: 0.098128963 | L9: 9027.8646 | M9: 10499.799 | N9: 25 | O9: 广东省 | P9: 2215 | Q9: 0.141 | R9: 0.017 | S9: 0.2333
C10: =(D10+N10)^(1/2) -> 6.3245553 | D10: 29 | E10: 山东省 | F10: 0.5547 | G10: 0.5502 | H10: 7382.93 | I10: 83095.9 | J10: =H10/I10 -> 0.088848307 | K10: 0.092095251 | L10: 8472.7631 | M10: 9854.1919 | N10: 11 | O10: 山东省 | P10: 5285 | Q10: 0.305 | R10: 0.05 | S10: 0.42
B11: 第一批 | C11: =(D11+N11)^(1/2) -> 6.4807407 | D11: 28 | E11: 江苏省 | F11: 0.8368 | G11: 0.8389 | H11: 7001.16 | I11: 116364.2 | J11: =H11/I11 -> 0.060165927 | K11: 0.087333022 | L11: 8034.638 | M11: 9344.6334 | N11: 14 | O11: 江苏省 | P11: 4150 | Q11: 0.269 | R11: 0.033 | S11: 0.34363636
C12: =(D12+N12)^(1/2) -> 6.78233 | D12: 27 | E12: 浙江省 | F12: 0.5915 | G12: 0.622 | H12: 5514.11 | I12: 73516 | J12: =H12/I12 -> 0.075005577 | K12: 0.068783443 | L12: 6328.0768 | M12: 7359.8284 | N12: 19 | O12: 浙江省 | P12: 2206 | Q12: 0.204 | R12: 0.037 | S12: 0.36
C13: =(D13+N13)^(1/2) -> 5.5677644 | D13: 26 | E13: 内蒙古自治区 | F13: 0.598588 | G13: 0.590095 | H13: 4154.98 | I13: 20514.2 | J13: =H13/I13 -> 0.20254165 | K13: 0.051829548 | L13: 4768.3184 | M13: 5545.7617 | N13: 5 | O13: 内蒙古自治区 | P13: 5408 | Q13: 0.349 | R13: 0.035 | S13: 0.622
B14: 第二批 | C14: =(D14+N14)^(1/2) -> 5.9160798 | D14: 25 | E14: 河南省 | F14: 0.661431 | G14: 0.665818 | H14: 3646.91 | I14: 58887.41 | J14: =H14/I14 -> 0.061930216 | K14: 0.045491843 | L14: 4185.2496 | M14: 4867.6272 | N14: 10 | O14: 河南省 | P14: 3406 | Q14: 0.306 | R14: 0.046 | S14: 0.3846
B15: 第一批 | C15: =(D15+N15)^(1/2) -> 7.3484692 | D15: 24 | E15: 四川省 | F15: 0.78948 | G15: 0.792 | H15: 3274.81 | I15: 53850.79 | J15: =H15/I15 -> 0.060812664 | K15: 0.040850238 | L15: 3758.2219 | M15: 4370.9755 | N15: 30 | O15: 四川省 | P15: 723 | Q15: 0.063 | R15: 0.007 | S15: 0.1467
B16: 第一批-蒙西 | C16: =(D16+N16)^(1/2) -> 6.78233 | D16: 23 | E16: 福建省 | F16: 0.5681 | G16: 0.5653 | H16: 2836.66 | I16: 48810 | J16: =H16/I16 -> 0.05811637 | K16: 0.035384721 | L16: 3255.3943 | M16: 3786.1651 | N16: 23 | O16: 福建省 | P16: 1012 | Q16: 0.145 | R16: 0.009 | S16: 0.23
C17: =(D17+N17)^(1/2) -> 5.2915026 | D17: 22 | E17: 新疆维吾尔自治区 | F17: 0 | G17: 0 | H17: 2734.18 | I17: 16000 | J17: =H17/I17 -> 0.17088625 | K17: 0.034106377 | L17: 3137.7867 | M17: 3649.3823 | N17: 6 | O17: 新疆省 | P17: 3762 | Q17: 0.326 | R17: 0.044 | S17: 0.38
B18: 第二批 | C18: =(D18+N18)^(1/2) -> 6 | D18: 21 | E18: 安徽省 | F18: 0.8279 | G18: 0.8279 | H18: 2715.47 | I18: 42959.2 | J18: =H18/I18 -> 0.063210442 | K18: 0.033872987 | L18: 3116.3148 | M18: 3624.4096 | N18: 15 | O18: 安徽省 | P18: 2218 | Q18: 0.262 | R18: 0.051 | S18: 0.4
B19: 第一批 | C19: =(D19+N19)^(1/2) -> 6 | D19: 20 | E19: 山西省 | F19: 0.64983 | G19: 0.511179 | H19: 2607.91 | I19: 22590.16 | J19: =H19/I19 -> 0.11544451 | K19: 0.032531275 | L19: 2992.8773 | M19: 3480.8464 | N19: 16 | O19: 山西省 | P19: 1565 | Q19: 0.253 | R19: 0.026 | S19: 0.4
C20: =(D20+N20)^(1/2) -> 5.1961524 | D20: 19 | E20: 辽宁省 | F20: 0.553506 | G20: 0.64485 | H20: 2575.61 | I20: 27584.1 | J20: =H20/I20 -> 0.093372994 | K20: 0.032128362 | L20: 2955.8093 | M20: 3437.7348 | N20: 8 | O20: 辽宁省 | P20: 3581 | Q20: 0.316 | R20: 0.049 | S20: 0.5
B21: 第二批 | C21: =(D21+N21)^(1/2) -> 6.244998 | D21: 18 | E21: 湖北省 | F21: 0.712151 | G21: 0.671852 | H21: 2470.76 | I21: 50012.94 | J21: =H21/I21 -> 0.049402415 | K21: 0.030820455 | L21: 2835.4819 | M21: 3297.7887 | N21: 21 | O21: 湖北省 | P21: 1673 | Q21: 0.19 | R21: 0.025 | S21: 0.25
C22: =(D22+N22)^(1/2) -> 4.3588989 | D22: 17 | E22: 河北省 | F22: 0.4052 | G22: 0.4024 | H22: 2431.43 | I22: 40391.3 | J22: =H22/I22 -> 0.060196874 | K22: 0.03032985 | L22: 2790.3462 | M22: 3245.2939 | N22: 2 | O22: 河北省 | P22: 5467 | Q22: 0.494 | R22: 0.091 | S22: 0.55
C23: =(D23+N23)^(1/2) -> 6 | D23: 16 | E23: 广西壮族自治区 | F23: 0.558375 | G23: 0.576575 | H23: 2236.23 | I23: 24740.86 | J23: =H23/I23 -> 0.090386106 | K23: 0.027894909 | L23: 2566.3317 | M23: 2984.7553 | N23: 20 | O23: 广西壮族自治区 | P23: 1053 | Q23: 0.192 | R23: 0.014 | S23: 0.51
B24: 第一批 | C24: =(D24+N24)^(1/2) -> 5.6568542 | D24: 15 | E24: 湖南省 | F24: 0.83305 | G24: 0.576575 | H24: 2154.54 | I24: 46063.09 | J24: =H24/I24 -> 0.046773675 | K24: 0.026875902 | L24: 2472.583 | M24: 2875.7215 | N24: 17 | O24: 湖南省 | P24: 1254 | Q24: 0.234 | R24: 0.022 | S24: 0.57
C25: =(D25+N25)^(1/2) -> 6.3245553 | D25: 14 | E25: 云南省 | F25: 0.46815 | G25: 0.46815 | H25: 2138.25 | I25: 27100 | J25: =H25/I25 -> 0.078902214 | K25: 0.026672699 | L25: 2453.8883 | M25: 2853.9788 | N25: 26 | O25: 云南省 | P25: 1278 | Q25: 0.12 | R25: 0.014 | S25: 0.26
C26: =(D26+N26)^(1/2) -> 5 | D26: 13 | E26: 江西省 | F26: 0.388656 | G26: 0.388656 | H26: 1862.52 | I26: 29619.7 | J26: =H26/I26 -> 0.062881123 | K26: 0.023233221 | L26: 2137.4564 | M26: 2485.9547 | N26: 12 | O26: 江西省 | P26: 1458 | Q26: 0.301 | R26: 0.049 | S26: 0.475
C27: =(D27+N27)^(1/2) -> 6.244998 | D27: 12 | E27: 上海市 | F27: 0.5039 | G27: 0.4931 | H27: 1749.62 | I27: 43214.85 | J27: =H27/I27 -> 0.040486546 | K27: 0.021824898 | L27: 2007.8906 | M27: 2335.2641 | N27: 27 | O27: 上海市 | P27: 275 | Q27: 0.098 | R27: 0.015 | S27: 0.17
C28: =(D28+N28)^(1/2) -> 5.3851648 | D28: 11 | E28: 贵州省 | F28: 0 | G28: 0 | H28: 1742.75 | I28: 19586.42 | J28: =H28/I28 -> 0.088977465 | K28: 0.021739201 | L28: 2000.0065 | M28: 2326.0945 | N28: 18 | O28: 贵州省 | P28: 1717 | Q28: 0.227 | R28: 0.034 | S28: 0.4
B29: 第二批 | C29: =(D29+N29)^(1/2) -> 4.3588989 | D29: 10 | E29: 陕西省 | F29: 0.5414 | G29: 0.5261 | H29: 1736.73 | I29: 29800.98 | J29: =H29/I29 -> 0.058277614 | K29: 0.021664107 | L29: 1993.0978 | M29: 2318.0594 | N29: 9 | O29: 陕西省 | P29: 2335 | Q29: 0.306 | R29: 0.051 | S29: 0.5
B30: 第一批 | C30: =(D30+N30)^(1/2) -> 3.4641016 | D30: 9 | E30: 甘肃省 | F30: 0.2563 | G30: 0.356 | H30: 1494.7 | I30: 10243.3 | J30: =H30/I30 -> 0.14591977 | K30: 0.018645006 | L30: 1715.3405 | M30: 1995.0156 | N30: 3 | O30: 甘肃省 | P30: 2871 | Q30: 0.466 | R30: 0.078 | S30: 0.65
B31: 第二批 | C31: =(D31+N31)^(1/2) -> 6.0827625 | D31: 8 | E31: 北京市 | F31: 0.632901 | G31: 0.57259 | H31: 1232.92 | I31: 40269.6 | J31: =H31/I31 -> 0.030616644 | K31: 0.015379541 | L31: 1414.9178 | M31: 1645.6109 | N31: 29 | O31: 北京市 | P31: 104 | Q31: 0.078 | R31: 0.013 | S31: 0.14
C32: =(D32+N32)^(1/2) -> 5.9160798 | D32: 7 | E32: 重庆市 | F32: 0.784269 | G32: 0.75874 | H32: 1167.55 | I32: 27894.02 | J32: =H32/I32 -> 0.041856642 | K32: 0.014564111 | L32: 1339.8982 | M32: 1558.3599 | N32: 28 | O32: 重庆市 | P32: 228 | Q32: 0.09 | R32: 0.005 | S32: 0.193
C33: =(D33+N33)^(1/2) -> 3.1622777 | D33: 6 | E33: 宁夏回族自治区 | F33: 0.3942 | G33: 0.4682 | H33: 1158.49 | I33: 4522.3 | J33: =H33/I33 -> 0.25617274 | K33: 0.014451096 | L33: 1329.5008 | M33: 1546.2672 | N33: 4 | O33: 宁夏回族自治区 | P33: 2839 | Q33: 0.457 | R33: 0.092 | S33: 0.5
C34: =(D34+N34)^(1/2) -> 3.4641016 | D34: 5 | E34: 黑龙江省 | F34: 0.721331 | G34: 0.721065 | H34: 1088.75 | I34: 14879.2 | J34: =H34/I34 -> 0.073172617 | K34: 0.013581153 | L34: 1249.4661 | M34: 1453.1834 | N34: 7 | O34: 黑龙江省 | P34: 1255 | Q34: 0.317 | R34: 0.045 | S34: 0.5
C35: =(D35+N35)^(1/2) -> 5.2915026 | D35: 4 | E35: 天津市 | F35: 0.6485 | G35: 0.6475 | H35: 982.29 | I35: 15695.05 | J35: =H35/I35 -> 0.062585975 | K35: 0.012253163 | L35: 1127.291 | M35: 1311.0884 | N35: 24 | O35: 天津市 | P35: 308 | Q35: 0.141 | R35: 0.026 | S35: 0.3
C36: =(D36+N36)^(1/2) -> 2 | D36: 3 | E36: 青海省 | F36: 0.148995 | G36: 0.298368 | H36: 857.64 | I36: 3346.63 | J36: =H36/I36 -> 0.25626974 | K36: 0.010698269 | L36: 984.24075 | M36: 1144.7148 | N36: 1 | O36: 青海省 | P36: 2528 | Q36: 0.615 | R36: 0.213 | S36: 0.67
C37: =(D37+N37)^(1/2) -> 3.8729833 | D37: 2 | E37: 吉林省 | F37: 0.71114 | G37: 0.71106 | H37: 843.18 | I37: 13235.52 | J37: =H37/I37 -> 0.063705846 | K37: 0.010517894 | L37: 967.64623 | M37: 1125.4146 | N37: 13 | O37: 吉林省 | P37: 1011 | Q37: 0.29 | R37: 0.053 | S37: 0.224
B38: 第一批 | C38: =(D38+N38)^(1/2) -> 4.7958315 | D38: 1 | E38: 海南省 | F38: 0.8417 | G38: 0.8489 | H38: 405.47 | I38: 6475.2 | J38: =H38/I38 -> 0.062618915 | K38: 0.0050578648 | L38: 465.32356 | M38: 541.19153 | N38: 22 | O38: 海南省 | P38: 176 | Q38: 0.166 | R38: 0.041 | S38: 0.3
K40: 高：用电量占全国比重>4.1% | O40: 高：2025年风光装机占本地电力总装机量比重>40%
K41: 中：2.6-4.1% | O41: 中：20~40%
K42: 低：<2.6% | O42: 低：<20%

Sheet 表后_现货价差高
B1: xxx | C1: M2访谈数据/Assumption
B2: xxx | C2: 引用数据
B3: xxx | C3: 计算所得数据
C4: 自变量 | D4: *表后用户侧储能主要通过现货形式进行峰谷套利，收益部分由峰负荷时的用户分摊
C5: 支出项 | D5: 关键假设：
C6: 收入项 | D6: 1）电池充放电循环次数~6525次
D7: 2）PCS成本：0.21元/W；电池充放电循环次数~6525次；容量型储能电站运维费用：0.1%；PCS效率：98%；线损：98%；系统使用天数：350天；充放循环次数（1次为1充1放）(次/天）：1次
B8: 更新处：标绿色的单元格 | D8: 3）充放策略：一充一放（1*谷-1*峰）
B11: 基本数据 | E11: 计算结果
B12: 充放策略：一充一放（1*谷-1*峰） | E12: LCOS（元/kWh) | F12: =F43 -> 0.65629663
B13: 谷 | C13: 1 | E13: 投资回报率 | F13: =F48 -> -0.25538842
B14: 平 | C14: 0 | E14: NPV(折现率=7%） | F14: =SUM(F47:O47) -> -3.1165991 | H14: 价差为0.8时： | I14: 0.096140341
B15: 峰 | C15: =C13+C14 -> 1 | E15: IRR | F15: =V48 -> 0.023663328 | H15: 价差为0.7时： | I15: 0.074401405
B16: 基本数据 | E16: 折现率 | F16: 0.07 | U16: 折现率 | V16: 0
B17: PCS(KW） | C17: 1200 | E17: 所得税率 | F17: 0.25 | U17: 所得税率 | V17: 0.25
B18: PCS成本（元/kW) | C18: 210 | E18: 增值税率 | F18: 0 | G18: 暂不考虑 | U18: 增值税率 | V18: 0 | W18: 暂不考虑
B19: ESS(KWh) | C19: 4800 | E19: 储能系统经济效益估算表（元） | U19: 储能系统经济效益估算表（元）
B20: ESS成本（元/kWh) | C20: 1400 | E20: 储能平准化成本LCOS（Levelized Cost of Storage） | G20: 1 | H20: 2 | I20: 3 | J20: 4 | K20: 5 | L20: 6 | M20: 7 | N20: 8 | O20: 9 | P20: 10 | Q20: 11 | R20: 12 | S20: 13 | U20: 储能平准化成本LCOS（Levelized Cost of Storage） | W20: 1 | X20: 2 | Y20: 3 | Z20: 4 | AA20: 5 | AB20: 6 | AC20: 7 | AD20: 8 | AE20: 9 | AF20: 10 | AG20: 11 | AH20: 12 | AI20: 13
B21: PCS效率 | C21: 0.98 | F21: 基准年 | G21: 第1年 | H21: 第2年 | I21: 第3年 | J21: 第4年 | K21: 第5年 | L21: 第6年 | M21: 第7年 | N21: 第8年 | O21: 第9年 | P21: 第10年 | Q21: 第11年 | R21: 第12年 | S21: 第13年 | V21: 基准年 | W21: 第1年 | X21: 第2年 | Y21: 第3年 | Z21: 第4年 | AA21: 第5年 | AB21: 第6年 | AC21: 第7年 | AD21: 第8年 | AE21: 第9年 | AF21: 第10年 | AG21: 第11年 | AH21: 第12年 | AI21: 第13年
B22: 线损 | C22: 0.98 | E22: 初始投资成本（Mn RMB） | F22: =C46/1000000 -> 7.442 | U22: 初始投资成本（Mn RMB） | V22: =C46/1000000 -> 7.442
B23: 峰价（元/KWh) | C23: 0.6 | E23: 折旧现值和（Mn RMB） | F23: =SUM(G24:S24) -> 3.1183056 | U23: 折旧现值和（Mn RMB） | V23: =SUM(W24:AI24) -> 4.8504028
B24: 平价（元/KWh) | C24: 0 | E24: 折旧现值（Mn RMB） | G24: =($C$41+$C$42+$C$32)*(1-$C$35)/$C$40/1000000/(1+$F$16)^G20 -> 0.34869898 | H24: =($C$41+$C$42+$C$32)*(1-$C$35)/$C$40/1000000/(1+$F$16)^H20 -> 0.3258869 | I24: =($C$41+$C$42+$C$32)*(1-$C$35)/$C$40/1000000/(1+$F$16)^I20 -> 0.30456719 | J24: =($C$41+$C$42+$C$32)*(1-$C$35)/$C$40/1000000/(1+$F$16)^J20 -> 0.28464224 | K24: =($C$41+$C$42+$C$32)*(1-$C$35)/$C$40/1000000/(1+$F$16)^K20 -> 0.26602078 | L24: =($C$41+$C$42+$C$32)*(1-$C$35)/$C$40/1000000/(1+$F$16)^L20 -> 0.24861755 | M24: =($C$41+$C$42+$C$32)*(1-$C$35)/$C$40/1000000/(1+$F$16)^M20 -> 0.23235285 | N24: =($C$41+$C$42+$C$32)*(1-$C$35)/$C$40/1000000/(1+$F$16)^N20 -> 0.2171522 | ... S24: =($C$41+$C$42+$C$32)*(1-$C$35)/$C$40/1000000/(1+$F$16)^S20 -> 0.15482652 | U24: 折旧现值（Mn RMB） | W24: =($C$41+$C$42+$C$32)*(1-$C$35)/$C$40/1000000/(1+$V$16)^W20 -> 0.37310791 | X24: =($C$41+$C$42+$C$32)*(1-$C$35)/$C$40/1000000/(1+$V$16)^X20 -> 0.37310791 | Y24: =($C$41+$C$42+$C$32)*(1-$C$35)/$C$40/1000000/(1+$V$16)^Y20 -> 0.37310791 | Z24: =($C$41+$C$42+$C$32)*(1-$C$35)/$C$40/1000000/(1+$V$16)^Z20 -> 0.37310791 | AA24: =($C$41+$C$42+$C$32)*(1-$C$35)/$C$40/1000000/(1+$V$16)^AA20 -> 0.37310791 | AB24: =($C$41+$C$42+$C$32)*(1-$C$35)/$C$40/1000000/(1+$V$16)^AB20 -> 0.37310791 | AC24: =($C$41+$C$42+$C$32)*(1-$C$35)/$C$40/1000000/(1+$V$16)^AC20 -> 0.37310791 | AD24: =($C$41+$C$42+$C$32)*(1-$C$35)/$C$40/1000000/(1+$V$16)^AD20 -> 0.37310791 | ... AI24: =($C$41+$C$42+$C$32)*(1-$C$35)/$C$40/1000000/(1+$V$16)^AI20 -> 0.37310791
B25: 谷价（元/KWh) | C25: 0 | E25: 运行成本现值和（Mn RMB） | F25: =SUM(G26:S26) -> 0.062197637 | U25: 运行成本现值和（Mn RMB） | V25: =SUM(W26:AI26) -> 0.096746
B26: 系统年使用天数 (天) | C26: 350 | E26: 运行成本现值（Mn RMB） | G26: =($C$34*$F$22)/((1+$F$16)^G20) -> 0.0069551402 | H26: =($C$34*$F$22)/((1+$F$16)^H20) -> 0.006500131 | I26: =($C$34*$F$22)/((1+$F$16)^I20) -> 0.0060748888 | J26: =($C$34*$F$22)/((1+$F$16)^J20) -> 0.0056774662 | K26: =($C$34*$F$22)/((1+$F$16)^K20) -> 0.0053060431 | L26: =($C$34*$F$22)/((1+$F$16)^L20) -> 0.0049589188 | M26: =($C$34*$F$22)/((1+$F$16)^M20) -> 0.0046345036 | N26: =($C$34*$F$22)/((1+$F$16)^N20) -> 0.0043313118 | ... S26: =($C$34*$F$22)/((1+$F$16)^S20) -> 0.0030881654 | U26: 运行成本现值（Mn RMB） | W26: =($C$34*$V$22)/((1+$V$16)^W20) -> 0.007442 | X26: =($C$34*$V$22)/((1+$V$16)^X20) -> 0.007442 | Y26: =($C$34*$V$22)/((1+$V$16)^Y20) -> 0.007442 | Z26: =($C$34*$V$22)/((1+$V$16)^Z20) -> 0.007442 | AA26: =($C$34*$V$22)/((1+$V$16)^AA20) -> 0.007442 | AB26: =($C$34*$V$22)/((1+$V$16)^AB20) -> 0.007442 | AC26: =($C$34*$V$22)/((1+$V$16)^AC20) -> 0.007442 | AD26: =($C$34*$V$22)/((1+$V$16)^AD20) -> 0.007442 | ... AI26: =($C$34*$V$22)/((1+$V$16)^AI20) -> 0.007442
B27: DOD% | C27: 0.95 | E27: 固定资产残值现值 (Mn RMB) | S27: =(C41+C42)*C35/((1+F16)^S20)/1000000 -> 0.14465661 | U27: 固定资产残值现值 (Mn RMB) | AI27: =(C41+C42)*C35/((1+V16)^AI20)/1000000 -> 0.3486
B28: 单次循环衰减率 | C28: 4.68e-05 | E28: 充电电量现值和(KWh) | F28: =SUM(G29:S29) -> 13339597 | U28: 充电电量现值和(KWh) | V28: =SUM(W29:AI29) -> 20435477
B29: 系统报废终止标准 | C29: 0.7 | E29: 充电电量现值(KWh) | G29: =$C$19*$C$36*$C$26/$C$37*($C$27*(1-$C$28)^((G20-1)*$C$26*$C$36))/$C$21/$C$22/((1+$F$16)^G20) -> 1617803.3 | H29: =$C$19*$C$36*$C$26/$C$37*($C$27*(1-$C$28)^((H20-1)*$C$26*$C$36))/$C$21/$C$22/((1+$F$16)^H20) -> 1487400.9 | I29: =$C$19*$C$36*$C$26/$C$37*($C$27*(1-$C$28)^((I20-1)*$C$26*$C$36))/$C$21/$C$22/((1+$F$16)^I20) -> 1367509.5 | J29: =$C$19*$C$36*$C$26/$C$37*($C$27*(1-$C$28)^((J20-1)*$C$26*$C$36))/$C$21/$C$22/((1+$F$16)^J20) -> 1257281.9 | K29: =$C$19*$C$36*$C$26/$C$37*($C$27*(1-$C$28)^((K20-1)*$C$26*$C$36))/$C$21/$C$22/((1+$F$16)^K20) -> 1155939.2 | L29: =$C$19*$C$36*$C$26/$C$37*($C$27*(1-$C$28)^((L20-1)*$C$26*$C$36))/$C$21/$C$22/((1+$F$16)^L20) -> 1062765.1 | M29: =$C$19*$C$36*$C$26/$C$37*($C$27*(1-$C$28)^((M20-1)*$C$26*$C$36))/$C$21/$C$22/((1+$F$16)^M20) -> 977101.32 | N29: =$C$19*$C$36*$C$26/$C$37*($C$27*(1-$C$28)^((N20-1)*$C$26*$C$36))/$C$21/$C$22/((1+$F$16)^N20) -> 898342.43 | ... S29: =$C$19*$C$36*$C$26/$C$37*($C$27*(1-$C$28)^((S20-1)*$C$26*$C$36))/$C$21/$C$22/((1+$F$16)^S20) -> 590137.85 | U29: 充电电量现值(KWh) | W29: =$C$19*$C$36*$C$26/$C$37*($C$27*(1-$C$28)^((W20-1)*$C$26*$C$36))/$C$21/$C$22/((1+$V$16)^W20) -> 1731049.6 | X29: =$C$19*$C$36*$C$26/$C$37*($C$27*(1-$C$28)^((X20-1)*$C$26*$C$36))/$C$21/$C$22/((1+$V$16)^X20) -> 1702925.3 | Y29: =$C$19*$C$36*$C$26/$C$37*($C$27*(1-$C$28)^((Y20-1)*$C$26*$C$36))/$C$21/$C$22/((1+$V$16)^Y20) -> 1675257.9 | Z29: =$C$19*$C$36*$C$26/$C$37*($C$27*(1-$C$28)^((Z20-1)*$C$26*$C$36))/$C$21/$C$22/((1+$V$16)^Z20) -> 1648040.1 | AA29: =$C$19*$C$36*$C$26/$C$37*($C$27*(1-$C$28)^((AA20-1)*$C$26*$C$36))/$C$21/$C$22/((1+$V$16)^AA20) -> 1621264.5 | AB29: =$C$19*$C$36*$C$26/$C$37*($C$27*(1-$C$28)^((AB20-1)*$C$26*$C$36))/$C$21/$C$22/((1+$V$16)^AB20) -> 1594923.8 | AC29: =$C$19*$C$36*$C$26/$C$37*($C$27*(1-$C$28)^((AC20-1)*$C$26*$C$36))/$C$21/$C$22/((1+$V$16)^AC20) -> 1569011.2 | AD29: =$C$19*$C$36*$C$26/$C$37*($C$27*(1-$C$28)^((AD20-1)*$C$26*$C$36))/$C$21/$C$22/((1+$V$16)^AD20) -> 1543519.5 | ... AI29: =$C$19*$C$36*$C$26/$C$37*($C$27*(1-$C$28)^((AI20-1)*$C$26*$C$36))/$C$21/$C$22/((1+$V$16)^AI20) -> 1422140.8
B30: 土建成本(元/Wh) | C30: 0.015 | E30: 放电电量现值和(KWh) | F30: =SUM(G31:S31) -> 11339385 | U30: 放电电量现值和(KWh) | V30: =SUM(W31:AI31) -> 17371269
B31: 土建残值率（%） | C31: 0 | E31: 放电电量现值(KWh) | G31: =$C$19*$C$36*$C$26*$C$37*($C$27*(1-$C$28)^((G20-1)*$C$26*$C$36))*$C$21*$C$22/((1+$F$16)^G20) -> 1375221 | H31: =$C$19*$C$36*$C$26*$C$37*($C$27*(1-$C$28)^((H20-1)*$C$26*$C$36))*$C$21*$C$22/((1+$F$16)^H20) -> 1264371.8 | I31: =$C$19*$C$36*$C$26*$C$37*($C$27*(1-$C$28)^((I20-1)*$C$26*$C$36))*$C$21*$C$22/((1+$F$16)^I20) -> 1162457.6 | J31: =$C$19*$C$36*$C$26*$C$37*($C$27*(1-$C$28)^((J20-1)*$C$26*$C$36))*$C$21*$C$22/((1+$F$16)^J20) -> 1068758.1 | K31: =$C$19*$C$36*$C$26*$C$37*($C$27*(1-$C$28)^((K20-1)*$C$26*$C$36))*$C$21*$C$22/((1+$F$16)^K20) -> 982611.27 | L31: =$C$19*$C$36*$C$26*$C$37*($C$27*(1-$C$28)^((L20-1)*$C$26*$C$36))*$C$21*$C$22/((1+$F$16)^L20) -> 903408.26 | M31: =$C$19*$C$36*$C$26*$C$37*($C$27*(1-$C$28)^((M20-1)*$C$26*$C$36))*$C$21*$C$22/((1+$F$16)^M20) -> 830589.37 | N31: =$C$19*$C$36*$C$26*$C$37*($C$27*(1-$C$28)^((N20-1)*$C$26*$C$36))*$C$21*$C$22/((1+$F$16)^N20) -> 763640.02 | ... S31: =$C$19*$C$36*$C$26*$C$37*($C$27*(1-$C$28)^((S20-1)*$C$26*$C$36))*$C$21*$C$22/((1+$F$16)^S20) -> 501649.33 | U31: 放电电量现值(KWh) | W31: =$C$19*$C$36*$C$26*$C$37*($C$27*(1-$C$28)^((W20-1)*$C$26*$C$36))*$C$21*$C$22/((1+$V$16)^W20) -> 1471486.5 | X31: =$C$19*$C$36*$C$26*$C$37*($C$27*(1-$C$28)^((X20-1)*$C$26*$C$36))*$C$21*$C$22/((1+$V$16)^X20) -> 1447579.3 | Y31: =$C$19*$C$36*$C$26*$C$37*($C$27*(1-$C$28)^((Y20-1)*$C$26*$C$36))*$C$21*$C$22/((1+$V$16)^Y20) -> 1424060.5 | Z31: =$C$19*$C$36*$C$26*$C$37*($C$27*(1-$C$28)^((Z20-1)*$C$26*$C$36))*$C$21*$C$22/((1+$V$16)^Z20) -> 1400923.9 | AA31: =$C$19*$C$36*$C$26*$C$37*($C$27*(1-$C$28)^((AA20-1)*$C$26*$C$36))*$C$21*$C$22/((1+$V$16)^AA20) -> 1378163.1 | AB31: =$C$19*$C$36*$C$26*$C$37*($C$27*(1-$C$28)^((AB20-1)*$C$26*$C$36))*$C$21*$C$22/((1+$V$16)^AB20) -> 1355772.2 | AC31: =$C$19*$C$36*$C$26*$C$37*($C$27*(1-$C$28)^((AC20-1)*$C$26*$C$36))*$C$21*$C$22/((1+$V$16)^AC20) -> 1333745 | AD31: =$C$19*$C$36*$C$26*$C$37*($C$27*(1-$C$28)^((AD20-1)*$C$26*$C$36))*$C$21*$C$22/((1+$V$16)^AD20) -> 1312075.7 | ... AI31: =$C$19*$C$36*$C$26*$C$37*($C$27*(1-$C$28)^((AI20-1)*$C$26*$C$36))*$C$21*$C$22/((1+$V$16)^AI20) -> 1208897.1
B32: 其它设备投资费用（升压变等） | C32: 350000 | E32: 充电成本现值和（Mn RMB） | F32: =SUM(G33:S33) -> 0 | U32: 充电成本现值和（Mn RMB） | V32: =SUM(W33:AI33) -> 0
B33: 其它成本：入网检测费、项目管理费等（元/Wh） | C33: 0.01 | E33: 充电成本现值（Mn RMB） | G33: =($C$13*$C$25*G29/($C$13+$C$14)+$C$14*$C$24*G29/($C$13+$C$14))/1000000 -> 0 | H33: =($C$13*$C$25*H29/($C$13+$C$14)+$C$14*$C$24*H29/($C$13+$C$14))/1000000 -> 0 | I33: =($C$13*$C$25*I29/($C$13+$C$14)+$C$14*$C$24*I29/($C$13+$C$14))/1000000 -> 0 | J33: =($C$13*$C$25*J29/($C$13+$C$14)+$C$14*$C$24*J29/($C$13+$C$14))/1000000 -> 0 | K33: =($C$13*$C$25*K29/($C$13+$C$14)+$C$14*$C$24*K29/($C$13+$C$14))/1000000 -> 0 | L33: =($C$13*$C$25*L29/($C$13+$C$14)+$C$14*$C$24*L29/($C$13+$C$14))/1000000 -> 0 | M33: =($C$13*$C$25*M29/($C$13+$C$14)+$C$14*$C$24*M29/($C$13+$C$14))/1000000 -> 0 | N33: =($C$13*$C$25*N29/($C$13+$C$14)+$C$14*$C$24*N29/($C$13+$C$14))/1000000 -> 0 | ... S33: =($C$13*$C$25*S29/($C$13+$C$14)+$C$14*$C$24*S29/($C$13+$C$14))/1000000 -> 0 | U33: 充电成本现值（Mn RMB） | W33: =($C$13*$C$25*W29/($C$13+$C$14)+$C$14*$C$24*W29/($C$13+$C$14))/1000000 -> 0 | X33: =($C$13*$C$25*X29/($C$13+$C$14)+$C$14*$C$24*X29/($C$13+$C$14))/1000000 -> 0 | Y33: =($C$13*$C$25*Y29/($C$13+$C$14)+$C$14*$C$24*Y29/($C$13+$C$14))/1000000 -> 0 | Z33: =($C$13*$C$25*Z29/($C$13+$C$14)+$C$14*$C$24*Z29/($C$13+$C$14))/1000000 -> 0 | AA33: =($C$13*$C$25*AA29/($C$13+$C$14)+$C$14*$C$24*AA29/($C$13+$C$14))/1000000 -> 0 | AB33: =($C$13*$C$25*AB29/($C$13+$C$14)+$C$14*$C$24*AB29/($C$13+$C$14))/1000000 -> 0 | AC33: =($C$13*$C$25*AC29/($C$13+$C$14)+$C$14*$C$24*AC29/($C$13+$C$14))/1000000 -> 0 | AD33: =($C$13*$C$25*AD29/($C$13+$C$14)+$C$14*$C$24*AD29/($C$13+$C$14))/1000000 -> 0 | ... AI33: =($C$13*$C$25*AI29/($C$13+$C$14)+$C$14*$C$24*AI29/($C$13+$C$14))/1000000 -> 0
B34: 容量型储能电站运维费用 | C34: 0.001 | E34: 放电收益现值和（Mn RMB） | F34: =SUM(G35:S35) -> 6.8036309 | U34: 放电收益现值和（Mn RMB） | V34: =SUM(W35:AI35) -> 10.422762
B35: 储能系统残值 | C35: 0.05 | E35: 放电收益现值（Mn RMB） | G35: =G31*$C$23/1000000 -> 0.8251326 | H35: =H31*$C$23/1000000 -> 0.75862309 | I35: =I31*$C$23/1000000 -> 0.69747456 | J35: =J31*$C$23/1000000 -> 0.64125488 | K35: =K31*$C$23/1000000 -> 0.58956676 | L35: =L31*$C$23/1000000 -> 0.54204495 | M35: =M31*$C$23/1000000 -> 0.49835362 | N35: =N31*$C$23/1000000 -> 0.45818401 | ... S35: =S31*$C$23/1000000 -> 0.3009896 | U35: 放电收益现值（Mn RMB） | W35: =W31*$C$23/1000000 -> 0.88289188 | X35: =X31*$C$23/1000000 -> 0.86854757 | Y35: =Y31*$C$23/1000000 -> 0.85443632 | Z35: =Z31*$C$23/1000000 -> 0.84055433 | AA35: =AA31*$C$23/1000000 -> 0.82689789 | AB35: =AB31*$C$23/1000000 -> 0.81346331 | AC35: =AC31*$C$23/1000000 -> 0.80024701 | AD35: =AD31*$C$23/1000000 -> 0.78724544 | ... AI35: =AI31*$C$23/1000000 -> 0.72533828
B36: 充放循环次数（1次为1充1放）(次/天） | C36: =C13+C14 -> 1 | E36: 所得税现值和（Mn RMB） | F36: =SUM(G37:S37) -> 0.90578192 | U36: 所得税现值和（Mn RMB） | V36: =SUM(W37:AI37) -> 1.3689032
B37: 充放电效率RTE（%） | C37: 0.96 | E37: 所得税现值（Mn RMB） | G37: =(G35-G33-G26-G24)*$F$17 -> 0.11736962 | H37: =(H35-H33-H26-H24)*$F$17 -> 0.10655902 | I37: =(I35-I33-I26-I24)*$F$17 -> 0.096708118 | J37: =(J35-J33-J26-J24)*$F$17 -> 0.087733794 | K37: =(K35-K33-K26-K24)*$F$17 -> 0.079559985 | L37: =(L35-L33-L26-L24)*$F$17 -> 0.07211712 | M37: =(M35-M33-M26-M24)*$F$17 -> 0.065341566 | N37: =(N35-N33-N26-N24)*$F$17 -> 0.059175125 | ... S37: =(S35-S33-S26-S24)*$F$17 -> 0.03576873 | U37: 所得税现值（Mn RMB） | W37: =(W35-W33-W26-W24)*$V$17 -> 0.12558549 | X37: =(X35-X33-X26-X24)*$V$17 -> 0.12199942 | Y37: =(Y35-Y33-Y26-Y24)*$V$17 -> 0.1184716 | Z37: =(Z35-Z33-Z26-Z24)*$V$17 -> 0.11500111 | AA37: =(AA35-AA33-AA26-AA24)*$V$17 -> 0.11158699 | AB37: =(AB35-AB33-AB26-AB24)*$V$17 -> 0.10822835 | AC37: =(AC35-AC33-AC26-AC24)*$V$17 -> 0.10492428 | AD37: =(AD35-AD33-AD26-AD24)*$V$17 -> 0.10167388 | ... AI37: =(AI35-AI33-AI26-AI24)*$V$17 -> 0.086197094
B38: 用户分成比例（%） | C38: 0.1 | E38: 增值税现值和（Mn RMB） | F38: =SUM(G39:S39) -> 0 | U38: 增值税现值和（Mn RMB） | V38: =SUM(W39:AI39) -> 0
B39: 充放循环总次数（次数） | C39: =LOG(C29/C27,(1-C28)) -> 6525.0962 | E39: 增值税现值（Mn RMB） | G39: =(G35-G33)*$F$18 -> 0 | H39: =(H35-H33)*$F$18 -> 0 | I39: =(I35-I33)*$F$18 -> 0 | J39: =(J35-J33)*$F$18 -> 0 | K39: =(K35-K33)*$F$18 -> 0 | L39: =(L35-L33)*$F$18 -> 0 | M39: =(M35-M33)*$F$18 -> 0 | N39: =(N35-N33)*$F$18 -> 0 | ... S39: =(S35-S33)*$F$18 -> 0 | U39: 增值税现值（Mn RMB） | W39: =(W35-W33)*$V$18 -> 0 | X39: =(X35-X33)*$V$18 -> 0 | Y39: =(Y35-Y33)*$V$18 -> 0 | Z39: =(Z35-Z33)*$V$18 -> 0 | AA39: =(AA35-AA33)*$V$18 -> 0 | AB39: =(AB35-AB33)*$V$18 -> 0 | AC39: =(AC35-AC33)*$V$18 -> 0 | AD39: =(AD35-AD33)*$V$18 -> 0 | ... AI39: =(AI35-AI33)*$V$18 -> 0
B40: 系统寿命（年） | C40: =C39/C36/C26 -> 18.643132 | E40: 放电利润现值和（Mn RMB） | F40: =SUM(G41:S41) -> 5.8356513 | U40: 放电利润现值和（Mn RMB） | V40: =SUM(W41:AI41) -> 8.9571124
B41: PCS总成本（元） | C41: =C18*C17 -> 252000 | E41: 放电利润现值和（Mn RMB） | G41: =G35-G33-G37-G39-G26 -> 0.70080784 | H41: =H35-H33-H37-H39-H26 -> 0.64556394 | I41: =I35-I33-I37-I39-I26 -> 0.59469155 | J41: =J35-J33-J37-J39-J26 -> 0.54784362 | K41: =K35-K33-K37-K39-K26 -> 0.50470074 | L41: =L35-L33-L37-L39-L26 -> 0.46496891 | M41: =M35-M33-M37-M39-M26 -> 0.42837755 | N41: =N35-N33-N37-N39-N26 -> 0.39467757 | ... S41: =S35-S33-S37-S39-S26 -> 0.26213271 | U41: 放电利润现值和（Mn RMB） | W41: =W35-W33-W37-W39-W26 -> 0.74986439 | X41: =X35-X33-X37-X39-X26 -> 0.73910616 | Y41: =Y35-Y33-Y37-Y39-Y26 -> 0.72852272 | Z41: =Z35-Z33-Z37-Z39-Z26 -> 0.71811123 | AA41: =AA35-AA33-AA37-AA39-AA26 -> 0.70786889 | AB41: =AB35-AB33-AB37-AB39-AB26 -> 0.69779296 | AC41: =AC35-AC33-AC37-AC39-AC26 -> 0.68788074 | AD41: =AD35-AD33-AD37-AD39-AD26 -> 0.67812955 | ... AI41: =AI35-AI33-AI37-AI39-AI26 -> 0.63169919
B42: ESS总成本（元） | C42: =C19*C20 -> 6720000 | E42: 度电收益（元/kWh) | F42: =C23 -> 0.6 | U42: 度电收益（元/kWh) | V42: =C23 -> 0.6
B43: 土建总投资（元） | C43: =C30*C19*1000 -> 72000 | E43: LCOS（元/kWh) | F43: =F22/F30*1000000 -> 0.65629663 | U43: LCOS（元/kWh) | V43: =V22/V30*1000000 -> 0.42840853
B44: 其它投资（元） | C44: =C33*C19*1000 -> 48000 | E44: 充电成本（元/kWh) | F44: =F32*1000000/F30 -> 0 | U44: 充电成本（元/kWh) | V44: =V32*1000000/V30 -> 0
B45: 设备购置补助（元） | C45: 0 | E45: 用户分成部分（元/kWh) | F45: =SUM(G46:O46) -> 0.46452714 | U45: 用户分成部分（元/kWh) | V45: =SUM(W46:AI46) -> 0.89571124
B46: 设备总投资（元） | C46: =(C44+C43+C42+C41+C32-C45) -> 7442000 | E46: 用户分成部分现值 | G46: =G41*$C$38 -> 0.070080784 | H46: =H41*$C$38 -> 0.064556394 | I46: =I41*$C$38 -> 0.059469155 | J46: =J41*$C$38 -> 0.054784362 | K46: =K41*$C$38 -> 0.050470074 | L46: =L41*$C$38 -> 0.046496891 | M46: =M41*$C$38 -> 0.042837755 | N46: =N41*$C$38 -> 0.039467757 | ... S46: =S41*$C$38 -> 0.026213271 | U46: 用户分成部分现值 | W46: =W41*$C$38 -> 0.074986439 | X46: =X41*$C$38 -> 0.073910616 | Y46: =Y41*$C$38 -> 0.072852272 | Z46: =Z41*$C$38 -> 0.071811123 | AA46: =AA41*$C$38 -> 0.070786889 | AB46: =AB41*$C$38 -> 0.069779296 | AC46: =AC41*$C$38 -> 0.068788074 | AD46: =AD41*$C$38 -> 0.067812955 | ... AI46: =AI41*$C$38 -> 0.063169919
B47: 投资回收年限 | C47: 9+ | E47: NPV | F47: =-(F22) -> -7.442 | G47: =G35-G33-G46-G37-G39-G26 -> 0.63072705 | H47: =H35-H33-H46-H37-H39-H26 -> 0.58100755 | I47: =I35-I33-I46-I37-I39-I26 -> 0.53522239 | J47: =J35-J33-J46-J37-J39-J26 -> 0.49305926 | K47: =K35-K33-K46-K37-K39-K26 -> 0.45423066 | L47: =L35-L33-L46-L37-L39-L26 -> 0.41847202 | M47: =M35-M33-M46-M37-M39-M26 -> 0.3855398 | N47: =N35-N33-N46-N37-N39-N26 -> 0.35520982 | O47: =O35-O33-O46-O37-O39-O26+S27 -> 0.47193236 | P47: =P35-P33-P46-P37-P39-P26+P27 -> 0.30154767 | Q47: =Q35-Q33-Q46-Q37-Q39-Q26+Q27 -> 0.27785074 | R47: =R35-R33-R46-R37-R39-R26+R27 -> 0.25602405 | S47: =S35-S33-S46-S37-S39-S26+S27 -> 0.38057604 | U47: NPV | V47: =-(V22) -> -7.442 | W47: =W35-W33-W46-W37-W39-W26 -> 0.67487795 | X47: =X35-X33-X46-X37-X39-X26 -> 0.66519554 | Y47: =Y35-Y33-Y46-Y37-Y39-Y26 -> 0.65567045 | Z47: =Z35-Z33-Z46-Z37-Z39-Z26 -> 0.6463001 | AA47: =AA35-AA33-AA46-AA37-AA39-AA26 -> 0.637082 | AB47: =AB35-AB33-AB46-AB37-AB39-AB26 -> 0.62801367 | AC47: =AC35-AC33-AC46-AC37-AC39-AC26 -> 0.61909266 | AD47: =AD35-AD33-AD46-AD37-AD39-AD26 -> 0.6103166 | AE47: =AE35-AE33-AE46-AE37-AE39-AE26+AI27 -> 0.95028312 | AF47: =AF35-AF33-AF46-AF37-AF39-AF26+AF27 -> 0.59318991 | AG47: =AG35-AG33-AG46-AG37-AG39-AG26+AG27 -> 0.58483468 | AH47: =AH35-AH33-AH46-AH37-AH39-AH26+AH27 -> 0.57661521 | AI47: =AI35-AI33-AI46-AI37-AI39-AI26+AI27 -> 0.91712927
B48: 投资回报率 | C48: =F48 -> -0.25538842 | E48: 投资回报率 | F48: =SUM(F47:S47)/F22 -> -0.25538842 | U48: IRR | V48: =IRR(V47:AI47) -> 0.023663328
B49: 放电补贴（元/kWh) | C49: 0

Sheet 表后_现货价差中
B1: xxx | C1: M2访谈数据/Assumption
B2: xxx | C2: 引用数据
B3: xxx | C3: 计算所得数据
C4: 自变量 | D4: *表后用户侧储能主要通过现货形式进行峰谷套利，收益部分由峰负荷时的用户分摊
C5: 支出项 | D5: 关键假设：
C6: 收入项 | D6: 1）电池充放电循环次数~6525次
D7: 2）PCS成本：0.21元/W；电池充放电循环次数~6525次；容量型储能电站运维费用：0.1%；PCS效率：98%；线损：98%；系统使用天数：350天；充放循环次数（1次为1充1放）(次/天）：1次
B8: 更新处：标绿色的单元格 | D8: 3）充放策略：一充一放（1*谷-1*峰）
B11: 基本数据 | E11: 计算结果
B12: 充放策略：一充一放（1*谷-1*峰） | E12: LCOS（元/kWh) | F12: =F43 -> 0.65629663
B13: 谷 | C13: 1 | E13: 投资回报率 | F13: =F48 -> -0.25538842
B14: 平 | C14: 0 | E14: NPV(折现率=7%） | F14: =SUM(F47:O47) -> -3.1165991 | H14: 价差为0.65时： | I14: 0.063152031
B15: 峰 | C15: =C13+C14 -> 1 | E15: IRR | F15: =V48 -> 0.023663328 | H15: 价差为0.6时： | I15: 0.051605782
B16: 基本数据 | E16: 折现率 | F16: 0.07 | H16: 价差为0.55时： | I16: 0.039722393 | U16: 折现率 | V16: 0
B17: PCS(KW） | C17: 1200 | E17: 所得税率 | F17: 0.25 | U17: 所得税率 | V17: 0.25
B18: PCS成本（元/kW) | C18: 210 | E18: 增值税率 | F18: 0 | G18: 暂不考虑 | U18: 增值税率 | V18: 0 | W18: 暂不考虑
B19: ESS(KWh) | C19: 4800 | E19: 储能系统经济效益估算表（元） | U19: 储能系统经济效益估算表（元）
B20: ESS成本（元/kWh) | C20: 1400 | E20: 储能平准化成本LCOS（Levelized Cost of Storage） | G20: 1 | H20: 2 | I20: 3 | J20: 4 | K20: 5 | L20: 6 | M20: 7 | N20: 8 | O20: 9 | P20: 10 | Q20: 11 | R20: 12 | S20: 13 | U20: 储能平准化成本LCOS（Levelized Cost of Storage） | W20: 1 | X20: 2 | Y20: 3 | Z20: 4 | AA20: 5 | AB20: 6 | AC20: 7 | AD20: 8 | AE20: 9 | AF20: 10 | AG20: 11 | AH20: 12 | AI20: 13
B21: PCS效率 | C21: 0.98 | F21: 基准年 | G21: 第1年 | H21: 第2年 | I21: 第3年 | J21: 第4年 | K21: 第5年 | L21: 第6年 | M21: 第7年 | N21: 第8年 | O21: 第9年 | P21: 第10年 | Q21: 第11年 | R21: 第12年 | S21: 第13年 | V21: 基准年 | W21: 第1年 | X21: 第2年 | Y21: 第3年 | Z21: 第4年 | AA21: 第5年 | AB21: 第6年 | AC21: 第7年 | AD21: 第8年 | AE21: 第9年 | AF21: 第10年 | AG21: 第11年 | AH21: 第12年 | AI21: 第13年
B22: 线损 | C22: 0.98 | E22: 初始投资成本（Mn RMB） | F22: =C46/1000000 -> 7.442 | U22: 初始投资成本（Mn RMB） | V22: =C46/1000000 -> 7.442
B23: 峰价（元/KWh) | C23: 0.6 | E23: 折旧现值和（Mn RMB） | F23: =SUM(G24:S24) -> 3.1183056 | U23: 折旧现值和（Mn RMB） | V23: =SUM(W24:AI24) -> 4.8504028
B24: 平价（元/KWh) | C24: 0 | E24: 折旧现值（Mn RMB） | G24: =($C$41+$C$42+$C$32)*(1-$C$35)/$C$40/1000000/(1+$F$16)^G20 -> 0.34869898 | H24: =($C$41+$C$42+$C$32)*(1-$C$35)/$C$40/1000000/(1+$F$16)^H20 -> 0.3258869 | I24: =($C$41+$C$42+$C$32)*(1-$C$35)/$C$40/1000000/(1+$F$16)^I20 -> 0.30456719 | J24: =($C$41+$C$42+$C$32)*(1-$C$35)/$C$40/1000000/(1+$F$16)^J20 -> 0.28464224 | K24: =($C$41+$C$42+$C$32)*(1-$C$35)/$C$40/1000000/(1+$F$16)^K20 -> 0.26602078 | L24: =($C$41+$C$42+$C$32)*(1-$C$35)/$C$40/1000000/(1+$F$16)^L20 -> 0.24861755 | M24: =($C$41+$C$42+$C$32)*(1-$C$35)/$C$40/1000000/(1+$F$16)^M20 -> 0.23235285 | N24: =($C$41+$C$42+$C$32)*(1-$C$35)/$C$40/1000000/(1+$F$16)^N20 -> 0.2171522 | ... S24: =($C$41+$C$42+$C$32)*(1-$C$35)/$C$40/1000000/(1+$F$16)^S20 -> 0.15482652 | U24: 折旧现值（Mn RMB） | W24: =($C$41+$C$42+$C$32)*(1-$C$35)/$C$40/1000000/(1+$V$16)^W20 -> 0.37310791 | X24: =($C$41+$C$42+$C$32)*(1-$C$35)/$C$40/1000000/(1+$V$16)^X20 -> 0.37310791 | Y24: =($C$41+$C$42+$C$32)*(1-$C$35)/$C$40/1000000/(1+$V$16)^Y20 -> 0.37310791 | Z24: =($C$41+$C$42+$C$32)*(1-$C$35)/$C$40/1000000/(1+$V$16)^Z20 -> 0.37310791 | AA24: =($C$41+$C$42+$C$32)*(1-$C$35)/$C$40/1000000/(1+$V$16)^AA20 -> 0.37310791 | AB24: =($C$41+$C$42+$C$32)*(1-$C$35)/$C$40/1000000/(1+$V$16)^AB20 -> 0.37310791 | AC24: =($C$41+$C$42+$C$32)*(1-$C$35)/$C$40/1000000/(1+$V$16)^AC20 -> 0.37310791 | AD24: =($C$41+$C$42+$C$32)*(1-$C$35)/$C$40/1000000/(1+$V$16)^AD20 -> 0.37310791 | ... AI24: =($C$41+$C$42+$C$32)*(1-$C$35)/$C$40/1000000/(1+$V$16)^AI20 -> 0.37310791
B25: 谷价（元/KWh) | C25: 0 | E25: 运行成本现值和（Mn RMB） | F25: =SUM(G26:S26) -> 0.062197637 | U25: 运行成本现值和（Mn RMB） | V25: =SUM(W26:AI26) -> 0.096746
B26: 系统年使用天数 (天) | C26: 350 | E26: 运行成本现值（Mn RMB） | G26: =($C$34*$F$22)/((1+$F$16)^G20) -> 0.0069551402 | H26: =($C$34*$F$22)/((1+$F$16)^H20) -> 0.006500131 | I26: =($C$34*$F$22)/((1+$F$16)^I20) -> 0.0060748888 | J26: =($C$34*$F$22)/((1+$F$16)^J20) -> 0.0056774662 | K26: =($C$34*$F$22)/((1+$F$16)^K20) -> 0.0053060431 | L26: =($C$34*$F$22)/((1+$F$16)^L20) -> 0.0049589188 | M26: =($C$34*$F$22)/((1+$F$16)^M20) -> 0.0046345036 | N26: =($C$34*$F$22)/((1+$F$16)^N20) -> 0.0043313118 | ... S26: =($C$34*$F$22)/((1+$F$16)^S20) -> 0.0030881654 | U26: 运行成本现值（Mn RMB） | W26: =($C$34*$V$22)/((1+$V$16)^W20) -> 0.007442 | X26: =($C$34*$V$22)/((1+$V$16)^X20) -> 0.007442 | Y26: =($C$34*$V$22)/((1+$V$16)^Y20) -> 0.007442 | Z26: =($C$34*$V$22)/((1+$V$16)^Z20) -> 0.007442 | AA26: =($C$34*$V$22)/((1+$V$16)^AA20) -> 0.007442 | AB26: =($C$34*$V$22)/((1+$V$16)^AB20) -> 0.007442 | AC26: =($C$34*$V$22)/((1+$V$16)^AC20) -> 0.007442 | AD26: =($C$34*$V$22)/((1+$V$16)^AD20) -> 0.007442 | ... AI26: =($C$34*$V$22)/((1+$V$16)^AI20) -> 0.007442
B27: DOD% | C27: 0.95 | E27: 固定资产残值现值 (Mn RMB) | S27: =(C41+C42)*C35/((1+F16)^S20)/1000000 -> 0.14465661 | U27: 固定资产残值现值 (Mn RMB) | AI27: =(C41+C42)*C35/((1+V16)^AI20)/1000000 -> 0.3486
B28: 单次循环衰减率 | C28: 4.68e-05 | E28: 充电电量现值和(KWh) | F28: =SUM(G29:S29) -> 13339597 | U28: 充电电量现值和(KWh) | V28: =SUM(W29:AI29) -> 20435477
B29: 系统报废终止标准 | C29: 0.7 | E29: 充电电量现值(KWh) | G29: =$C$19*$C$36*$C$26/$C$37*($C$27*(1-$C$28)^((G20-1)*$C$26*$C$36))/$C$21/$C$22/((1+$F$16)^G20) -> 1617803.3 | H29: =$C$19*$C$36*$C$26/$C$37*($C$27*(1-$C$28)^((H20-1)*$C$26*$C$36))/$C$21/$C$22/((1+$F$16)^H20) -> 1487400.9 | I29: =$C$19*$C$36*$C$26/$C$37*($C$27*(1-$C$28)^((I20-1)*$C$26*$C$36))/$C$21/$C$22/((1+$F$16)^I20) -> 1367509.5 | J29: =$C$19*$C$36*$C$26/$C$37*($C$27*(1-$C$28)^((J20-1)*$C$26*$C$36))/$C$21/$C$22/((1+$F$16)^J20) -> 1257281.9 | K29: =$C$19*$C$36*$C$26/$C$37*($C$27*(1-$C$28)^((K20-1)*$C$26*$C$36))/$C$21/$C$22/((1+$F$16)^K20) -> 1155939.2 | L29: =$C$19*$C$36*$C$26/$C$37*($C$27*(1-$C$28)^((L20-1)*$C$26*$C$36))/$C$21/$C$22/((1+$F$16)^L20) -> 1062765.1 | M29: =$C$19*$C$36*$C$26/$C$37*($C$27*(1-$C$28)^((M20-1)*$C$26*$C$36))/$C$21/$C$22/((1+$F$16)^M20) -> 977101.32 | N29: =$C$19*$C$36*$C$26/$C$37*($C$27*(1-$C$28)^((N20-1)*$C$26*$C$36))/$C$21/$C$22/((1+$F$16)^N20) -> 898342.43 | ... S29: =$C$19*$C$36*$C$26/$C$37*($C$27*(1-$C$28)^((S20-1)*$C$26*$C$36))/$C$21/$C$22/((1+$F$16)^S20) -> 590137.85 | U29: 充电电量现值(KWh) | W29: =$C$19*$C$36*$C$26/$C$37*($C$27*(1-$C$28)^((W20-1)*$C$26*$C$36))/$C$21/$C$22/((1+$V$16)^W20) -> 1731049.6 | X29: =$C$19*$C$36*$C$26/$C$37*($C$27*(1-$C$28)^((X20-1)*$C$26*$C$36))/$C$21/$C$22/((1+$V$16)^X20) -> 1702925.3 | Y29: =$C$19*$C$36*$C$26/$C$37*($C$27*(1-$C$28)^((Y20-1)*$C$26*$C$36))/$C$21/$C$22/((1+$V$16)^Y20) -> 1675257.9 | Z29: =$C$19*$C$36*$C$26/$C$37*($C$27*(1-$C$28)^((Z20-1)*$C$26*$C$36))/$C$21/$C$22/((1+$V$16)^Z20) -> 1648040.1 | AA29: =$C$19*$C$36*$C$26/$C$37*($C$27*(1-$C$28)^((AA20-1)*$C$26*$C$36))/$C$21/$C$22/((1+$V$16)^AA20) -> 1621264.5 | AB29: =$C$19*$C$36*$C$26/$C$37*($C$27*(1-$C$28)^((AB20-1)*$C$26*$C$36))/$C$21/$C$22/((1+$V$16)^AB20) -> 1594923.8 | AC29: =$C$19*$C$36*$C$26/$C$37*($C$27*(1-$C$28)^((AC20-1)*$C$26*$C$36))/$C$21/$C$22/((1+$V$16)^AC20) -> 1569011.2 | AD29: =$C$19*$C$36*$C$26/$C$37*($C$27*(1-$C$28)^((AD20-1)*$C$26*$C$36))/$C$21/$C$22/((1+$V$16)^AD20) -> 1543519.5 | ... AI29: =$C$19*$C$36*$C$26/$C$37*($C$27*(1-$C$28)^((AI20-1)*$C$26*$C$36))/$C$21/$C$22/((1+$V$16)^AI20) -> 1422140.8
B30: 土建成本(元/Wh) | C30: 0.015 | E30: 放电电量现值和(KWh) | F30: =SUM(G31:S31) -> 11339385 | U30: 放电电量现值和(KWh) | V30: =SUM(W31:AI31) -> 17371269
B31: 土建残值率（%） | C31: 0 | E31: 放电电量现值(KWh) | G31: =$C$19*$C$36*$C$26*$C$37*($C$27*(1-$C$28)^((G20-1)*$C$26*$C$36))*$C$21*$C$22/((1+$F$16)^G20) -> 1375221 | H31: =$C$19*$C$36*$C$26*$C$37*($C$27*(1-$C$28)^((H20-1)*$C$26*$C$36))*$C$21*$C$22/((1+$F$16)^H20) -> 1264371.8 | I31: =$C$19*$C$36*$C$26*$C$37*($C$27*(1-$C$28)^((I20-1)*$C$26*$C$36))*$C$21*$C$22/((1+$F$16)^I20) -> 1162457.6 | J31: =$C$19*$C$36*$C$26*$C$37*($C$27*(1-$C$28)^((J20-1)*$C$26*$C$36))*$C$21*$C$22/((1+$F$16)^J20) -> 1068758.1 | K31: =$C$19*$C$36*$C$26*$C$37*($C$27*(1-$C$28)^((K20-1)*$C$26*$C$36))*$C$21*$C$22/((1+$F$16)^K20) -> 982611.27 | L31: =$C$19*$C$36*$C$26*$C$37*($C$27*(1-$C$28)^((L20-1)*$C$26*$C$36))*$C$21*$C$22/((1+$F$16)^L20) -> 903408.26 | M31: =$C$19*$C$36*$C$26*$C$37*($C$27*(1-$C$28)^((M20-1)*$C$26*$C$36))*$C$21*$C$22/((1+$F$16)^M20) -> 830589.37 | N31: =$C$19*$C$36*$C$26*$C$37*($C$27*(1-$C$28)^((N20-1)*$C$26*$C$36))*$C$21*$C$22/((1+$F$16)^N20) -> 763640.02 | ... S31: =$C$19*$C$36*$C$26*$C$37*($C$27*(1-$C$28)^((S20-1)*$C$26*$C$36))*$C$21*$C$22/((1+$F$16)^S20) -> 501649.33 | U31: 放电电量现值(KWh) | W31: =$C$19*$C$36*$C$26*$C$37*($C$27*(1-$C$28)^((W20-1)*$C$26*$C$36))*$C$21*$C$22/((1+$V$16)^W20) -> 1471486.5 | X31: =$C$19*$C$36*$C$26*$C$37*($C$27*(1-$C$28)^((X20-1)*$C$26*$C$36))*$C$21*$C$22/((1+$V$16)^X20) -> 1447579.3 | Y31: =$C$19*$C$36*$C$26*$C$37*($C$27*(1-$C$28)^((Y20-1)*$C$26*$C$36))*$C$21*$C$22/((1+$V$16)^Y20) -> 1424060.5 | Z31: =$C$19*$C$36*$C$26*$C$37*($C$27*(1-$C$28)^((Z20-1)*$C$26*$C$36))*$C$21*$C$22/((1+$V$16)^Z20) -> 1400923.9 | AA31: =$C$19*$C$36*$C$26*$C$37*($C$27*(1-$C$28)^((AA20-1)*$C$26*$C$36))*$C$21*$C$22/((1+$V$16)^AA20) -> 1378163.1 | AB31: =$C$19*$C$36*$C$26*$C$37*($C$27*(1-$C$28)^((AB20-1)*$C$26*$C$36))*$C$21*$C$22/((1+$V$16)^AB20) -> 1355772.2 | AC31: =$C$19*$C$36*$C$26*$C$37*($C$27*(1-$C$28)^((AC20-1)*$C$26*$C$36))*$C$21*$C$22/((1+$V$16)^AC20) -> 1333745 | AD31: =$C$19*$C$36*$C$26*$C$37*($C$27*(1-$C$28)^((AD20-1)*$C$26*$C$36))*$C$21*$C$22/((1+$V$16)^AD20) -> 1312075.7 | ... AI31: =$C$19*$C$36*$C$26*$C$37*($C$27*(1-$C$28)^((AI20-1)*$C$26*$C$36))*$C$21*$C$22/((1+$V$16)^AI20) -> 1208897.1
B32: 其它设备投资费用（升压变等） | C32: 350000 | E32: 充电成本现值和（Mn RMB） | F32: =SUM(G33:S33) -> 0 | U32: 充电成本现值和（Mn RMB） | V32: =SUM(W33:AI33) -> 0
B33: 其它成本：入网检测费、项目管理费等（元/Wh） | C33: 0.01 | E33: 充电成本现值（Mn RMB） | G33: =($C$13*$C$25*G29/($C$13+$C$14)+$C$14*$C$24*G29/($C$13+$C$14))/1000000 -> 0 | H33: =($C$13*$C$25*H29/($C$13+$C$14)+$C$14*$C$24*H29/($C$13+$C$14))/1000000 -> 0 | I33: =($C$13*$C$25*I29/($C$13+$C$14)+$C$14*$C$24*I29/($C$13+$C$14))/1000000 -> 0 | J33: =($C$13*$C$25*J29/($C$13+$C$14)+$C$14*$C$24*J29/($C$13+$C$14))/1000000 -> 0 | K33: =($C$13*$C$25*K29/($C$13+$C$14)+$C$14*$C$24*K29/($C$13+$C$14))/1000000 -> 0 | L33: =($C$13*$C$25*L29/($C$13+$C$14)+$C$14*$C$24*L29/($C$13+$C$14))/1000000 -> 0 | M33: =($C$13*$C$25*M29/($C$13+$C$14)+$C$14*$C$24*M29/($C$13+$C$14))/1000000 -> 0 | N33: =($C$13*$C$25*N29/($C$13+$C$14)+$C$14*$C$24*N29/($C$13+$C$14))/1000000 -> 0 | ... S33: =($C$13*$C$25*S29/($C$13+$C$14)+$C$14*$C$24*S29/($C$13+$C$14))/1000000 -> 0 | U33: 充电成本现值（Mn RMB） | W33: =($C$13*$C$25*W29/($C$13+$C$14)+$C$14*$C$24*W29/($C$13+$C$14))/1000000 -> 0 | X33: =($C$13*$C$25*X29/($C$13+$C$14)+$C$14*$C$24*X29/($C$13+$C$14))/1000000 -> 0 | Y33: =($C$13*$C$25*Y29/($C$13+$C$14)+$C$14*$C$24*Y29/($C$13+$C$14))/1000000 -> 0 | Z33: =($C$13*$C$25*Z29/($C$13+$C$14)+$C$14*$C$24*Z29/($C$13+$C$14))/1000000 -> 0 | AA33: =($C$13*$C$25*AA29/($C$13+$C$14)+$C$14*$C$24*AA29/($C$13+$C$14))/1000000 -> 0 | AB33: =($C$13*$C$25*AB29/($C$13+$C$14)+$C$14*$C$24*AB29/($C$13+$C$14))/1000000 -> 0 | AC33: =($C$13*$C$25*AC29/($C$13+$C$14)+$C$14*$C$24*AC29/($C$13+$C$14))/1000000 -> 0 | AD33: =($C$13*$C$25*AD29/($C$13+$C$14)+$C$14*$C$24*AD29/($C$13+$C$14))/1000000 -> 0 | ... AI33: =($C$13*$C$25*AI29/($C$13+$C$14)+$C$14*$C$24*AI29/($C$13+$C$14))/1000000 -> 0
B34: 容量型储能电站运维费用 | C34: 0.001 | E34: 放电收益现值和（Mn RMB） | F34: =SUM(G35:S35) -> 6.8036309 | U34: 放电收益现值和（Mn RMB） | V34: =SUM(W35:AI35) -> 10.422762
B35: 储能系统残值 | C35: 0.05 | E35: 放电收益现值（Mn RMB） | G35: =G31*$C$23/1000000 -> 0.8251326 | H35: =H31*$C$23/1000000 -> 0.75862309 | I35: =I31*$C$23/1000000 -> 0.69747456 | J35: =J31*$C$23/1000000 -> 0.64125488 | K35: =K31*$C$23/1000000 -> 0.58956676 | L35: =L31*$C$23/1000000 -> 0.54204495 | M35: =M31*$C$23/1000000 -> 0.49835362 | N35: =N31*$C$23/1000000 -> 0.45818401 | ... S35: =S31*$C$23/1000000 -> 0.3009896 | U35: 放电收益现值（Mn RMB） | W35: =W31*$C$23/1000000 -> 0.88289188 | X35: =X31*$C$23/1000000 -> 0.86854757 | Y35: =Y31*$C$23/1000000 -> 0.85443632 | Z35: =Z31*$C$23/1000000 -> 0.84055433 | AA35: =AA31*$C$23/1000000 -> 0.82689789 | AB35: =AB31*$C$23/1000000 -> 0.81346331 | AC35: =AC31*$C$23/1000000 -> 0.80024701 | AD35: =AD31*$C$23/1000000 -> 0.78724544 | ... AI35: =AI31*$C$23/1000000 -> 0.72533828
B36: 充放循环次数（1次为1充1放）(次/天） | C36: =C13+C14 -> 1 | E36: 所得税现值和（Mn RMB） | F36: =SUM(G37:S37) -> 0.90578192 | U36: 所得税现值和（Mn RMB） | V36: =SUM(W37:AI37) -> 1.3689032
B37: 充放电效率RTE（%） | C37: 0.96 | E37: 所得税现值（Mn RMB） | G37: =(G35-G33-G26-G24)*$F$17 -> 0.11736962 | H37: =(H35-H33-H26-H24)*$F$17 -> 0.10655902 | I37: =(I35-I33-I26-I24)*$F$17 -> 0.096708118 | J37: =(J35-J33-J26-J24)*$F$17 -> 0.087733794 | K37: =(K35-K33-K26-K24)*$F$17 -> 0.079559985 | L37: =(L35-L33-L26-L24)*$F$17 -> 0.07211712 | M37: =(M35-M33-M26-M24)*$F$17 -> 0.065341566 | N37: =(N35-N33-N26-N24)*$F$17 -> 0.059175125 | ... S37: =(S35-S33-S26-S24)*$F$17 -> 0.03576873 | U37: 所得税现值（Mn RMB） | W37: =(W35-W33-W26-W24)*$V$17 -> 0.12558549 | X37: =(X35-X33-X26-X24)*$V$17 -> 0.12199942 | Y37: =(Y35-Y33-Y26-Y24)*$V$17 -> 0.1184716 | Z37: =(Z35-Z33-Z26-Z24)*$V$17 -> 0.11500111 | AA37: =(AA35-AA33-AA26-AA24)*$V$17 -> 0.11158699 | AB37: =(AB35-AB33-AB26-AB24)*$V$17 -> 0.10822835 | AC37: =(AC35-AC33-AC26-AC24)*$V$17 -> 0.10492428 | AD37: =(AD35-AD33-AD26-AD24)*$V$17 -> 0.10167388 | ... AI37: =(AI35-AI33-AI26-AI24)*$V$17 -> 0.086197094
B38: 用户分成比例（%） | C38: 0.1 | E38: 增值税现值和（Mn RMB） | F38: =SUM(G39:S39) -> 0 | U38: 增值税现值和（Mn RMB） | V38: =SUM(W39:AI39) -> 0
B39: 充放循环总次数（次数） | C39: =LOG(C29/C27,(1-C28)) -> 6525.0962 | E39: 增值税现值（Mn RMB） | G39: =(G35-G33)*$F$18 -> 0 | H39: =(H35-H33)*$F$18 -> 0 | I39: =(I35-I33)*$F$18 -> 0 | J39: =(J35-J33)*$F$18 -> 0 | K39: =(K35-K33)*$F$18 -> 0 | L39: =(L35-L33)*$F$18 -> 0 | M39: =(M35-M33)*$F$18 -> 0 | N39: =(N35-N33)*$F$18 -> 0 | ... S39: =(S35-S33)*$F$18 -> 0 | U39: 增值税现值（Mn RMB） | W39: =(W35-W33)*$V$18 -> 0 | X39: =(X35-X33)*$V$18 -> 0 | Y39: =(Y35-Y33)*$V$18 -> 0 | Z39: =(Z35-Z33)*$V$18 -> 0 | AA39: =(AA35-AA33)*$V$18 -> 0 | AB39: =(AB35-AB33)*$V$18 -> 0 | AC39: =(AC35-AC33)*$V$18 -> 0 | AD39: =(AD35-AD33)*$V$18 -> 0 | ... AI39: =(AI35-AI33)*$V$18 -> 0
B40: 系统寿命（年） | C40: =C39/C36/C26 -> 18.643132 | E40: 放电利润现值和（Mn RMB） | F40: =SUM(G41:S41) -> 5.8356513 | U40: 放电利润现值和（Mn RMB） | V40: =SUM(W41:AI41) -> 8.9571124
B41: PCS总成本（元） | C41: =C18*C17 -> 252000 | E41: 放电利润现值和（Mn RMB） | G41: =G35-G33-G37-G39-G26 -> 0.70080784 | H41: =H35-H33-H37-H39-H26 -> 0.64556394 | I41: =I35-I33-I37-I39-I26 -> 0.59469155 | J41: =J35-J33-J37-J39-J26 -> 0.54784362 | K41: =K35-K33-K37-K39-K26 -> 0.50470074 | L41: =L35-L33-L37-L39-L26 -> 0.46496891 | M41: =M35-M33-M37-M39-M26 -> 0.42837755 | N41: =N35-N33-N37-N39-N26 -> 0.39467757 | ... S41: =S35-S33-S37-S39-S26 -> 0.26213271 | U41: 放电利润现值和（Mn RMB） | W41: =W35-W33-W37-W39-W26 -> 0.74986439 | X41: =X35-X33-X37-X39-X26 -> 0.73910616 | Y41: =Y35-Y33-Y37-Y39-Y26 -> 0.72852272 | Z41: =Z35-Z33-Z37-Z39-Z26 -> 0.71811123 | AA41: =AA35-AA33-AA37-AA39-AA26 -> 0.70786889 | AB41: =AB35-AB33-AB37-AB39-AB26 -> 0.69779296 | AC41: =AC35-AC33-AC37-AC39-AC26 -> 0.68788074 | AD41: =AD35-AD33-AD37-AD39-AD26 -> 0.67812955 | ... AI41: =AI35-AI33-AI37-AI39-AI26 -> 0.63169919
B42: ESS总成本（元） | C42: =C19*C20 -> 6720000 | E42: 度电收益（元/kWh) | F42: =C23 -> 0.6 | U42: 度电收益（元/kWh) | V42: =C23 -> 0.6
B43: 土建总投资（元） | C43: =C30*C19*1000 -> 72000 | E43: LCOS（元/kWh) | F43: =F22/F30*1000000 -> 0.65629663 | U43: LCOS（元/kWh) | V43: =V22/V30*1000000 -> 0.42840853
B44: 其它投资（元） | C44: =C33*C19*1000 -> 48000 | E44: 充电成本（元/kWh) | F44: =F32*1000000/F30 -> 0 | U44: 充电成本（元/kWh) | V44: =V32*1000000/V30 -> 0
B45: 设备购置补助（元） | C45: 0 | E45: 用户分成部分（元/kWh) | F45: =SUM(G46:O46) -> 0.46452714 | U45: 用户分成部分（元/kWh) | V45: =SUM(W46:AI46) -> 0.89571124
B46: 设备总投资（元） | C46: =(C44+C43+C42+C41+C32-C45) -> 7442000 | E46: 用户分成部分现值 | G46: =G41*$C$38 -> 0.070080784 | H46: =H41*$C$38 -> 0.064556394 | I46: =I41*$C$38 -> 0.059469155 | J46: =J41*$C$38 -> 0.054784362 | K46: =K41*$C$38 -> 0.050470074 | L46: =L41*$C$38 -> 0.046496891 | M46: =M41*$C$38 -> 0.042837755 | N46: =N41*$C$38 -> 0.039467757 | ... S46: =S41*$C$38 -> 0.026213271 | U46: 用户分成部分现值 | W46: =W41*$C$38 -> 0.074986439 | X46: =X41*$C$38 -> 0.073910616 | Y46: =Y41*$C$38 -> 0.072852272 | Z46: =Z41*$C$38 -> 0.071811123 | AA46: =AA41*$C$38 -> 0.070786889 | AB46: =AB41*$C$38 -> 0.069779296 | AC46: =AC41*$C$38 -> 0.068788074 | AD46: =AD41*$C$38 -> 0.067812955 | ... AI46: =AI41*$C$38 -> 0.063169919
B47: 投资回收年限 | C47: 9+ | E47: NPV | F47: =-(F22) -> -7.442 | G47: =G35-G33-G46-G37-G39-G26 -> 0.63072705 | H47: =H35-H33-H46-H37-H39-H26 -> 0.58100755 | I47: =I35-I33-I46-I37-I39-I26 -> 0.53522239 | J47: =J35-J33-J46-J37-J39-J26 -> 0.49305926 | K47: =K35-K33-K46-K37-K39-K26 -> 0.45423066 | L47: =L35-L33-L46-L37-L39-L26 -> 0.41847202 | M47: =M35-M33-M46-M37-M39-M26 -> 0.3855398 | N47: =N35-N33-N46-N37-N39-N26 -> 0.35520982 | O47: =O35-O33-O46-O37-O39-O26+S27 -> 0.47193236 | P47: =P35-P33-P46-P37-P39-P26+P27 -> 0.30154767 | Q47: =Q35-Q33-Q46-Q37-Q39-Q26+Q27 -> 0.27785074 | R47: =R35-R33-R46-R37-R39-R26+R27 -> 0.25602405 | S47: =S35-S33-S46-S37-S39-S26+S27 -> 0.38057604 | U47: NPV | V47: =-(V22) -> -7.442 | W47: =W35-W33-W46-W37-W39-W26 -> 0.67487795 | X47: =X35-X33-X46-X37-X39-X26 -> 0.66519554 | Y47: =Y35-Y33-Y46-Y37-Y39-Y26 -> 0.65567045 | Z47: =Z35-Z33-Z46-Z37-Z39-Z26 -> 0.6463001 | AA47: =AA35-AA33-AA46-AA37-AA39-AA26 -> 0.637082 | AB47: =AB35-AB33-AB46-AB37-AB39-AB26 -> 0.62801367 | AC47: =AC35-AC33-AC46-AC37-AC39-AC26 -> 0.61909266 | AD47: =AD35-AD33-AD46-AD37-AD39-AD26 -> 0.6103166 | AE47: =AE35-AE33-AE46-AE37-AE39-AE26+AI27 -> 0.95028312 | AF47: =AF35-AF33-AF46-AF37-AF39-AF26+AF27 -> 0.59318991 | AG47: =AG35-AG33-AG46-AG37-AG39-AG26+AG27 -> 0.58483468 | AH47: =AH35-AH33-AH46-AH37-AH39-AH26+AH27 -> 0.57661521 | AI47: =AI35-AI33-AI46-AI37-AI39-AI26+AI27 -> 0.91712927
B48: 投资回报率 | C48: =F48 -> -0.25538842 | E48: 投资回报率 | F48: =SUM(F47:S47)/F22 -> -0.25538842 | U48: IRR | V48: =IRR(V47:AI47) -> 0.023663328
B49: 放电补贴（元/kWh) | C49: 0
D53: =5280/6002 -> 0.87970676

Sheet 表后_现货价差低
B1: xxx | C1: M2访谈数据/Assumption
B2: xxx | C2: 引用数据
B3: xxx | C3: 计算所得数据
C4: 自变量 | D4: *表后用户侧储能主要通过现货形式进行峰谷套利，收益部分由峰负荷时的用户分摊
C5: 支出项 | D5: 关键假设：
C6: 收入项 | D6: 1）电池充放电循环次数~6525次
D7: 2）PCS成本：0.21元/W；电池充放电循环次数~6525次；容量型储能电站运维费用：0.1%；PCS效率：98%；线损：98%；系统使用天数：350天；充放循环次数（1次为1充1放）(次/天）：1次
B8: 更新处：标绿色的单元格 | D8: 3）充放策略：一充一放（1*谷-1*峰）
B11: 基本数据 | E11: 计算结果
B12: 充放策略：一充一放（1*谷-1*峰） | E12: LCOS（元/kWh) | F12: =F43 -> 0.52930561
B13: 谷 | C13: 1 | E13: 投资回报率 | F13: =F48 -> -0.49091018
B14: 平 | C14: 0 | E14: NPV(折现率=7%） | F14: =SUM(F47:O47) -> -3.6409726 | H14: 价差为0.45时： | I14: 0.014741147
B15: 峰 | C15: =C13+C14 -> 1 | E15: IRR | F15: =V48 -> -0.026870407 | H15: 价差为0.3时： | I15: -0.026870407
B16: 基本数据 | E16: 折现率 | F16: 0.07 | U16: 折现率 | V16: 0
B17: PCS(KW） | C17: 1200 | E17: 所得税率 | F17: 0.25 | U17: 所得税率 | V17: 0.25
B18: PCS成本（元/kW) | C18: 210 | E18: 增值税率 | F18: 0 | G18: 暂不考虑 | U18: 增值税率 | V18: 0 | W18: 暂不考虑
B19: ESS(KWh) | C19: 4800 | E19: 储能系统经济效益估算表（元） | U19: 储能系统经济效益估算表（元）
B20: ESS成本（元/kWh) | C20: 1100 | E20: 储能平准化成本LCOS（Levelized Cost of Storage） | G20: 1 | H20: 2 | I20: 3 | J20: 4 | K20: 5 | L20: 6 | M20: 7 | N20: 8 | O20: 9 | P20: 10 | Q20: 11 | R20: 12 | S20: 13 | U20: 储能平准化成本LCOS（Levelized Cost of Storage） | W20: 1 | X20: 2 | Y20: 3 | Z20: 4 | AA20: 5 | AB20: 6 | AC20: 7 | AD20: 8 | AE20: 9 | AF20: 10 | AG20: 11 | AH20: 12 | AI20: 13
B21: PCS效率 | C21: 0.98 | F21: 基准年 | G21: 第1年 | H21: 第2年 | I21: 第3年 | J21: 第4年 | K21: 第5年 | L21: 第6年 | M21: 第7年 | N21: 第8年 | O21: 第9年 | P21: 第10年 | Q21: 第11年 | R21: 第12年 | S21: 第13年 | V21: 基准年 | W21: 第1年 | X21: 第2年 | Y21: 第3年 | Z21: 第4年 | AA21: 第5年 | AB21: 第6年 | AC21: 第7年 | AD21: 第8年 | AE21: 第9年 | AF21: 第10年 | AG21: 第11年 | AH21: 第12年 | AI21: 第13年
B22: 线损 | C22: 0.98 | E22: 初始投资成本（Mn RMB） | F22: =C46/1000000 -> 6.002 | U22: 初始投资成本（Mn RMB） | V22: =C46/1000000 -> 6.002
B23: 峰价（元/KWh) | C23: 0.3 | E23: 折旧现值和（Mn RMB） | F23: =SUM(G24:S24) -> 2.505036 | U23: 折旧现值和（Mn RMB） | V23: =SUM(W24:AI24) -> 3.8964858
B24: 平价（元/KWh) | C24: 0 | E24: 折旧现值（Mn RMB） | G24: =($C$41+$C$42+$C$32)*(1-$C$35)/$C$40/1000000/(1+$F$16)^G20 -> 0.2801212 | H24: =($C$41+$C$42+$C$32)*(1-$C$35)/$C$40/1000000/(1+$F$16)^H20 -> 0.26179551 | I24: =($C$41+$C$42+$C$32)*(1-$C$35)/$C$40/1000000/(1+$F$16)^I20 -> 0.2446687 | J24: =($C$41+$C$42+$C$32)*(1-$C$35)/$C$40/1000000/(1+$F$16)^J20 -> 0.22866234 | K24: =($C$41+$C$42+$C$32)*(1-$C$35)/$C$40/1000000/(1+$F$16)^K20 -> 0.21370312 | L24: =($C$41+$C$42+$C$32)*(1-$C$35)/$C$40/1000000/(1+$F$16)^L20 -> 0.19972254 | M24: =($C$41+$C$42+$C$32)*(1-$C$35)/$C$40/1000000/(1+$F$16)^M20 -> 0.18665658 | N24: =($C$41+$C$42+$C$32)*(1-$C$35)/$C$40/1000000/(1+$F$16)^N20 -> 0.1744454 | ... S24: =($C$41+$C$42+$C$32)*(1-$C$35)/$C$40/1000000/(1+$F$16)^S20 -> 0.12437716 | U24: 折旧现值（Mn RMB） | W24: =($C$41+$C$42+$C$32)*(1-$C$35)/$C$40/1000000/(1+$V$16)^W20 -> 0.29972968 | X24: =($C$41+$C$42+$C$32)*(1-$C$35)/$C$40/1000000/(1+$V$16)^X20 -> 0.29972968 | Y24: =($C$41+$C$42+$C$32)*(1-$C$35)/$C$40/1000000/(1+$V$16)^Y20 -> 0.29972968 | Z24: =($C$41+$C$42+$C$32)*(1-$C$35)/$C$40/1000000/(1+$V$16)^Z20 -> 0.29972968 | AA24: =($C$41+$C$42+$C$32)*(1-$C$35)/$C$40/1000000/(1+$V$16)^AA20 -> 0.29972968 | AB24: =($C$41+$C$42+$C$32)*(1-$C$35)/$C$40/1000000/(1+$V$16)^AB20 -> 0.29972968 | AC24: =($C$41+$C$42+$C$32)*(1-$C$35)/$C$40/1000000/(1+$V$16)^AC20 -> 0.29972968 | AD24: =($C$41+$C$42+$C$32)*(1-$C$35)/$C$40/1000000/(1+$V$16)^AD20 -> 0.29972968 | ... AI24: =($C$41+$C$42+$C$32)*(1-$C$35)/$C$40/1000000/(1+$V$16)^AI20 -> 0.29972968
B25: 谷价（元/KWh) | C25: 0 | E25: 运行成本现值和（Mn RMB） | F25: =SUM(G26:S26) -> 0.05016262 | U25: 运行成本现值和（Mn RMB） | V25: =SUM(W26:AI26) -> 0.078026
B26: 系统年使用天数 (天) | C26: 350 | E26: 运行成本现值（Mn RMB） | G26: =($C$34*$F$22)/((1+$F$16)^G20) -> 0.0056093458 | H26: =($C$34*$F$22)/((1+$F$16)^H20) -> 0.0052423792 | I26: =($C$34*$F$22)/((1+$F$16)^I20) -> 0.0048994199 | J26: =($C$34*$F$22)/((1+$F$16)^J20) -> 0.0045788971 | K26: =($C$34*$F$22)/((1+$F$16)^K20) -> 0.004279343 | L26: =($C$34*$F$22)/((1+$F$16)^L20) -> 0.003999386 | M26: =($C$34*$F$22)/((1+$F$16)^M20) -> 0.003737744 | N26: =($C$34*$F$22)/((1+$F$16)^N20) -> 0.0034932186 | ... S26: =($C$34*$F$22)/((1+$F$16)^S20) -> 0.0024906166 | U26: 运行成本现值（Mn RMB） | W26: =($C$34*$V$22)/((1+$V$16)^W20) -> 0.006002 | X26: =($C$34*$V$22)/((1+$V$16)^X20) -> 0.006002 | Y26: =($C$34*$V$22)/((1+$V$16)^Y20) -> 0.006002 | Z26: =($C$34*$V$22)/((1+$V$16)^Z20) -> 0.006002 | AA26: =($C$34*$V$22)/((1+$V$16)^AA20) -> 0.006002 | AB26: =($C$34*$V$22)/((1+$V$16)^AB20) -> 0.006002 | AC26: =($C$34*$V$22)/((1+$V$16)^AC20) -> 0.006002 | AD26: =($C$34*$V$22)/((1+$V$16)^AD20) -> 0.006002 | ... AI26: =($C$34*$V$22)/((1+$V$16)^AI20) -> 0.006002
B27: DOD% | C27: 0.95 | E27: 固定资产残值现值 (Mn RMB) | S27: =(C41+C42)*C35/((1+F16)^S20)/1000000 -> 0.11477917 | U27: 固定资产残值现值 (Mn RMB) | AI27: =(C41+C42)*C35/((1+V16)^AI20)/1000000 -> 0.2766
B28: 单次循环衰减率 | C28: 4.68e-05 | E28: 充电电量现值和(KWh) | F28: =SUM(G29:S29) -> 13339597 | U28: 充电电量现值和(KWh) | V28: =SUM(W29:AI29) -> 20435477
B29: 系统报废终止标准 | C29: 0.7 | E29: 充电电量现值(KWh) | G29: =$C$19*$C$36*$C$26/$C$37*($C$27*(1-$C$28)^((G20-1)*$C$26*$C$36))/$C$21/$C$22/((1+$F$16)^G20) -> 1617803.3 | H29: =$C$19*$C$36*$C$26/$C$37*($C$27*(1-$C$28)^((H20-1)*$C$26*$C$36))/$C$21/$C$22/((1+$F$16)^H20) -> 1487400.9 | I29: =$C$19*$C$36*$C$26/$C$37*($C$27*(1-$C$28)^((I20-1)*$C$26*$C$36))/$C$21/$C$22/((1+$F$16)^I20) -> 1367509.5 | J29: =$C$19*$C$36*$C$26/$C$37*($C$27*(1-$C$28)^((J20-1)*$C$26*$C$36))/$C$21/$C$22/((1+$F$16)^J20) -> 1257281.9 | K29: =$C$19*$C$36*$C$26/$C$37*($C$27*(1-$C$28)^((K20-1)*$C$26*$C$36))/$C$21/$C$22/((1+$F$16)^K20) -> 1155939.2 | L29: =$C$19*$C$36*$C$26/$C$37*($C$27*(1-$C$28)^((L20-1)*$C$26*$C$36))/$C$21/$C$22/((1+$F$16)^L20) -> 1062765.1 | M29: =$C$19*$C$36*$C$26/$C$37*($C$27*(1-$C$28)^((M20-1)*$C$26*$C$36))/$C$21/$C$22/((1+$F$16)^M20) -> 977101.32 | N29: =$C$19*$C$36*$C$26/$C$37*($C$27*(1-$C$28)^((N20-1)*$C$26*$C$36))/$C$21/$C$22/((1+$F$16)^N20) -> 898342.43 | ... S29: =$C$19*$C$36*$C$26/$C$37*($C$27*(1-$C$28)^((S20-1)*$C$26*$C$36))/$C$21/$C$22/((1+$F$16)^S20) -> 590137.85 | U29: 充电电量现值(KWh) | W29: =$C$19*$C$36*$C$26/$C$37*($C$27*(1-$C$28)^((W20-1)*$C$26*$C$36))/$C$21/$C$22/((1+$V$16)^W20) -> 1731049.6 | X29: =$C$19*$C$36*$C$26/$C$37*($C$27*(1-$C$28)^((X20-1)*$C$26*$C$36))/$C$21/$C$22/((1+$V$16)^X20) -> 1702925.3 | Y29: =$C$19*$C$36*$C$26/$C$37*($C$27*(1-$C$28)^((Y20-1)*$C$26*$C$36))/$C$21/$C$22/((1+$V$16)^Y20) -> 1675257.9 | Z29: =$C$19*$C$36*$C$26/$C$37*($C$27*(1-$C$28)^((Z20-1)*$C$26*$C$36))/$C$21/$C$22/((1+$V$16)^Z20) -> 1648040.1 | AA29: =$C$19*$C$36*$C$26/$C$37*($C$27*(1-$C$28)^((AA20-1)*$C$26*$C$36))/$C$21/$C$22/((1+$V$16)^AA20) -> 1621264.5 | AB29: =$C$19*$C$36*$C$26/$C$37*($C$27*(1-$C$28)^((AB20-1)*$C$26*$C$36))/$C$21/$C$22/((1+$V$16)^AB20) -> 1594923.8 | AC29: =$C$19*$C$36*$C$26/$C$37*($C$27*(1-$C$28)^((AC20-1)*$C$26*$C$36))/$C$21/$C$22/((1+$V$16)^AC20) -> 1569011.2 | AD29: =$C$19*$C$36*$C$26/$C$37*($C$27*(1-$C$28)^((AD20-1)*$C$26*$C$36))/$C$21/$C$22/((1+$V$16)^AD20) -> 1543519.5 | ... AI29: =$C$19*$C$36*$C$26/$C$37*($C$27*(1-$C$28)^((AI20-1)*$C$26*$C$36))/$C$21/$C$22/((1+$V$16)^AI20) -> 1422140.8
B30: 土建成本(元/Wh) | C30: 0.015 | E30: 放电电量现值和(KWh) | F30: =SUM(G31:S31) -> 11339385 | U30: 放电电量现值和(KWh) | V30: =SUM(W31:AI31) -> 17371269
B31: 土建残值率（%） | C31: 0 | E31: 放电电量现值(KWh) | G31: =$C$19*$C$36*$C$26*$C$37*($C$27*(1-$C$28)^((G20-1)*$C$26*$C$36))*$C$21*$C$22/((1+$F$16)^G20) -> 1375221 | H31: =$C$19*$C$36*$C$26*$C$37*($C$27*(1-$C$28)^((H20-1)*$C$26*$C$36))*$C$21*$C$22/((1+$F$16)^H20) -> 1264371.8 | I31: =$C$19*$C$36*$C$26*$C$37*($C$27*(1-$C$28)^((I20-1)*$C$26*$C$36))*$C$21*$C$22/((1+$F$16)^I20) -> 1162457.6 | J31: =$C$19*$C$36*$C$26*$C$37*($C$27*(1-$C$28)^((J20-1)*$C$26*$C$36))*$C$21*$C$22/((1+$F$16)^J20) -> 1068758.1 | K31: =$C$19*$C$36*$C$26*$C$37*($C$27*(1-$C$28)^((K20-1)*$C$26*$C$36))*$C$21*$C$22/((1+$F$16)^K20) -> 982611.27 | L31: =$C$19*$C$36*$C$26*$C$37*($C$27*(1-$C$28)^((L20-1)*$C$26*$C$36))*$C$21*$C$22/((1+$F$16)^L20) -> 903408.26 | M31: =$C$19*$C$36*$C$26*$C$37*($C$27*(1-$C$28)^((M20-1)*$C$26*$C$36))*$C$21*$C$22/((1+$F$16)^M20) -> 830589.37 | N31: =$C$19*$C$36*$C$26*$C$37*($C$27*(1-$C$28)^((N20-1)*$C$26*$C$36))*$C$21*$C$22/((1+$F$16)^N20) -> 763640.02 | ... S31: =$C$19*$C$36*$C$26*$C$37*($C$27*(1-$C$28)^((S20-1)*$C$26*$C$36))*$C$21*$C$22/((1+$F$16)^S20) -> 501649.33 | U31: 放电电量现值(KWh) | W31: =$C$19*$C$36*$C$26*$C$37*($C$27*(1-$C$28)^((W20-1)*$C$26*$C$36))*$C$21*$C$22/((1+$V$16)^W20) -> 1471486.5 | X31: =$C$19*$C$36*$C$26*$C$37*($C$27*(1-$C$28)^((X20-1)*$C$26*$C$36))*$C$21*$C$22/((1+$V$16)^X20) -> 1447579.3 | Y31: =$C$19*$C$36*$C$26*$C$37*($C$27*(1-$C$28)^((Y20-1)*$C$26*$C$36))*$C$21*$C$22/((1+$V$16)^Y20) -> 1424060.5 | Z31: =$C$19*$C$36*$C$26*$C$37*($C$27*(1-$C$28)^((Z20-1)*$C$26*$C$36))*$C$21*$C$22/((1+$V$16)^Z20) -> 1400923.9 | AA31: =$C$19*$C$36*$C$26*$C$37*($C$27*(1-$C$28)^((AA20-1)*$C$26*$C$36))*$C$21*$C$22/((1+$V$16)^AA20) -> 1378163.1 | AB31: =$C$19*$C$36*$C$26*$C$37*($C$27*(1-$C$28)^((AB20-1)*$C$26*$C$36))*$C$21*$C$22/((1+$V$16)^AB20) -> 1355772.2 | AC31: =$C$19*$C$36*$C$26*$C$37*($C$27*(1-$C$28)^((AC20-1)*$C$26*$C$36))*$C$21*$C$22/((1+$V$16)^AC20) -> 1333745 | AD31: =$C$19*$C$36*$C$26*$C$37*($C$27*(1-$C$28)^((AD20-1)*$C$26*$C$36))*$C$21*$C$22/((1+$V$16)^AD20) -> 1312075.7 | ... AI31: =$C$19*$C$36*$C$26*$C$37*($C$27*(1-$C$28)^((AI20-1)*$C$26*$C$36))*$C$21*$C$22/((1+$V$16)^AI20) -> 1208897.1
B32: 其它设备投资费用（升压变等） | C32: 350000 | E32: 充电成本现值和（Mn RMB） | F32: =SUM(G33:S33) -> 0 | U32: 充电成本现值和（Mn RMB） | V32: =SUM(W33:AI33) -> 0
B33: 其它成本：入网检测费、项目管理费等（元/Wh） | C33: 0.01 | E33: 充电成本现值（Mn RMB） | G33: =($C$13*$C$25*G29/($C$13+$C$14)+$C$14*$C$24*G29/($C$13+$C$14))/1000000 -> 0 | H33: =($C$13*$C$25*H29/($C$13+$C$14)+$C$14*$C$24*H29/($C$13+$C$14))/1000000 -> 0 | I33: =($C$13*$C$25*I29/($C$13+$C$14)+$C$14*$C$24*I29/($C$13+$C$14))/1000000 -> 0 | J33: =($C$13*$C$25*J29/($C$13+$C$14)+$C$14*$C$24*J29/($C$13+$C$14))/1000000 -> 0 | K33: =($C$13*$C$25*K29/($C$13+$C$14)+$C$14*$C$24*K29/($C$13+$C$14))/1000000 -> 0 | L33: =($C$13*$C$25*L29/($C$13+$C$14)+$C$14*$C$24*L29/($C$13+$C$14))/1000000 -> 0 | M33: =($C$13*$C$25*M29/($C$13+$C$14)+$C$14*$C$24*M29/($C$13+$C$14))/1000000 -> 0 | N33: =($C$13*$C$25*N29/($C$13+$C$14)+$C$14*$C$24*N29/($C$13+$C$14))/1000000 -> 0 | ... S33: =($C$13*$C$25*S29/($C$13+$C$14)+$C$14*$C$24*S29/($C$13+$C$14))/1000000 -> 0 | U33: 充电成本现值（Mn RMB） | W33: =($C$13*$C$25*W29/($C$13+$C$14)+$C$14*$C$24*W29/($C$13+$C$14))/1000000 -> 0 | X33: =($C$13*$C$25*X29/($C$13+$C$14)+$C$14*$C$24*X29/($C$13+$C$14))/1000000 -> 0 | Y33: =($C$13*$C$25*Y29/($C$13+$C$14)+$C$14*$C$24*Y29/($C$13+$C$14))/1000000 -> 0 | Z33: =($C$13*$C$25*Z29/($C$13+$C$14)+$C$14*$C$24*Z29/($C$13+$C$14))/1000000 -> 0 | AA33: =($C$13*$C$25*AA29/($C$13+$C$14)+$C$14*$C$24*AA29/($C$13+$C$14))/1000000 -> 0 | AB33: =($C$13*$C$25*AB29/($C$13+$C$14)+$C$14*$C$24*AB29/($C$13+$C$14))/1000000 -> 0 | AC33: =($C$13*$C$25*AC29/($C$13+$C$14)+$C$14*$C$24*AC29/($C$13+$C$14))/1000000 -> 0 | AD33: =($C$13*$C$25*AD29/($C$13+$C$14)+$C$14*$C$24*AD29/($C$13+$C$14))/1000000 -> 0 | ... AI33: =($C$13*$C$25*AI29/($C$13+$C$14)+$C$14*$C$24*AI29/($C$13+$C$14))/1000000 -> 0
B34: 容量型储能电站运维费用 | C34: 0.001 | E34: 放电收益现值和（Mn RMB） | F34: =SUM(G35:S35) -> 3.4018154 | U34: 放电收益现值和（Mn RMB） | V34: =SUM(W35:AI35) -> 5.2113808
B35: 储能系统残值 | C35: 0.05 | E35: 放电收益现值（Mn RMB） | G35: =G31*$C$23/1000000 -> 0.4125663 | H35: =H31*$C$23/1000000 -> 0.37931154 | I35: =I31*$C$23/1000000 -> 0.34873728 | J35: =J31*$C$23/1000000 -> 0.32062744 | K35: =K31*$C$23/1000000 -> 0.29478338 | L35: =L31*$C$23/1000000 -> 0.27102248 | M35: =M31*$C$23/1000000 -> 0.24917681 | N35: =N31*$C$23/1000000 -> 0.22909201 | ... S35: =S31*$C$23/1000000 -> 0.1504948 | U35: 放电收益现值（Mn RMB） | W35: =W31*$C$23/1000000 -> 0.44144594 | X35: =X31*$C$23/1000000 -> 0.43427379 | Y35: =Y31*$C$23/1000000 -> 0.42721816 | Z35: =Z31*$C$23/1000000 -> 0.42027717 | AA35: =AA31*$C$23/1000000 -> 0.41344894 | AB35: =AB31*$C$23/1000000 -> 0.40673166 | AC35: =AC31*$C$23/1000000 -> 0.40012351 | AD35: =AD31*$C$23/1000000 -> 0.39362272 | ... AI35: =AI31*$C$23/1000000 -> 0.36266914
B36: 充放循环次数（1次为1充1放）(次/天） | C36: =C13+C14 -> 1 | E36: 所得税现值和（Mn RMB） | F36: =SUM(G37:S37) -> 0.21165421 | U36: 所得税现值和（Mn RMB） | V36: =SUM(W37:AI37) -> 0.30921724
B37: 充放电效率RTE（%） | C37: 0.96 | E37: 所得税现值（Mn RMB） | G37: =(G35-G33-G26-G24)*$F$17 -> 0.031708939 | H37: =(H35-H33-H26-H24)*$F$17 -> 0.028068414 | I37: =(I35-I33-I26-I24)*$F$17 -> 0.024792289 | J37: =(J35-J33-J26-J24)*$F$17 -> 0.021846551 | K37: =(K35-K33-K26-K24)*$F$17 -> 0.01920023 | L37: =(L35-L33-L26-L24)*$F$17 -> 0.016825137 | M37: =(M35-M33-M26-M24)*$F$17 -> 0.014695621 | N37: =(N35-N33-N26-N24)*$F$17 -> 0.012788346 | ... S37: =(S35-S33-S26-S24)*$F$17 -> 0.0059067557 | U37: 所得税现值（Mn RMB） | W37: =(W35-W33-W26-W24)*$V$17 -> 0.033928565 | X37: =(X35-X33-X26-X24)*$V$17 -> 0.032135527 | Y37: =(Y35-Y33-Y26-Y24)*$V$17 -> 0.03037162 | Z37: =(Z35-Z33-Z26-Z24)*$V$17 -> 0.028636372 | AA37: =(AA35-AA33-AA26-AA24)*$V$17 -> 0.026929316 | AB37: =(AB35-AB33-AB26-AB24)*$V$17 -> 0.025249994 | AC37: =(AC35-AC33-AC26-AC24)*$V$17 -> 0.023597957 | AD37: =(AD35-AD33-AD26-AD24)*$V$17 -> 0.02197276 | ... AI37: =(AI35-AI33-AI26-AI24)*$V$17 -> 0.014234366
B38: 用户分成比例（%） | C38: 0.1 | E38: 增值税现值和（Mn RMB） | F38: =SUM(G39:S39) -> 0 | U38: 增值税现值和（Mn RMB） | V38: =SUM(W39:AI39) -> 0
B39: 充放循环总次数（次数） | C39: =LOG(C29/C27,(1-C28)) -> 6525.0962 | E39: 增值税现值（Mn RMB） | G39: =(G35-G33)*$F$18 -> 0 | H39: =(H35-H33)*$F$18 -> 0 | I39: =(I35-I33)*$F$18 -> 0 | J39: =(J35-J33)*$F$18 -> 0 | K39: =(K35-K33)*$F$18 -> 0 | L39: =(L35-L33)*$F$18 -> 0 | M39: =(M35-M33)*$F$18 -> 0 | N39: =(N35-N33)*$F$18 -> 0 | ... S39: =(S35-S33)*$F$18 -> 0 | U39: 增值税现值（Mn RMB） | W39: =(W35-W33)*$V$18 -> 0 | X39: =(X35-X33)*$V$18 -> 0 | Y39: =(Y35-Y33)*$V$18 -> 0 | Z39: =(Z35-Z33)*$V$18 -> 0 | AA39: =(AA35-AA33)*$V$18 -> 0 | AB39: =(AB35-AB33)*$V$18 -> 0 | AC39: =(AC35-AC33)*$V$18 -> 0 | AD39: =(AD35-AD33)*$V$18 -> 0 | ... AI39: =(AI35-AI33)*$V$18 -> 0
B40: 系统寿命（年） | C40: =C39/C36/C26 -> 18.643132 | E40: 放电利润现值和（Mn RMB） | F40: =SUM(G41:S41) -> 3.1399986 | U40: 放电利润现值和（Mn RMB） | V40: =SUM(W41:AI41) -> 4.8241376
B41: PCS总成本（元） | C41: =C18*C17 -> 252000 | E41: 放电利润现值和（Mn RMB） | G41: =G35-G33-G37-G39-G26 -> 0.37524801 | H41: =H35-H33-H37-H39-H26 -> 0.34600075 | I41: =I35-I33-I37-I39-I26 -> 0.31904557 | J41: =J35-J33-J37-J39-J26 -> 0.29420199 | K41: =K35-K33-K37-K39-K26 -> 0.27130381 | L41: =L35-L33-L37-L39-L26 -> 0.25019795 | M41: =M35-M33-M37-M39-M26 -> 0.23074344 | N41: =N35-N33-N37-N39-N26 -> 0.21281044 | ... S41: =S35-S33-S37-S39-S26 -> 0.14209743 | U41: 放电利润现值和（Mn RMB） | W41: =W35-W33-W37-W39-W26 -> 0.40151537 | X41: =X35-X33-X37-X39-X26 -> 0.39613626 | Y41: =Y35-Y33-Y37-Y39-Y26 -> 0.39084454 | Z41: =Z35-Z33-Z37-Z39-Z26 -> 0.38563879 | AA41: =AA35-AA33-AA37-AA39-AA26 -> 0.38051763 | AB41: =AB35-AB33-AB37-AB39-AB26 -> 0.37547966 | AC41: =AC35-AC33-AC37-AC39-AC26 -> 0.37052355 | AD41: =AD35-AD33-AD37-AD39-AD26 -> 0.36564796 | ... AI41: =AI35-AI33-AI37-AI39-AI26 -> 0.34243278
B42: ESS总成本（元） | C42: =C19*C20 -> 5280000 | E42: 度电收益（元/kWh) | F42: =C23 -> 0.3 | U42: 度电收益（元/kWh) | V42: =C23 -> 0.3
B43: 土建总投资（元） | C43: =C30*C19*1000 -> 72000 | E43: LCOS（元/kWh) | F43: =F22/F30*1000000 -> 0.52930561 | U43: LCOS（元/kWh) | V43: =V22/V30*1000000 -> 0.34551304
B44: 其它投资（元） | C44: =C33*C19*1000 -> 48000 | E44: 充电成本（元/kWh) | F44: =F32*1000000/F30 -> 0 | U44: 充电成本（元/kWh) | V44: =V32*1000000/V30 -> 0
B45: 设备购置补助（元） | C45: 0 | E45: 用户分成部分（元/kWh) | F45: =SUM(G46:O46) -> 0.24958313 | U45: 用户分成部分（元/kWh) | V45: =SUM(W46:AI46) -> 0.48241376
B46: 设备总投资（元） | C46: =(C44+C43+C42+C41+C32-C45) -> 6002000 | E46: 用户分成部分现值 | G46: =G41*$C$38 -> 0.037524801 | H46: =H41*$C$38 -> 0.034600075 | I46: =I41*$C$38 -> 0.031904557 | J46: =J41*$C$38 -> 0.029420199 | K46: =K41*$C$38 -> 0.027130381 | L46: =L41*$C$38 -> 0.025019795 | M46: =M41*$C$38 -> 0.023074344 | N46: =N41*$C$38 -> 0.021281044 | ... S46: =S41*$C$38 -> 0.014209743 | U46: 用户分成部分现值 | W46: =W41*$C$38 -> 0.040151537 | X46: =X41*$C$38 -> 0.039613626 | Y46: =Y41*$C$38 -> 0.039084454 | Z46: =Z41*$C$38 -> 0.038563879 | AA46: =AA41*$C$38 -> 0.038051763 | AB46: =AB41*$C$38 -> 0.037547966 | AC46: =AC41*$C$38 -> 0.037052355 | AD46: =AD41*$C$38 -> 0.036564796 | ... AI46: =AI41*$C$38 -> 0.034243278
B47: 投资回收年限 | C47: 9+ | E47: NPV | F47: =-(F22) -> -6.002 | G47: =G35-G33-G46-G37-G39-G26 -> 0.33772321 | H47: =H35-H33-H46-H37-H39-H26 -> 0.31140068 | I47: =I35-I33-I46-I37-I39-I26 -> 0.28714101 | J47: =J35-J33-J46-J37-J39-J26 -> 0.26478179 | K47: =K35-K33-K46-K37-K39-K26 -> 0.24417343 | L47: =L35-L33-L46-L37-L39-L26 -> 0.22517816 | M47: =M35-M33-M46-M37-M39-M26 -> 0.2076691 | N47: =N35-N33-N46-N37-N39-N26 -> 0.1915294 | O47: =O35-O33-O46-O37-O39-O26+S27 -> 0.29143058 | P47: =P35-P33-P46-P37-P39-P26+P27 -> 0.16293602 | Q47: =Q35-Q33-Q46-Q37-Q39-Q26+Q27 -> 0.1502919 | R47: =R35-R33-R46-R37-R39-R26+R27 -> 0.13863495 | S47: =S35-S33-S46-S37-S39-S26+S27 -> 0.24266685 | U47: NPV | V47: =-(V22) -> -6.002 | W47: =W35-W33-W46-W37-W39-W26 -> 0.36136384 | X47: =X35-X33-X46-X37-X39-X26 -> 0.35652263 | Y47: =Y35-Y33-Y46-Y37-Y39-Y26 -> 0.35176009 | Z47: =Z35-Z33-Z46-Z37-Z39-Z26 -> 0.34707492 | AA47: =AA35-AA33-AA46-AA37-AA39-AA26 -> 0.34246586 | AB47: =AB35-AB33-AB46-AB37-AB39-AB26 -> 0.3379317 | AC47: =AC35-AC33-AC46-AC37-AC39-AC26 -> 0.33347119 | AD47: =AD35-AD33-AD46-AD37-AD39-AD26 -> 0.32908316 | AE47: =AE35-AE33-AE46-AE37-AE39-AE26+AI27 -> 0.60136642 | AF47: =AF35-AF33-AF46-AF37-AF39-AF26+AF27 -> 0.32051982 | AG47: =AG35-AG33-AG46-AG37-AG39-AG26+AG27 -> 0.3163422 | AH47: =AH35-AH33-AH46-AH37-AH39-AH26+AH27 -> 0.31223247 | AI47: =AI35-AI33-AI46-AI37-AI39-AI26+AI27 -> 0.5847895
B48: 投资回报率 | C48: =F48 -> -0.49091018 | E48: 投资回报率 | F48: =SUM(F47:S47)/F22 -> -0.49091018 | U48: IRR | V48: =IRR(V47:AI47) -> -0.026870407
B49: 放电补贴（元/kWh) | C49: 0

Sheet 表前_共享储能_现货
C1: 自变量 | D1: *表前储能主要通过现货形式进行峰谷套利、容量租赁等方式活力
C2: 支出项 | D2: 关键假定：
C3: 收入项 | D3: 1）电池充放电循环次数~6525次
D4: 2）PCS成本：0.21元/W；电池充放电循环次数~6525次；容量型储能电站运维费用：0.1%；PCS效率：98%；线损：98%；系统使用天数：350天；充放循环次数（1次为1充1放）(次/天）：1次
B5: Updated-新增表前结合现货盈利模型 | D5: 3）一充一放（一谷一峰）
B6: Base | E6: 计算结果
B7: 储能电站:一充一放（一谷一峰） | E7: LCOS（元/kWh) | F7: =F42 -> 0.65232481 | I7: 价差为0.8时： | K7: 0.17612056
B8: 基本数据 | E8: 投资回报率 | F8: =F46 -> 0.044444708 | I8: 价差为0.7时： | K8: 0.15935511
B9: PCS(KW） | C9: 100000 | E9: NPV(折现率=7%） | F9: =SUM(F45:S45) -> 116.93111 | I9: 价差为0.65时： | K9: 0.15086564
B10: PCS成本（元/kW) | C10: 210 | E10: IRR | F10: =V46 -> 0.13015744 | I10: 价差为0.55时： | K10: 0.13364414
B11: ESS(KWh) | C11: 200000 | E11: 折现率 | F11: 0.07 | I11: 价差为0.5时： | K11: 0.12489873 | U11: 折现率 | V11: 0
B12: ESS成本（元/kWh) | C12: 1100 | E12: 所得税率 | F12: 0.25 | I12: 价差为0.45时： | K12: 0.11605349 | U12: 所得税率 | V12: 0.25
B13: PCS效率 | C13: 0.98 | E13: 增值税率 | F13: 0 | G13: 暂不考虑 | I13: 价差为0.3时： | K13: 0.088828898 | U13: 增值税率 | V13: 0 | W13: 暂不考虑
B14: 线损 | C14: 0.98 | E14: 储能系统经济效益估算表（元） | U14: 储能系统经济效益估算表（元）
B15: 峰价（元/KWh) | C15: 0.53 | E15: 储能平准化成本LCOS（Levelized Cost of Storage） | G15: 1 | H15: 2 | I15: 3 | J15: 4 | K15: 5 | L15: 6 | M15: 7 | N15: 8 | O15: 9 | P15: 10 | Q15: 11 | R15: 12 | S15: 13 | U15: 储能平准化成本LCOS（Levelized Cost of Storage） | W15: 1 | X15: 2 | Y15: 3 | Z15: 4 | AA15: 5 | AB15: 6 | AC15: 7 | AD15: 8 | AE15: 9 | AF15: 10 | AG15: 11 | AH15: 12 | AI15: 13
B16: 平价（元/KWh) | C16: 0 | F16: 基准年 | G16: 第1年 | H16: 第2年 | I16: 第3年 | J16: 第4年 | K16: 第5年 | L16: 第6年 | M16: 第7年 | N16: 第8年 | O16: 第9年 | P16: 第10年 | Q16: 第11年 | R16: 第12年 | S16: 第13年 | V16: 基准年 | W16: 第1年 | X16: 第2年 | Y16: 第3年 | Z16: 第4年 | AA16: 第5年 | AB16: 第6年 | AC16: 第7年 | AD16: 第8年 | AE16: 第9年 | AF16: 第10年 | AG16: 第11年 | AH16: 第12年 | AI16: 第13年
B17: 谷价（元/KWh) | C17: 0 | E17: 初始投资成本（Mn RMB） | F17: =C37/1000000 -> 311 | U17: 初始投资成本（Mn RMB） | V17: =C37/1000000 -> 311
B18: 系统年使用天数 (天) | C18: 350 | D18: =C15-C17 -> 0.53 | E18: 折旧现值和（Mn RMB） | F18: =SUM(G19:S19) -> 108.91363 | U18: 折旧现值和（Mn RMB） | V18: =SUM(W19:AI19) -> 169.41091
B19: DOD% | C19: 0.95 | E19: 折旧现值（Mn RMB） | G19: =($C$33+$C$34+$C$24)*(1-$C$27)/$C$32/1000000/(1+$F$11)^G15+($C$35)*(1-$C$23)/$C$32/1000000/(1+$F$11)^G15 -> 12.179073 | H19: =($C$33+$C$34+$C$24)*(1-$C$27)/$C$32/1000000/(1+$F$11)^H15+($C$35)*(1-$C$23)/$C$32/1000000/(1+$F$11)^H15 -> 11.382312 | I19: =($C$33+$C$34+$C$24)*(1-$C$27)/$C$32/1000000/(1+$F$11)^I15+($C$35)*(1-$C$23)/$C$32/1000000/(1+$F$11)^I15 -> 10.637674 | J19: =($C$33+$C$34+$C$24)*(1-$C$27)/$C$32/1000000/(1+$F$11)^J15+($C$35)*(1-$C$23)/$C$32/1000000/(1+$F$11)^J15 -> 9.9417518 | K19: =($C$33+$C$34+$C$24)*(1-$C$27)/$C$32/1000000/(1+$F$11)^K15+($C$35)*(1-$C$23)/$C$32/1000000/(1+$F$11)^K15 -> 9.2913568 | L19: =($C$33+$C$34+$C$24)*(1-$C$27)/$C$32/1000000/(1+$F$11)^L15+($C$35)*(1-$C$23)/$C$32/1000000/(1+$F$11)^L15 -> 8.683511 | M19: =($C$33+$C$34+$C$24)*(1-$C$27)/$C$32/1000000/(1+$F$11)^M15+($C$35)*(1-$C$23)/$C$32/1000000/(1+$F$11)^M15 -> 8.1154309 | N19: =($C$33+$C$34+$C$24)*(1-$C$27)/$C$32/1000000/(1+$F$11)^N15+($C$35)*(1-$C$23)/$C$32/1000000/(1+$F$11)^N15 -> 7.5845148 | ... S19: =($C$33+$C$34+$C$24)*(1-$C$27)/$C$32/1000000/(1+$F$11)^S15+($C$35)*(1-$C$23)/$C$32/1000000/(1+$F$11)^S15 -> 5.4076543 | U19: 折旧现值（Mn RMB） | W19: =($C$33+$C$34+$C$24)*(1-$C$27)/$C$32/1000000/(1+$V$11)^W15+($C$35)*(1-$C$23)/$C$32/1000000/(1+$V$11)^W15 -> 13.031609 | X19: =($C$33+$C$34+$C$24)*(1-$C$27)/$C$32/1000000/(1+$V$11)^X15+($C$35)*(1-$C$23)/$C$32/1000000/(1+$V$11)^X15 -> 13.031609 | Y19: =($C$33+$C$34+$C$24)*(1-$C$27)/$C$32/1000000/(1+$V$11)^Y15+($C$35)*(1-$C$23)/$C$32/1000000/(1+$V$11)^Y15 -> 13.031609 | Z19: =($C$33+$C$34+$C$24)*(1-$C$27)/$C$32/1000000/(1+$V$11)^Z15+($C$35)*(1-$C$23)/$C$32/1000000/(1+$V$11)^Z15 -> 13.031609 | AA19: =($C$33+$C$34+$C$24)*(1-$C$27)/$C$32/1000000/(1+$V$11)^AA15+($C$35)*(1-$C$23)/$C$32/1000000/(1+$V$11)^AA15 -> 13.031609 | AB19: =($C$33+$C$34+$C$24)*(1-$C$27)/$C$32/1000000/(1+$V$11)^AB15+($C$35)*(1-$C$23)/$C$32/1000000/(1+$V$11)^AB15 -> 13.031609 | AC19: =($C$33+$C$34+$C$24)*(1-$C$27)/$C$32/1000000/(1+$V$11)^AC15+($C$35)*(1-$C$23)/$C$32/1000000/(1+$V$11)^AC15 -> 13.031609 | AD19: =($C$33+$C$34+$C$24)*(1-$C$27)/$C$32/1000000/(1+$V$11)^AD15+($C$35)*(1-$C$23)/$C$32/1000000/(1+$V$11)^AD15 -> 13.031609 | ... AI19: =($C$33+$C$34+$C$24)*(1-$C$27)/$C$32/1000000/(1+$V$11)^AI15+($C$35)*(1-$C$23)/$C$32/1000000/(1+$V$11)^AI15 -> 13.031609
B20: 单次循环衰减率 | C20: 4.68e-05 | E20: 运行成本现值和（Mn RMB） | F20: =SUM(G21:S21) -> 12.996147 | U20: 运行成本现值和（Mn RMB） | V20: =SUM(W21:AI21) -> 20.215
B21: 系统报废终止标准 | C21: 0.7 | E21: 运行成本现值（Mn RMB） | G21: =($C$26*$F$17)/((1+$F$11)^G15) -> 1.453271 | H21: =($C$26*$F$17)/((1+$F$11)^H15) -> 1.3581972 | I21: =($C$26*$F$17)/((1+$F$11)^I15) -> 1.2693432 | J21: =($C$26*$F$17)/((1+$F$11)^J15) -> 1.1863021 | K21: =($C$26*$F$17)/((1+$F$11)^K15) -> 1.1086935 | L21: =($C$26*$F$17)/((1+$F$11)^L15) -> 1.0361622 | M21: =($C$26*$F$17)/((1+$F$11)^M15) -> 0.96837585 | N21: =($C$26*$F$17)/((1+$F$11)^N15) -> 0.90502416 | ... S21: =($C$26*$F$17)/((1+$F$11)^S15) -> 0.64526972 | U21: 运行成本现值（Mn RMB） | W21: =($C$26*$V$17)/((1+$V$11)^W15) -> 1.555 | X21: =($C$26*$V$17)/((1+$V$11)^X15) -> 1.555 | Y21: =($C$26*$V$17)/((1+$V$11)^Y15) -> 1.555 | Z21: =($C$26*$V$17)/((1+$V$11)^Z15) -> 1.555 | AA21: =($C$26*$V$17)/((1+$V$11)^AA15) -> 1.555 | AB21: =($C$26*$V$17)/((1+$V$11)^AB15) -> 1.555 | AC21: =($C$26*$V$17)/((1+$V$11)^AC15) -> 1.555 | AD21: =($C$26*$V$17)/((1+$V$11)^AD15) -> 1.555 | ... AI21: =($C$26*$V$17)/((1+$V$11)^AI15) -> 1.555
B22: 土建成本(元/Wh) | C22: 0.2 | E22: 固定资产残值现值 (Mn RMB) | S22: =($C$33+$C$34)*$C$27/((1+$F$11)^$S$15)/1000000+($C$35)*$C$23/((1+$F$11)^$S$15)/1000000 -> 15.789397 | U22: 固定资产残值现值 (Mn RMB) | AI22: =($C$33+$C$34)*$C$27/((1+$V$11)^$AI$15)/1000000+($C$35)*$C$23/((1+$V$11)^$AI$15)/1000000 -> 38.05
B23: 土建残值率（%） | C23: 0.65 | E23: 充电电量现值和(KWh) | F23: =SUM(G24:S24) -> 5.5581656e+08 | U23: 充电电量现值和(KWh) | V23: =SUM(W24:AI24) -> 8.5147822e+08
B24: 其它 | C24: 0 | E24: 充电电量现值(KWh) | G24: =$C$11*$C$28*$C$18/$C$29*($C$19*(1-$C$20)^((G15-1)*$C$18*$C$28))/$C$13/$C$14/((1+$F$11)^G15) -> 67408472 | H24: =$C$11*$C$28*$C$18/$C$29*($C$19*(1-$C$20)^((H15-1)*$C$18*$C$28))/$C$13/$C$14/((1+$F$11)^H15) -> 61975037 | I24: =$C$11*$C$28*$C$18/$C$29*($C$19*(1-$C$20)^((I15-1)*$C$18*$C$28))/$C$13/$C$14/((1+$F$11)^I15) -> 56979562 | J24: =$C$11*$C$28*$C$18/$C$29*($C$19*(1-$C$20)^((J15-1)*$C$18*$C$28))/$C$13/$C$14/((1+$F$11)^J15) -> 52386746 | K24: =$C$11*$C$28*$C$18/$C$29*($C$19*(1-$C$20)^((K15-1)*$C$18*$C$28))/$C$13/$C$14/((1+$F$11)^K15) -> 48164131 | L24: =$C$11*$C$28*$C$18/$C$29*($C$19*(1-$C$20)^((L15-1)*$C$18*$C$28))/$C$13/$C$14/((1+$F$11)^L15) -> 44281879 | M24: =$C$11*$C$28*$C$18/$C$29*($C$19*(1-$C$20)^((M15-1)*$C$18*$C$28))/$C$13/$C$14/((1+$F$11)^M15) -> 40712555 | N24: =$C$11*$C$28*$C$18/$C$29*($C$19*(1-$C$20)^((N15-1)*$C$18*$C$28))/$C$13/$C$14/((1+$F$11)^N15) -> 37430934 | ... S24: =$C$11*$C$28*$C$18/$C$29*($C$19*(1-$C$20)^((S15-1)*$C$18*$C$28))/$C$13/$C$14/((1+$F$11)^S15) -> 24589077 | U24: 充电电量现值(KWh) | W24: =($C$11*$C$28*$C$18/$C$29*($C$19*(1-$C$20)^((W15-1)*$C$18*$C$28))/$C$13/$C$14/((1+$V$11)^W15)) -> 72127065 | X24: =($C$11*$C$28*$C$18/$C$29*($C$19*(1-$C$20)^((X15-1)*$C$18*$C$28))/$C$13/$C$14/((1+$V$11)^X15)) -> 70955220 | Y24: =($C$11*$C$28*$C$18/$C$29*($C$19*(1-$C$20)^((Y15-1)*$C$18*$C$28))/$C$13/$C$14/((1+$V$11)^Y15)) -> 69802414 | Z24: =($C$11*$C$28*$C$18/$C$29*($C$19*(1-$C$20)^((Z15-1)*$C$18*$C$28))/$C$13/$C$14/((1+$V$11)^Z15)) -> 68668337 | AA24: =($C$11*$C$28*$C$18/$C$29*($C$19*(1-$C$20)^((AA15-1)*$C$18*$C$28))/$C$13/$C$14/((1+$V$11)^AA15)) -> 67552686 | AB24: =($C$11*$C$28*$C$18/$C$29*($C$19*(1-$C$20)^((AB15-1)*$C$18*$C$28))/$C$13/$C$14/((1+$V$11)^AB15)) -> 66455160 | AC24: =($C$11*$C$28*$C$18/$C$29*($C$19*(1-$C$20)^((AC15-1)*$C$18*$C$28))/$C$13/$C$14/((1+$V$11)^AC15)) -> 65375466 | AD24: =($C$11*$C$28*$C$18/$C$29*($C$19*(1-$C$20)^((AD15-1)*$C$18*$C$28))/$C$13/$C$14/((1+$V$11)^AD15)) -> 64313314 | ... AI24: =($C$11*$C$28*$C$18/$C$29*($C$19*(1-$C$20)^((AI15-1)*$C$18*$C$28))/$C$13/$C$14/((1+$V$11)^AI15)) -> 59255865
B25: 其它成本：入网检测费、项目管理费等（元/Wh） | C25: 0.15 | E25: 放电电量现值和(KWh) | F25: =SUM(G26:S26) -> 4.7247437e+08 | U25: 放电电量现值和(KWh) | V25: =SUM(W26:AI26) -> 7.2380289e+08
B26: 容量型储能电站运维费用 | C26: 0.005 | E26: 放电电量现值(KWh) | G26: =$C$11*$C$28*$C$18*$C$29*($C$19*(1-$C$20)^((G15-1)*$C$18*$C$28))*$C$13*$C$14/((1+$F$11)^G15) -> 57300875 | H26: =$C$11*$C$28*$C$18*$C$29*($C$19*(1-$C$20)^((H15-1)*$C$18*$C$28))*$C$13*$C$14/((1+$F$11)^H15) -> 52682159 | I26: =$C$11*$C$28*$C$18*$C$29*($C$19*(1-$C$20)^((I15-1)*$C$18*$C$28))*$C$13*$C$14/((1+$F$11)^I15) -> 48435733 | J26: =$C$11*$C$28*$C$18*$C$29*($C$19*(1-$C$20)^((J15-1)*$C$18*$C$28))*$C$13*$C$14/((1+$F$11)^J15) -> 44531589 | K26: =$C$11*$C$28*$C$18*$C$29*($C$19*(1-$C$20)^((K15-1)*$C$18*$C$28))*$C$13*$C$14/((1+$F$11)^K15) -> 40942136 | L26: =$C$11*$C$28*$C$18*$C$29*($C$19*(1-$C$20)^((L15-1)*$C$18*$C$28))*$C$13*$C$14/((1+$F$11)^L15) -> 37642011 | M26: =$C$11*$C$28*$C$18*$C$29*($C$19*(1-$C$20)^((M15-1)*$C$18*$C$28))*$C$13*$C$14/((1+$F$11)^M15) -> 34607890 | N26: =$C$11*$C$28*$C$18*$C$29*($C$19*(1-$C$20)^((N15-1)*$C$18*$C$28))*$C$13*$C$14/((1+$F$11)^N15) -> 31818334 | ... S26: =$C$11*$C$28*$C$18*$C$29*($C$19*(1-$C$20)^((S15-1)*$C$18*$C$28))*$C$13*$C$14/((1+$F$11)^S15) -> 20902056 | U26: 放电电量现值(KWh) | W26: =($C$11*$C$28*$C$18*$C$29*($C$19*(1-$C$20)^((W15-1)*$C$18*$C$28))*$C$13*$C$14/((1+$V$11)^W15)) -> 61311936 | X26: =($C$11*$C$28*$C$18*$C$29*($C$19*(1-$C$20)^((X15-1)*$C$18*$C$28))*$C$13*$C$14/((1+$V$11)^X15)) -> 60315804 | Y26: =($C$11*$C$28*$C$18*$C$29*($C$19*(1-$C$20)^((Y15-1)*$C$18*$C$28))*$C$13*$C$14/((1+$V$11)^Y15)) -> 59335856 | Z26: =($C$11*$C$28*$C$18*$C$29*($C$19*(1-$C$20)^((Z15-1)*$C$18*$C$28))*$C$13*$C$14/((1+$V$11)^Z15)) -> 58371829 | AA26: =($C$11*$C$28*$C$18*$C$29*($C$19*(1-$C$20)^((AA15-1)*$C$18*$C$28))*$C$13*$C$14/((1+$V$11)^AA15)) -> 57423464 | AB26: =($C$11*$C$28*$C$18*$C$29*($C$19*(1-$C$20)^((AB15-1)*$C$18*$C$28))*$C$13*$C$14/((1+$V$11)^AB15)) -> 56490508 | AC26: =($C$11*$C$28*$C$18*$C$29*($C$19*(1-$C$20)^((AC15-1)*$C$18*$C$28))*$C$13*$C$14/((1+$V$11)^AC15)) -> 55572709 | AD26: =($C$11*$C$28*$C$18*$C$29*($C$19*(1-$C$20)^((AD15-1)*$C$18*$C$28))*$C$13*$C$14/((1+$V$11)^AD15)) -> 54669822 | ... AI26: =($C$11*$C$28*$C$18*$C$29*($C$19*(1-$C$20)^((AI15-1)*$C$18*$C$28))*$C$13*$C$14/((1+$V$11)^AI15)) -> 50370714
B27: 储能系统残值 | C27: 0.05 | E27: 充电成本现值和（Mn RMB） | F27: =SUM(G28:S28) -> 0 | U27: 充电成本现值和（Mn RMB） | V27: =SUM(W28:AI28) -> 0
B28: 充放循环次数（1次为1充1放）(次/天） | C28: 1 | E28: 充电成本现值（Mn RMB） | G28: =($C$17+$C$16)*G24/2/1000000 -> 0 | H28: =($C$17+$C$16)*H24/2/1000000 -> 0 | I28: =($C$17+$C$16)*I24/2/1000000 -> 0 | J28: =($C$17+$C$16)*J24/2/1000000 -> 0 | K28: =($C$17+$C$16)*K24/2/1000000 -> 0 | L28: =($C$17+$C$16)*L24/2/1000000 -> 0 | M28: =($C$17+$C$16)*M24/2/1000000 -> 0 | N28: =($C$17+$C$16)*N24/2/1000000 -> 0 | ... S28: =($C$17+$C$16)*S24/2/1000000 -> 0 | U28: 充电成本现值（Mn RMB） | W28: =($C$17+$C$16)*W24/2/1000000 -> 0 | X28: =($C$17+$C$16)*X24/2/1000000 -> 0 | Y28: =($C$17+$C$16)*Y24/2/1000000 -> 0 | Z28: =($C$17+$C$16)*Z24/2/1000000 -> 0 | AA28: =($C$17+$C$16)*AA24/2/1000000 -> 0 | AB28: =($C$17+$C$16)*AB24/2/1000000 -> 0 | AC28: =($C$17+$C$16)*AC24/2/1000000 -> 0 | AD28: =($C$17+$C$16)*AD24/2/1000000 -> 0 | ... AI28: =($C$17+$C$16)*AI24/2/1000000 -> 0
B29: 充放电效率RTE（%） | C29: 0.96 | E29: 放电收益现值和（Mn RMB） | F29: =SUM(G30:S30) -> 250.41141 | U29: 放电收益现值和（Mn RMB） | V29: =SUM(W30:AI30) -> 383.61553
B30: 用户分成比例（%） | C30: 0 | E30: 放电收益现值（Mn RMB） | G30: =G26*$C$15/1000000 -> 30.369464 | H30: =H26*$C$15/1000000 -> 27.921544 | I30: =I26*$C$15/1000000 -> 25.670938 | J30: =J26*$C$15/1000000 -> 23.601742 | K30: =K26*$C$15/1000000 -> 21.699332 | L30: =L26*$C$15/1000000 -> 19.950266 | M30: =M26*$C$15/1000000 -> 18.342182 | N30: =N26*$C$15/1000000 -> 16.863717 | ... S30: =S26*$C$15/1000000 -> 11.078089 | U30: 放电收益现值（Mn RMB） | W30: =W26*$C$15/1000000 -> 32.495326 | X30: =X26*$C$15/1000000 -> 31.967376 | Y30: =Y26*$C$15/1000000 -> 31.448004 | Z30: =Z26*$C$15/1000000 -> 30.937069 | AA30: =AA26*$C$15/1000000 -> 30.434436 | AB30: =AB26*$C$15/1000000 -> 29.939969 | AC30: =AC26*$C$15/1000000 -> 29.453536 | AD30: =AD26*$C$15/1000000 -> 28.975006 | ... AI30: =AI26*$C$15/1000000 -> 26.696479
B31: 充放循环总次数（次数） | C31: =LOG(C21/C19,(1-C20)) -> 6525.0962 | E31: 容量租赁收益现值和（Mn RMB） | F31: =SUM(G32:S32) -> 275.80247 | U31: 容量租赁收益现值和（Mn RMB） | V31: =SUM(W32:AI32) -> 429
B32: 系统寿命（年） | C32: =C31/C28/C18 -> 18.643132 | E32: 容量租赁现值（Mn RMB） | G32: =$C$41*$C$9/(1+$F$11)^G15/1000000 -> 30.841121 | H32: =$C$41*$C$9/(1+$F$11)^H15/1000000 -> 28.823478 | I32: =$C$41*$C$9/(1+$F$11)^I15/1000000 -> 26.93783 | J32: =$C$41*$C$9/(1+$F$11)^J15/1000000 -> 25.175542 | K32: =$C$41*$C$9/(1+$F$11)^K15/1000000 -> 23.528544 | L32: =$C$41*$C$9/(1+$F$11)^L15/1000000 -> 21.989293 | M32: =$C$41*$C$9/(1+$F$11)^M15/1000000 -> 20.550741 | N32: =$C$41*$C$9/(1+$F$11)^N15/1000000 -> 19.2063 | ... S32: =$C$41*$C$9/(1+$F$11)^S15/1000000 -> 13.693827 | U32: 容量租赁现值（Mn RMB） | W32: =$C$41*$C$9/(1+$V$11)^W15/1000000 -> 33 | X32: =$C$41*$C$9/(1+$V$11)^X15/1000000 -> 33 | Y32: =$C$41*$C$9/(1+$V$11)^Y15/1000000 -> 33 | Z32: =$C$41*$C$9/(1+$V$11)^Z15/1000000 -> 33 | AA32: =$C$41*$C$9/(1+$V$11)^AA15/1000000 -> 33 | AB32: =$C$41*$C$9/(1+$V$11)^AB15/1000000 -> 33 | AC32: =$C$41*$C$9/(1+$V$11)^AC15/1000000 -> 33 | AD32: =$C$41*$C$9/(1+$V$11)^AD15/1000000 -> 33 | ... AI32: =$C$41*$C$9/(1+$V$11)^AI15/1000000 -> 33
B33: PCS总成本（元） | C33: =C10*C9 -> 21000000 | E33: 所得税现值和（Mn RMB） | F33: =SUM(G34:S34) -> 101.07603 | U33: 所得税现值和（Mn RMB） | V33: =SUM(W34:AI34) -> 155.7474
B34: ESS总成本（元） | C34: =C11*C12 -> 220000000 | E34: 所得税现值（Mn RMB） | G34: =(G30-G28-G21-G19+G32)*$F$12 -> 11.89456 | H34: =(H30-H28-H21-H19+H32)*$F$12 -> 11.001128 | I34: =(I30-I28-I21-I19+I32)*$F$12 -> 10.175438 | J34: =(J30-J28-J21-J19+J32)*$F$12 -> 9.4123075 | K34: =(K30-K28-K21-K19+K32)*$F$12 -> 8.7069565 | L34: =(L30-L28-L21-L19+L32)*$F$12 -> 8.0549715 | M34: =(M30-M28-M21-M19+M32)*$F$12 -> 7.4522792 | N34: =(N30-N28-N21-N19+N32)*$F$12 -> 6.8951196 | ... S34: =(S30-S28-S21-S19+S32)*$F$12 -> 4.6797481 | U34: 所得税现值（Mn RMB） | W34: =(W30-W28-W21-W19+W32)*$V$12 -> 12.727179 | X34: =(X30-X28-X21-X19+X32)*$V$12 -> 12.595192 | Y34: =(Y30-Y28-Y21-Y19+Y32)*$V$12 -> 12.465349 | Z34: =(Z30-Z28-Z21-Z19+Z32)*$V$12 -> 12.337615 | AA34: =(AA30-AA28-AA21-AA19+AA32)*$V$12 -> 12.211957 | AB34: =(AB30-AB28-AB21-AB19+AB32)*$V$12 -> 12.08834 | AC34: =(AC30-AC28-AC21-AC19+AC32)*$V$12 -> 11.966732 | AD34: =(AD30-AD28-AD21-AD19+AD32)*$V$12 -> 11.847099 | ... AI34: =(AI30-AI28-AI21-AI19+AI32)*$V$12 -> 11.277467
B35: 土建总投资（元） | C35: =C22*C11*1000 -> 40000000 | E35: 增值税现值和（Mn RMB） | F35: =SUM(G36:S36) -> 0 | U35: 增值税现值和（Mn RMB） | V35: =SUM(W36:AI36) -> 0
B36: 其它投资（元） | C36: =C25*C11*1000 -> 30000000 | E36: 增值税现值（Mn RMB） | G36: =(G30-G28)*$F$13 -> 0 | H36: =(H30-H28)*$F$13 -> 0 | I36: =(I30-I28)*$F$13 -> 0 | J36: =(J30-J28)*$F$13 -> 0 | K36: =(K30-K28)*$F$13 -> 0 | L36: =(L30-L28)*$F$13 -> 0 | M36: =(M30-M28)*$F$13 -> 0 | N36: =(N30-N28)*$F$13 -> 0 | ... S36: =(S30-S28)*$F$13 -> 0 | U36: 增值税现值（Mn RMB） | W36: =(W30-W28)*$V$13 -> 0 | X36: =(X30-X28)*$V$13 -> 0 | Y36: =(Y30-Y28)*$V$13 -> 0 | Z36: =(Z30-Z28)*$V$13 -> 0 | AA36: =(AA30-AA28)*$V$13 -> 0 | AB36: =(AB30-AB28)*$V$13 -> 0 | AC36: =(AC30-AC28)*$V$13 -> 0 | AD36: =(AD30-AD28)*$V$13 -> 0 | ... AI36: =(AI30-AI28)*$V$13 -> 0
B37: 设备总投资（元） | C37: =C36+C35+C34+C33+C24 -> 311000000 | E37: 放电利润现值和（Mn RMB） | F37: =SUM(G38:S38) -> 412.14171 | U37: 放电利润现值和（Mn RMB） | V37: =SUM(W38:AI38) -> 636.65313
B38: 投资回收年限 | C38: 9+ | E38: 放电利润现值和（Mn RMB） | G38: =G30-G28-G34-G36-G21+G32 -> 47.862754 | H38: =H30-H28-H34-H36-H21+H32 -> 44.385697 | I38: =I30-I28-I34-I36-I21+I32 -> 41.163988 | J38: =J30-J28-J34-J36-J21+J32 -> 38.178674 | K38: =K30-K28-K34-K36-K21+K32 -> 35.412226 | L38: =L30-L28-L34-L36-L21+L32 -> 32.848425 | M38: =M30-M28-M34-M36-M21+M32 -> 30.472268 | N38: =N30-N28-N34-N36-N21+N32 -> 28.269874 | ... S38: =S30-S28-S34-S36-S21+S32 -> 19.446898 | U38: 放电利润现值和（Mn RMB） | W38: =W30-W28-W34-W36-W21+W32 -> 51.213147 | X38: =X30-X28-X34-X36-X21+X32 -> 50.817184 | Y38: =Y30-Y28-Y34-Y36-Y21+Y32 -> 50.427655 | Z38: =Z30-Z28-Z34-Z36-Z21+Z32 -> 50.044454 | AA38: =AA30-AA28-AA34-AA36-AA21+AA32 -> 49.667479 | AB38: =AB30-AB28-AB34-AB36-AB21+AB32 -> 49.296629 | AC38: =AC30-AC28-AC34-AC36-AC21+AC32 -> 48.931804 | AD38: =AD30-AD28-AD34-AD36-AD21+AD32 -> 48.572906 | ... AI38: =AI30-AI28-AI34-AI36-AI21+AI32 -> 46.864011
B39: 投资回报率 | C39: =F46 -> 0.044444708 | E39: 初始投资成本（Mn RMB） | F39: =F17 -> 311 | U39: 初始投资成本（Mn RMB） | V39: =V17 -> 311
B40: 总收益（Mn RMB） | C40: =F29 -> 250.41141 | E40: 储能全生命周期成本现值（Mn RMB） | F40: =F39+F27+F20 -> 323.99615 | U40: 储能全生命周期成本现值（Mn RMB） | V40: =V39+V27+V20 -> 331.215
B41: 容量租赁（元/kW) | C41: 330 | E41: 度电收益（元/kWh) | F41: =C15 -> 0.53 | U41: 度电收益（元/kWh) | V41: =C15 -> 0.53
E42: LCOS（元/kWh) | F42: =(F20+F17-S22)*1000000/F25 -> 0.65232481 | U42: LCOS（元/kWh) | V42: =(V20+V17-AI22)*1000000/V25 -> 0.40503431
E43: 用户分成部分（元/kWh) | F43: =SUM(G44:O44) -> 0 | U43: 用户分成部分（元/kWh) | V43: =SUM(W44:AI44) -> 0
E44: 用户分成部分现值 | G44: =G38*$C$30 -> 0 | H44: =H38*$C$30 -> 0 | I44: =I38*$C$30 -> 0 | J44: =J38*$C$30 -> 0 | K44: =K38*$C$30 -> 0 | L44: =L38*$C$30 -> 0 | M44: =M38*$C$30 -> 0 | N44: =N38*$C$30 -> 0 | ... S44: =S38*$C$30 -> 0 | U44: 用户分成部分现值 | W44: =W38*$C$30 -> 0 | X44: =X38*$C$30 -> 0 | Y44: =Y38*$C$30 -> 0 | Z44: =Z38*$C$30 -> 0 | AA44: =AA38*$C$30 -> 0 | AB44: =AB38*$C$30 -> 0 | AC44: =AC38*$C$30 -> 0 | AD44: =AD38*$C$30 -> 0 | ... AI44: =AI38*$C$30 -> 0
E45: NPV | F45: =-F17 -> -311 | G45: =G30-G28-G44-G34-G36-G21+G32 -> 47.862754 | H45: =H30-H28-H44-H34-H36-H21+H32 -> 44.385697 | I45: =I30-I28-I44-I34-I36-I21+I32 -> 41.163988 | J45: =J30-J28-J44-J34-J36-J21+J32 -> 38.178674 | K45: =K30-K28-K44-K34-K36-K21+K32 -> 35.412226 | L45: =L30-L28-L44-L34-L36-L21+L32 -> 32.848425 | M45: =M30-M28-M44-M34-M36-M21+M32 -> 30.472268 | N45: =N30-N28-N44-N34-N36-N21+N32 -> 28.269874 | O45: =O30-O28-O44-O34-O36-O21+O32+O22 -> 26.228398 | P45: =P30-P28-P44-P34-P36-P21+P32+P22 -> 24.335956 | Q45: =Q30-Q28-Q44-Q34-Q36-Q21+Q32+Q22 -> 22.581551 | R45: =R30-R28-R44-R34-R36-R21+R32+R22 -> 20.955005 | S45: =S30-S28-S44-S34-S36-S21+S32+S22 -> 35.236296 | U45: NPV | V45: =-V17 -> -311 | W45: =W30-W28-W44-W34-W36-W21+W32 -> 51.213147 | X45: =X30-X28-X44-X34-X36-X21+X32 -> 50.817184 | Y45: =Y30-Y28-Y44-Y34-Y36-Y21+Y32 -> 50.427655 | Z45: =Z30-Z28-Z44-Z34-Z36-Z21+Z32 -> 50.044454 | AA45: =AA30-AA28-AA44-AA34-AA36-AA21+AA32 -> 49.667479 | AB45: =AB30-AB28-AB44-AB34-AB36-AB21+AB32 -> 49.296629 | AC45: =AC30-AC28-AC44-AC34-AC36-AC21+AC32 -> 48.931804 | AD45: =AD30-AD28-AD44-AD34-AD36-AD21+AD32 -> 48.572906 | AE45: =AE30-AE28-AE44-AE34-AE36-AE21+AE32+AE22 -> 48.21984 | AF45: =AF30-AF28-AF44-AF34-AF36-AF21+AF32+AF22 -> 47.872509 | AG45: =AG30-AG28-AG44-AG34-AG36-AG21+AG32+AG22 -> 47.530822 | AH45: =AH30-AH28-AH44-AH34-AH36-AH21+AH32+AH22 -> 47.194686 | AI45: =AI30-AI28-AI44-AI34-AI36-AI21+AI32+AI22 -> 84.914011
E46: 投资回报率 | F46: =SUM(F45:O45)/F17 -> 0.044444708 | U46: IRR | V46: =IRR(V45:AI45) -> 0.13015744

Sheet >>汇总_表后_非现货情景下_各省IRR
B1: xxx | C1: M2访谈数据/Assumption
B2: xxx | C2: 引用数据
B3: xxx | C3: 计算所得数据
B5: IRR >= 7 的省份（从高到底）：浙江省、江苏省、安徽省、广东省、湖北省、四川省
B6: IRR 1~6 的省份（从高到底）：重庆市、湖南省、海南省、陕西省、黑龙江省、吉林省、河南省、辽宁省、天津市、
B7: IRR <= 1 的省份（从高到底）：内蒙古自治区、福建省、山西省、山东省、北京市、广西壮族自治区、贵州省、宁夏回族自治区、云南省、青海省、河北省、甘肃省、江西省、上海市
B9: 优先地区/IRR高省份的特征：
C10: 1）用户峰谷价差大；
C11: 2）针对表后储能进行补贴的省份，补贴力度普遍较大，补贴规则设计合理
C12: 3）峰谷时段设计合理、平时段价格相对峰时段价格较低，储能系统可得到充分利用（如湖北省可以采用一谷一峰、一平一尖的放电策略，使得其IRR显著提高）
B13: 潜力地区/IRR中省份的特征：
C14: 1）用户峰谷价差一般；
C15: 2）大部分省份尚未出台针对表后储能的补贴政策；有补贴的省份，补贴力度小或规则设计不合理（如西安市财政局补贴，无法帮助典型储能系统有效提高IRR到有吸引力的水平）
C16: 3）平时段价格相对较高，不利于储能系统执行收益最大化的策略
B17: 观察地区/IRR低省份的特征：
C18: 1）用户峰谷价差一般或较小；
C19: 2）未出台针对表后储能的补贴政策
C20: 3）平时段价格相对较高、峰谷时段设计不合理，不利于储能系统的有效利用
B22: 2022年-全国（29个省份）表后储能IRR情况 | G22: 已失效政策
B23: 省份 | C23: 有无补贴政策 | D23: IRR：不含补贴 | E23: IRR：含补贴（1） | F23: 补贴（1）情况 | G23: IRR：含补贴（2） | H23: 补贴（2）情况 | I23: IRR（部分省份含补贴） | J23: Rank
B24: 浙江省 | C24: 有 | D24: =浙江!C12 -> 0.10476575 | E24: =浙江!C13 -> 0.16327082 | F24: 义乌市发改局 | G24: =浙江!C15 -> 0.18306688 | H24: 温州市经信局 | I24: =MAX(D24:H24) -> 0.18306688 | J24: =RANK(I24,$I$24:$I$52,0) -> 1
B25: 广东省 | C25: 有 | D25: =广东!C12 -> 0.063921609 | E25: =广东!C13 -> 0.073511721 | F25: 佛山市顺德区勒流街道 | G25: =广东!C15 -> 0.069874942 | H25: 佛山市顺德区容桂街道、龙江镇 | I25: =MAX(D25:H25) -> 0.073511721 | J25: =RANK(I25,$I$24:$I$52,0) -> 4
B26: 江苏省 | C26: 有 | D26: =江苏!C12 -> 0.055665502 | E26: =江苏!C13 -> 0.099816022 | F26: 苏州工业园 | G26: =江苏!C15 -> 0.065903393 | H26: 南京财政局 | I26: =MAX(D26:H26) -> 0.099816022 | J26: =RANK(I26,$I$24:$I$52,0) -> 2
B27: 湖南省 | C27: 无 | D27: =湖南!C12 -> 0.036886496 | E27: N/A | F27: N/A | G27: N/A | H27: N/A | I27: =MAX(D27:H27) -> 0.036886496 | J27: =RANK(I27,$I$24:$I$52,0) -> 5
B28: 辽宁省 | C28: 无 | D28: =辽宁!C12 -> 0.034020067 | E28: N/A | F28: N/A | G28: N/A | H28: N/A | I28: =MAX(D28:H28) -> 0.034020067 | J28: =RANK(I28,$I$24:$I$52,0) -> 6
B29: 黑龙江省 | C29: 无 | D29: =黑龙江!C12 -> 0.028673585 | E29: N/A | F29: N/A | G29: N/A | H29: N/A | I29: =MAX(D29:H29) -> 0.028673585 | J29: =RANK(I29,$I$24:$I$52,0) -> 7
B30: 重庆市 | C30: 无 | D30: =重庆!C12 -> 0.026052419 | E30: N/A | F30: N/A | G30: N/A | H30: N/A | I30: =MAX(D30:H30) -> 0.026052419 | J30: =RANK(I30,$I$24:$I$52,0) -> 9
B31: 河南省 | C31: 无 | D31: =河南!C12 -> 0.023789183 | E31: N/A | F31: N/A | G31: N/A | H31: N/A | I31: =MAX(D31:H31) -> 0.023789183 | J31: =RANK(I31,$I$24:$I$52,0) -> 10
B32: 陕西省 | C32: 无 | D32: =陕西!C12 -> -0.022556116 | E32: =陕西!C13 -> -0.0094424117 | F32: 西安市财政局 | G32: =陕西!C15 -> 0.023686861 | H32: 西安市工信局 | I32: =MAX(D32:H32) -> 0.023686861 | J32: =RANK(I32,$I$24:$I$52,0) -> 11
B33: 安徽省 | C33: 有 | D33: =安徽!C12 -> 0.020250782 | E33: =安徽!C13 -> 0.087459037 | F33: 芜湖市人民政府 | G33: =安徽!C15 -> 0.059528614 | H33: 合肥市人民政府 | I33: =MAX(D33:H33) -> 0.087459037 | J33: =RANK(I33,$I$24:$I$52,0) -> 3
B34: 湖北省 | C34: 无 | D34: =湖北!C12 -> 0.019012542 | E34: N/A | F34: N/A | G34: N/A | H34: N/A | I34: =MAX(D34:H34) -> 0.019012542 | J34: =RANK(I34,$I$24:$I$52,0) -> 12
B35: 海南省 | C35: 无 | D35: =海南!C12 -> 0.016002933 | E35: N/A | F35: N/A | G35: N/A | H35: N/A | I35: =MAX(D35:H35) -> 0.016002933 | J35: =RANK(I35,$I$24:$I$52,0) -> 13
B36: 四川省 | C36: 有 | D36: =四川!C12 -> 0.012543281 | E36: =四川!C13 -> 0.026427904 | F36: 成都市发改委 | G36: N/A | H36: N/A | I36: =MAX(D36:H36) -> 0.026427904 | J36: =RANK(I36,$I$24:$I$52,0) -> 8
B37: 吉林省 | C37: 无 | D37: =吉林!C12 -> 0.0074247458 | E37: N/A | F37: N/A | G37: N/A | H37: N/A | I37: =MAX(D37:H37) -> 0.0074247458 | J37: =RANK(I37,$I$24:$I$52,0) -> 14
B38: 山东省 | C38: 无 | D38: =山东!C12 -> 0.0060651792 | E38: N/A | F38: N/A | G38: N/A | H38: N/A | I38: =MAX(D38:H38) -> 0.0060651792 | J38: =RANK(I38,$I$24:$I$52,0) -> 15
B39: 山西省 | C39: 无 | D39: =山西!C12 -> 0.0020591176 | E39: N/A | F39: N/A | G39: N/A | H39: N/A | I39: =MAX(D39:H39) -> 0.0020591176 | J39: =RANK(I39,$I$24:$I$52,0) -> 16
B40: 天津市 | C40: 无 | D40: =天津!C12 -> -0.00066328747 | E40: N/A | F40: N/A | G40: N/A | H40: N/A | I40: =MAX(D40:H40) -> -0.00066328747 | J40: =RANK(I40,$I$24:$I$52,0) -> 17
B41: 内蒙古自治区 | C41: 无 | D41: =蒙东!C12 -> -0.0013315232 | E41: N/A | F41: N/A | G41: N/A | H41: N/A | I41: =MAX(D41:H41) -> -0.0013315232 | J41: =RANK(I41,$I$24:$I$52,0) -> 18
B42: 福建省 | C42: 无 | D42: =福建!C12 -> -0.006858429 | E42: N/A | F42: N/A | G42: N/A | H42: N/A | I42: =MAX(D42:H42) -> -0.006858429 | J42: =RANK(I42,$I$24:$I$52,0) -> 19
B43: 北京市 | C43: 无 | D43: =北京!C12 -> -0.029170052 | E43: N/A | F43: N/A | G43: N/A | H43: N/A | I43: =MAX(D43:H43) -> -0.029170052 | J43: =RANK(I43,$I$24:$I$52,0) -> 20
B44: 河北省 | C44: 无 | D44: =河北!C12 -> -0.029170052 | E44: N/A | F44: N/A | G44: N/A | H44: N/A | I44: =MAX(D44:H44) -> -0.029170052 | J44: =RANK(I44,$I$24:$I$52,0) -> 20
B45: 宁夏回族自治区 | C45: 无 | D45: =宁夏!C12 -> -0.033093639 | E45: N/A | F45: N/A | G45: N/A | H45: N/A | I45: =MAX(D45:H45) -> -0.033093639 | J45: =RANK(I45,$I$24:$I$52,0) -> 22
B46: 江西省 | C46: 无 | D46: =江西!C12 -> -0.044543503 | E46: N/A | F46: N/A | G46: N/A | H46: N/A | I46: =MAX(D46:H46) -> -0.044543503 | J46: =RANK(I46,$I$24:$I$52,0) -> 23
B47: 贵州省 | C47: 无 | D47: =贵州!C12 -> -0.044687664 | E47: N/A | F47: N/A | G47: N/A | H47: N/A | I47: =MAX(D47:H47) -> -0.044687664 | J47: =RANK(I47,$I$24:$I$52,0) -> 24
B48: 广西壮族自治区 | C48: 无 | D48: =广西!C12 -> -0.046699598 | E48: N/A | F48: N/A | G48: N/A | H48: N/A | I48: =MAX(D48:H48) -> -0.046699598 | J48: =RANK(I48,$I$24:$I$52,0) -> 25
B49: 云南省 | C49: 无 | D49: =云南!C12 -> -0.048324058 | E49: N/A | F49: N/A | G49: N/A | H49: N/A | I49: =MAX(D49:H49) -> -0.048324058 | J49: =RANK(I49,$I$24:$I$52,0) -> 26
B50: 上海市 | C50: 无 | D50: =上海!C12 -> -0.084807569 | E50: N/A | F50: N/A | G50: N/A | H50: N/A | I50: =MAX(D50:H50) -> -0.084807569 | J50: =RANK(I50,$I$24:$I$52,0) -> 27
B51: 甘肃省 | C51: 无 | D51: -0.099471148 | E51: N/A | F51: N/A | G51: N/A | H51: N/A | I51: =MAX(D51:H51) -> -0.099471148 | J51: =RANK(I51,$I$24:$I$52,0) -> 28
B52: 青海省 | C52: 无 | D52: =青海!C12 -> -0.10672909 | E52: N/A | F52: N/A | G52: N/A | H52: N/A | I52: =MAX(D52:H52) -> -0.10672909 | J52: =RANK(I52,$I$24:$I$52,0) -> 29
B54: 1）根据 [表后-用户侧储能-Base] 收益模型，按照典型储能项目规模计算；2）政府发放的补贴/补助资金按照全额缴纳企业所得税计算；3）根据电网公司代理购电价格峰谷价差计算

Sheet 各省峰谷价差
B1: xxx | C1: M2访谈数据/Assumption
B2: xxx | C2: 引用数据
B3: xxx | C3: 计算所得数据
B6: 全国（29省）电网代理购电电价统计
B7: 单位：元/度
B8: 区域 | C8: 省份 | D8: 企业用电属性 | E8: 企业用电电压等级 | F8: 收费类型 | G8: 时段 | H8: 时段是否适宜用户侧储能套利 | I8: 2021.12 | J8: 2022.1 | K8: 2022.2 | L8: 2022.3 | M8: 2022.4 | N8: STDEV.P | O8: AVERAGE
B9: 西北 | C9: 陕西省 | D9: 一般工商业用电 | E9: 35千伏 | F9: 不限 | G9: 峰 | H9: Base | I9: 0.879575 | J9: 0.855575 | K9: 0.830975 | L9: 0.858425 | M9: 0.835475 | N9: =_xlfn.STDEV.P(I9:M9) -> 0.017490386 | O9: 0.852005
B10: 西北 | C10: 陕西省 | D10: 一般工商业用电 | E10: 35千伏 | F10: 不限 | G10: 平 | H10: Base | I10: 0.601825 | J10: 0.585825 | K10: 0.569425 | L10: 0.587725 | M10: 0.572425 | N10: =_xlfn.STDEV.P(I10:M10) -> 0.011660257 | O10: 0.583445
B11: 西北 | C11: 陕西省 | D11: 一般工商业用电 | E11: 35千伏 | F11: 不限 | G11: 谷 | H11: Base | I11: 0.324075 | J11: 0.316075 | K11: 0.307875 | L11: 0.317025 | M11: 0.309375 | N11: =_xlfn.STDEV.P(I11:M11) -> 0.0058301286 | O11: 0.314885
B12: 西北 | C12: 青海省 | D12: 不限 | E12: 35千伏及以上 | F12: 单一制 | G12: 峰 | H12: Best | I12: 0.553975 | J12: 0.547687 | K12: 0.569692 | L12: 0.56252 | M12: 0.563009 | N12: =_xlfn.STDEV.P(I12:M12) -> 0.0076851389 | O12: 0.5593766
B13: 西北 | C13: 青海省 | D13: 不限 | E13: 35千伏及以上 | F13: 单一制 | G13: 平 | H13: Best | I13: 0.428325 | J13: 0.404425 | K13: 0.417925 | L13: 0.413525 | M13: 0.413825 | N13: =_xlfn.STDEV.P(I13:M13) -> 0.0077416794 | O13: 0.415605
B14: 西北 | C14: 青海省 | D14: 不限 | E14: 35千伏及以上 | F14: 单一制 | G14: 谷 | H14: Best | I14: 0.302675 | J14: 0.261163 | K14: 0.266158 | L14: 0.26453 | M14: 0.264641 | N14: =_xlfn.STDEV.P(I14:M14) -> 0.015507045 | O14: 0.2718334
B15: 西北 | C15: 宁夏 | D15: 一般工商业用电 | E15: 35-110千伏 | F15: 单一制 | G15: 峰 | H15: Base | I15: 0.693625 | J15: 0.716425 | K15: 0.723325 | L15: 0.723325 | M15: 0.723625 | N15: =_xlfn.STDEV.P(I15:M15) -> 0.011543414 | O15: 0.716065
B16: 西北 | C16: 宁夏 | D16: 一般工商业用电 | E16: 35-110千伏 | F16: 单一制 | G16: 平 | H16: Base | I16: 0.469525 | J16: 0.484725 | K16: 0.489325 | L16: 0.489325 | M16: 0.489525 | N16: =_xlfn.STDEV.P(I16:M16) -> 0.0076956091 | O16: 0.484485
B17: 西北 | C17: 宁夏 | D17: 一般工商业用电 | E17: 35-110千伏 | F17: 单一制 | G17: 谷 | H17: Base | I17: 0.245125 | J17: 0.253025 | K17: 0.255325 | L17: 0.255325 | M17: 0.226025 | N17: =_xlfn.STDEV.P(I17:M17) -> 0.011120899 | O17: 0.246965
B18: 西北 | C18: 甘肃省 | D18: 一般工商业用电 | E18: 35千伏及以上 | F18: 不限 | G18: 峰 | H18: Base | I18: 0.952475 | J18: 0.846025 | K18: 0.851325 | L18: 0.848625 | M18: 0.866125 | N18: =_xlfn.STDEV.P(I18:M18) -> 0.040385894 | O18: 0.872915
B19: 西北 | C19: 甘肃省 | D19: 一般工商业用电 | E19: 35千伏及以上 | F19: 不限 | G19: 平 | H19: Base | I19: 0.642625 | J19: 0.677025 | K19: 0.675025 | L19: 0.670225 | M19: 0.680925 | N19: =_xlfn.STDEV.P(I19:M19) -> 0.013710667 | O19: 0.669165
B20: 西北 | C20: 甘肃省 | D20: 一般工商业用电 | E20: 35千伏及以上 | F20: 不限 | G20: 谷 | H20: Base | I20: 0.332775 | J20: 0.508925 | K20: 0.516525 | L20: 0.592325 | M20: 0.510125 | N20: =_xlfn.STDEV.P(I20:M20) -> 0.085596801 | O20: 0.492135
... B47: 华北 | C47: 山西省 | D47: 一般工商业 | E47: 35千伏 | F47: 不限 | G47: 谷 | H47: Base | I47: 0.3159 | J47: 0.277963 | K47: 0.271813 | L47: 0.283856 | M47: 0.274 | N47: =_xlfn.STDEV.P(I47:M47) -> 0.016125161 | O47: 0.2847064
B48: 华中 | C48: 湖北省 | D48: 不限 | E48: 35千伏 | F48: 单一制 | G48: 峰 | H48: Best | I48: 1.071363 | J48: 1.065701 | K48: 1.094458 | L48: 1.095799 | M48: =(0.7104-0.0452)*1.49+0.0452 -> 1.036348 | N48: =_xlfn.STDEV.P(I48:M48) -> 0.021813804 | O48: 1.0727338
B49: 华中 | C49: 湖北省 | D49: 不限 | E49: 35千伏 | F49: 单一制 | G49: 平 | H49: Best | I49: 0.7339 | J49: 0.7301 | K49: 0.7494 | L49: 0.7503 | M49: 0.7104 | N49: =_xlfn.STDEV.P(I49:M49) -> 0.014640137 | O49: 0.73482
B50: 华中 | C50: 湖北省 | D50: 不限 | E50: 35千伏 | F50: 单一制 | G50: 谷 | H50: Best | I50: 0.375776 | J50: 0.373952 | K50: 0.383216 | L50: 0.383648 | M50: =(0.7104-0.0452)*0.48+0.0452 -> 0.364496 | N50: =_xlfn.STDEV.P(I50:M50) -> 0.0070272656 | O50: 0.3762176
B51: 华中 | C51: 湖南省 | D51: 一般工商业 | E51: 35千伏 | F51: 不限 | G51: 峰 | H51: Base | I51: 1.11773 | J51: 1.09607 | K51: 1.1666 | L51: 1.15698 | M51: 1.07161 | N51: =_xlfn.STDEV.P(I51:M51) -> 0.035895143 | O51: 1.121798
B52: 华中 | C52: 湖南省 | D52: 一般工商业 | E52: 35千伏 | F52: 不限 | G52: 平 | H52: Base | I52: 0.7493 | J52: 0.72764 | K52: 0.74647 | L52: 0.74045 | M52: 0.6871 | N52: =_xlfn.STDEV.P(I52:M52) -> 0.02279802 | O52: 0.730192
B53: 华中 | C53: 湖南省 | D53: 一般工商业 | E53: 35千伏 | F53: 不限 | G53: 谷 | H53: Base | I53: 0.38087 | J53: 0.35921 | K53: 0.32634 | L53: 0.32393 | M53: 0.30259 | N53: =_xlfn.STDEV.P(I53:M53) -> 0.02783437 | O53: 0.338588
B54: 华东 | C54: 江苏省 | D54: 普通工业用电；一般工商业及其他用电 | E54: 20-35千伏以下 | F54: 不限 | G54: 峰 | H54: Base | I54: 1.1399 | J54: 1.0851 | K54: 1.1096 | L54: 1.1466 | M54: 1.1496 | N54: =_xlfn.STDEV.P(I54:M54) -> 0.024964663 | O54: 1.12616
B55: 华东 | C55: 江苏省 | D55: 普通工业用电；一般工商业及其他用电 | E55: 20-35千伏以下 | F55: 不限 | G55: 平 | H55: Base | I55: 0.6818 | J55: 0.649 | K55: 0.6637 | L55: 0.6858 | M55: 0.6876 | N55: =_xlfn.STDEV.P(I55:M55) -> 0.014934845 | O55: 0.67358
B56: 华东 | C56: 江苏省 | D56: 普通工业用电；一般工商业及其他用电 | E56: 20-35千伏以下 | F56: 不限 | G56: 谷 | H56: Base | I56: 0.308 | J56: 0.2932 | K56: 0.2999 | L56: 0.3098 | M56: 0.3107 | N56: =_xlfn.STDEV.P(I56:M56) -> 0.0067448944 | O56: 0.30432
B57: 华东 | C57: 浙江省 | D57: 一般工商业及其他用电 | E57: 35千伏及以上 | F57: 不限 | G57: 尖 | H57: Base | I57: 1.267 | J57: 1.3224 | K57: 1.3269 | L57: 1.316 | M57: 1.3859 | N57: =_xlfn.STDEV.P(I57:M57) -> 0.037828381 | O57: 1.32364
B58: 华东 | C58: 浙江省 | D58: 一般工商业及其他用电 | E58: 35千伏及以上 | F58: 不限 | G58: 峰 | H58: Base | I58: 0.9431 | J58: 0.9843 | K58: 0.9877 | L58: 0.9795 | M58: 1.0315 | N58: =_xlfn.STDEV.P(I58:M58) -> 0.028127026 | O58: 0.98522
B59: 华东 | C59: 浙江省 | D59: 一般工商业及其他用电 | E59: 35千伏及以上 | F59: 不限 | G59: 谷 | H59: Base | I59: 0.3743 | J59: 0.3907 | K59: 0.392 | L59: 0.388 | M59: 0.4095 | N59: =_xlfn.STDEV.P(I59:M59) -> 0.01123548 | O59: 0.3909
B60: 华东 | C60: 安徽省 | D60: 不限 | E60: 35千伏 | F60: 单一制 | G60: 峰 | H60: Base | I60: 1.0111 | J60: 1.0111 | K60: 1.0196 | L60: 1.1274 | M60: 1.1309 | N60: =_xlfn.STDEV.P(I60:M60) -> 0.056540513 | O60: 1.06002
B61: 华东 | C61: 安徽省 | D61: 不限 | E61: 35千伏 | F61: 单一制 | G61: 平 | H61: Base | I61: 0.6667 | J61: 0.6667 | K61: 0.6752 | L61: 0.6746 | M61: 0.6781 | N61: =_xlfn.STDEV.P(I61:M61) -> 0.0046915243 | O61: 0.67226
B62: 华东 | C62: 安徽省 | D62: 不限 | E62: 35千伏 | F62: 单一制 | G62: 谷 | H62: Base | I62: 0.3988 | J62: 0.3988 | K62: 0.4073 | L62: 0.2995 | M62: 0.303 | N62: =_xlfn.STDEV.P(I62:M62) -> 0.049287865 | O62: 0.36148
... B95: 南方 | C95: 云南省（枯水期） | D95: 一般工商业及其他用电 | E95: 35千伏 | F95: 不限 | G95: 谷 | H95: Base | I95: 0.29845 | J95: 0.29845 | K95: 0.29845 | L95: 0.29845 | M95: 0.29845 | N95: =_xlfn.STDEV.P(I95:M95) -> 0 | O95: 0.29845
B96: Source：各省发改委；各省电网公司

Sheet >南方
B2: 部分省份的测算模型需要根据不同季节、时段的分时曲线进行下一阶段的优化：

Sheet 广西
B1: xxx | C1: M2访谈数据/Assumption
B2: xxx | C2: 引用数据
B3: xxx | C3: 计算所得数据
C4: 自变量 | D4: *表后用户侧储能主要通过现货形式进行峰谷套利，收益部分由峰负荷时的用户分摊
C5: 支出项 | D5: 关键假设：
C6: 收入项 | D6: 1）电池充放电循环次数~6525次
D7: 2）PCS成本：0.3元/W；电池充放电循环次数~6525次；容量型储能电站运维费用：0.1%；PCS效率：98%；线损：98%；系统使用天数：350天；充放循环次数（1次为1充1放）(次/天）：2次
B8: 更新处：标绿色的单元格 | D8: 3）充放策略：两充两放（1*谷-0.5*峰，0.5*平-1*峰）
B10: 省份 | C10: 广西壮族自治区 | D10: 备注：
B11: 有无补贴政策 | C11: 有
B12: IRR：不含补贴 | C12: -0.046699598
B13: IRR：含补贴（1） | C13: N/A
B14: 补贴（1）情况 | C14: N/A
B15: IRR：含补贴（2） | C15: N/A
B16: 补贴（2）情况 | C16: N/A
B17: 该省 Best IRR | C17: =MAX(C12:C16) -> -0.046699598
B19: 基本数据 | E19: 计算结果
B20: 充放策略：两充两放（1*谷-0.5*峰，0.5*平-1*峰） | E20: LCOS（元/kWh) | F20: =F51 -> 0.57176298
B21: 谷 | C21: 1 | E21: 投资回报率 | F21: =F56 -> -0.44170901
B22: 平 | C22: 0.5 | E22: NPV(折现率=7%） | F22: =SUM(F55:O55) -> -3.334903
B23: 峰 | C23: =C21+C22 -> 1.5 | E23: IRR | F23: =R56 -> -0.046699598
B24: 基本数据 | E24: 折现率 | F24: 0.07 | Q24: 折现率 | R24: 0
B25: PCS(KW） | C25: 1200 | E25: 所得税率 | F25: 0.25 | Q25: 所得税率 | R25: 0.25
B26: PCS成本（元/kW) | C26: 300 | E26: 增值税率 | F26: 0 | G26: 暂不考虑 | Q26: 增值税率 | R26: 0 | S26: 暂不考虑
B27: ESS(KWh) | C27: 4800 | E27: 储能系统经济效益估算表（元） | Q27: 储能系统经济效益估算表（元）
B28: ESS成本（元/kWh) | C28: 1400 | E28: 储能平准化成本LCOS（Levelized Cost of Storage） | G28: 1 | H28: 2 | I28: 3 | J28: 4 | K28: 5 | L28: 6 | M28: 7 | N28: 8 | O28: 9 | Q28: 储能平准化成本LCOS（Levelized Cost of Storage） | S28: 1 | T28: 2 | U28: 3 | V28: 4 | W28: 5 | X28: 6 | Y28: 7 | Z28: 8 | AA28: 9
B29: PCS效率 | C29: 0.98 | F29: 基准年 | G29: 第1年 | H29: 第2年 | I29: 第3年 | J29: 第4年 | K29: 第5年 | L29: 第6年 | M29: 第7年 | N29: 第8年 | O29: 第9年 | R29: 基准年 | S29: 第1年 | T29: 第2年 | U29: 第3年 | V29: 第4年 | W29: 第5年 | X29: 第6年 | Y29: 第7年 | Z29: 第8年 | AA29: 第9年
B30: 线损 | C30: 0.98 | E30: 初始投资成本（Mn RMB） | F30: =C54/1000000 -> 7.55 | Q30: 初始投资成本（Mn RMB） | R30: =C54/1000000 -> 7.55
B31: 峰价（元/KWh) | C31: 0.92516142 | E31: 折旧现值和（Mn RMB） | F31: =SUM(G32:O32) -> 3.7001106 | Q31: 折旧现值和（Mn RMB） | R31: =SUM(S32:AA32) -> 5.1112522
B32: 平价（元/KWh) | C32: 0.65748 | E32: 折旧现值（Mn RMB） | G32: =($C$49+$C$50+$C$40)*(1-$C$43)/$C$48/1000000/(1+$F$24)^G28 -> 0.53076347 | H32: =($C$49+$C$50+$C$40)*(1-$C$43)/$C$48/1000000/(1+$F$24)^H28 -> 0.49604063 | I32: =($C$49+$C$50+$C$40)*(1-$C$43)/$C$48/1000000/(1+$F$24)^I28 -> 0.46358937 | J32: =($C$49+$C$50+$C$40)*(1-$C$43)/$C$48/1000000/(1+$F$24)^J28 -> 0.43326109 | K32: =($C$49+$C$50+$C$40)*(1-$C$43)/$C$48/1000000/(1+$F$24)^K28 -> 0.40491691 | L32: =($C$49+$C$50+$C$40)*(1-$C$43)/$C$48/1000000/(1+$F$24)^L28 -> 0.37842702 | M32: =($C$49+$C$50+$C$40)*(1-$C$43)/$C$48/1000000/(1+$F$24)^M28 -> 0.35367011 | N32: =($C$49+$C$50+$C$40)*(1-$C$43)/$C$48/1000000/(1+$F$24)^N28 -> 0.33053281 | O32: =($C$49+$C$50+$C$40)*(1-$C$43)/$C$48/1000000/(1+$F$24)^O28 -> 0.30890917 | Q32: 折旧现值（Mn RMB） | S32: =($C$49+$C$50+$C$40)*(1-$C$43)/$C$48/1000000/(1+$R$24)^S28 -> 0.56791691 | T32: =($C$49+$C$50+$C$40)*(1-$C$43)/$C$48/1000000/(1+$R$24)^T28 -> 0.56791691 | U32: =($C$49+$C$50+$C$40)*(1-$C$43)/$C$48/1000000/(1+$R$24)^U28 -> 0.56791691 | V32: =($C$49+$C$50+$C$40)*(1-$C$43)/$C$48/1000000/(1+$R$24)^V28 -> 0.56791691 | W32: =($C$49+$C$50+$C$40)*(1-$C$43)/$C$48/1000000/(1+$R$24)^W28 -> 0.56791691 | X32: =($C$49+$C$50+$C$40)*(1-$C$43)/$C$48/1000000/(1+$R$24)^X28 -> 0.56791691 | Y32: =($C$49+$C$50+$C$40)*(1-$C$43)/$C$48/1000000/(1+$R$24)^Y28 -> 0.56791691 | Z32: =($C$49+$C$50+$C$40)*(1-$C$43)/$C$48/1000000/(1+$R$24)^Z28 -> 0.56791691 | AA32: =($C$49+$C$50+$C$40)*(1-$C$43)/$C$48/1000000/(1+$R$24)^AA28 -> 0.56791691
B33: 谷价（元/KWh) | C33: 0.38981798 | E33: 运行成本现值和（Mn RMB） | F33: =SUM(G34:O34) -> 0.049190003 | Q33: 运行成本现值和（Mn RMB） | R33: =SUM(S34:AA34) -> 0.06795
B34: 系统年使用天数 (天) | C34: 350 | E34: 运行成本现值（Mn RMB） | G34: =($C$42*$F$30)/((1+$F$24)^G28) -> 0.0070560748 | H34: =($C$42*$F$30)/((1+$F$24)^H28) -> 0.0065944624 | I34: =($C$42*$F$30)/((1+$F$24)^I28) -> 0.006163049 | J34: =($C$42*$F$30)/((1+$F$24)^J28) -> 0.0057598589 | K34: =($C$42*$F$30)/((1+$F$24)^K28) -> 0.0053830457 | L34: =($C$42*$F$30)/((1+$F$24)^L28) -> 0.0050308838 | M34: =($C$42*$F$30)/((1+$F$24)^M28) -> 0.0047017606 | N34: =($C$42*$F$30)/((1+$F$24)^N28) -> 0.0043941687 | O34: =($C$42*$F$30)/((1+$F$24)^O28) -> 0.0041066998 | Q34: 运行成本现值（Mn RMB） | S34: =($C$42*$R$30)/((1+$R$24)^S28) -> 0.00755 | T34: =($C$42*$R$30)/((1+$R$24)^T28) -> 0.00755 | U34: =($C$42*$R$30)/((1+$R$24)^U28) -> 0.00755 | V34: =($C$42*$R$30)/((1+$R$24)^V28) -> 0.00755 | W34: =($C$42*$R$30)/((1+$R$24)^W28) -> 0.00755 | X34: =($C$42*$R$30)/((1+$R$24)^X28) -> 0.00755 | Y34: =($C$42*$R$30)/((1+$R$24)^Y28) -> 0.00755 | Z34: =($C$42*$R$30)/((1+$R$24)^Z28) -> 0.00755 | AA34: =($C$42*$R$30)/((1+$R$24)^AA28) -> 0.00755
B35: DOD% | C35: 0.95 | E35: 固定资产残值现值 (Mn RMB) | O35: =(C49+C50)*C43/((1+F24)^O28)/1000000 -> 0.19255254 | Q35: 固定资产残值现值 (Mn RMB) | AA35: =(C49+C50)*C43/((1+R24)^AA28)/1000000 -> 0.354
B36: 单次循环衰减率 | C36: 4.68e-05 | E36: 充电电量现值和(KWh) | F36: =SUM(G37:O37) -> 15534030 | Q36: 充电电量现值和(KWh) | R36: =SUM(S37:AA37) -> 21224302
B37: 系统报废终止标准 | C37: 0.7 | E37: 充电电量现值(KWh) | G37: =$C$27*$C$44*$C$34/$C$45*($C$35*(1-$C$36)^((G28-1)*$C$34*$C$44))/$C$29/$C$30/((1+$F$24)^G28) -> 2426705 | H37: =$C$27*$C$44*$C$34/$C$45*($C$35*(1-$C$36)^((H28-1)*$C$34*$C$44))/$C$29/$C$30/((1+$F$24)^H28) -> 2212902.8 | I37: =$C$27*$C$44*$C$34/$C$45*($C$35*(1-$C$36)^((I28-1)*$C$34*$C$44))/$C$29/$C$30/((1+$F$24)^I28) -> 2017937.4 | J37: =$C$27*$C$44*$C$34/$C$45*($C$35*(1-$C$36)^((J28-1)*$C$34*$C$44))/$C$29/$C$30/((1+$F$24)^J28) -> 1840149.3 | K37: =$C$27*$C$44*$C$34/$C$45*($C$35*(1-$C$36)^((K28-1)*$C$34*$C$44))/$C$29/$C$30/((1+$F$24)^K28) -> 1678024.9 | L37: =$C$27*$C$44*$C$34/$C$45*($C$35*(1-$C$36)^((L28-1)*$C$34*$C$44))/$C$29/$C$30/((1+$F$24)^L28) -> 1530184.4 | M37: =$C$27*$C$44*$C$34/$C$45*($C$35*(1-$C$36)^((M28-1)*$C$34*$C$44))/$C$29/$C$30/((1+$F$24)^M28) -> 1395369.2 | N37: =$C$27*$C$44*$C$34/$C$45*($C$35*(1-$C$36)^((N28-1)*$C$34*$C$44))/$C$29/$C$30/((1+$F$24)^N28) -> 1272431.7 | O37: =$C$27*$C$44*$C$34/$C$45*($C$35*(1-$C$36)^((O28-1)*$C$34*$C$44))/$C$29/$C$30/((1+$F$24)^O28) -> 1160325.5 | Q37: 充电电量现值(KWh) | S37: =$C$27*$C$44*$C$34/$C$45*($C$35*(1-$C$36)^((S28-1)*$C$34*$C$44))/$C$29/$C$30/((1+$R$24)^S28) -> 2596574.3 | T37: =$C$27*$C$44*$C$34/$C$45*($C$35*(1-$C$36)^((T28-1)*$C$34*$C$44))/$C$29/$C$30/((1+$R$24)^T28) -> 2533552.4 | U37: =$C$27*$C$44*$C$34/$C$45*($C$35*(1-$C$36)^((U28-1)*$C$34*$C$44))/$C$29/$C$30/((1+$R$24)^U28) -> 2472060.1 | V37: =$C$27*$C$44*$C$34/$C$45*($C$35*(1-$C$36)^((V28-1)*$C$34*$C$44))/$C$29/$C$30/((1+$R$24)^V28) -> 2412060.3 | W37: =$C$27*$C$44*$C$34/$C$45*($C$35*(1-$C$36)^((W28-1)*$C$34*$C$44))/$C$29/$C$30/((1+$R$24)^W28) -> 2353516.8 | X37: =$C$27*$C$44*$C$34/$C$45*($C$35*(1-$C$36)^((X28-1)*$C$34*$C$44))/$C$29/$C$30/((1+$R$24)^X28) -> 2296394.2 | Y37: =$C$27*$C$44*$C$34/$C$45*($C$35*(1-$C$36)^((Y28-1)*$C$34*$C$44))/$C$29/$C$30/((1+$R$24)^Y28) -> 2240658 | Z37: =$C$27*$C$44*$C$34/$C$45*($C$35*(1-$C$36)^((Z28-1)*$C$34*$C$44))/$C$29/$C$30/((1+$R$24)^Z28) -> 2186274.6 | AA37: =$C$27*$C$44*$C$34/$C$45*($C$35*(1-$C$36)^((AA28-1)*$C$34*$C$44))/$C$29/$C$30/((1+$R$24)^AA28) -> 2133211.1
B38: 土建成本(元/Wh) | C38: 0.015 | E38: 放电电量现值和(KWh) | F38: =SUM(G39:O39) -> 13204772 | Q38: 放电电量现值和(KWh) | R38: =SUM(S39:AA39) -> 18041813
B39: 土建残值率（%） | C39: 0 | E39: 放电电量现值(KWh) | G39: =$C$27*$C$44*$C$34*$C$45*($C$35*(1-$C$36)^((G28-1)*$C$34*$C$44))*$C$29*$C$30/((1+$F$24)^G28) -> 2062831.5 | H39: =$C$27*$C$44*$C$34*$C$45*($C$35*(1-$C$36)^((H28-1)*$C$34*$C$44))*$C$29*$C$30/((1+$F$24)^H28) -> 1881088 | I39: =$C$27*$C$44*$C$34*$C$45*($C$35*(1-$C$36)^((I28-1)*$C$34*$C$44))*$C$29*$C$30/((1+$F$24)^I28) -> 1715356.8 | J39: =$C$27*$C$44*$C$34*$C$45*($C$35*(1-$C$36)^((J28-1)*$C$34*$C$44))*$C$29*$C$30/((1+$F$24)^J28) -> 1564227.2 | K39: =$C$27*$C$44*$C$34*$C$45*($C$35*(1-$C$36)^((K28-1)*$C$34*$C$44))*$C$29*$C$30/((1+$F$24)^K28) -> 1426412.6 | L39: =$C$27*$C$44*$C$34*$C$45*($C$35*(1-$C$36)^((L28-1)*$C$34*$C$44))*$C$29*$C$30/((1+$F$24)^L28) -> 1300740.1 | M39: =$C$27*$C$44*$C$34*$C$45*($C$35*(1-$C$36)^((M28-1)*$C$34*$C$44))*$C$29*$C$30/((1+$F$24)^M28) -> 1186139.8 | N39: =$C$27*$C$44*$C$34*$C$45*($C$35*(1-$C$36)^((N28-1)*$C$34*$C$44))*$C$29*$C$30/((1+$F$24)^N28) -> 1081636.3 | O39: =$C$27*$C$44*$C$34*$C$45*($C$35*(1-$C$36)^((O28-1)*$C$34*$C$44))*$C$29*$C$30/((1+$F$24)^O28) -> 986339.92 | Q39: 放电电量现值(KWh) | S39: =$C$27*$C$44*$C$34*$C$45*($C$35*(1-$C$36)^((S28-1)*$C$34*$C$44))*$C$29*$C$30/((1+$R$24)^S28) -> 2207229.7 | T39: =$C$27*$C$44*$C$34*$C$45*($C$35*(1-$C$36)^((T28-1)*$C$34*$C$44))*$C$29*$C$30/((1+$R$24)^T28) -> 2153657.6 | U39: =$C$27*$C$44*$C$34*$C$45*($C$35*(1-$C$36)^((U28-1)*$C$34*$C$44))*$C$29*$C$30/((1+$R$24)^U28) -> 2101385.8 | V39: =$C$27*$C$44*$C$34*$C$45*($C$35*(1-$C$36)^((V28-1)*$C$34*$C$44))*$C$29*$C$30/((1+$R$24)^V28) -> 2050382.7 | W39: =$C$27*$C$44*$C$34*$C$45*($C$35*(1-$C$36)^((W28-1)*$C$34*$C$44))*$C$29*$C$30/((1+$R$24)^W28) -> 2000617.5 | X39: =$C$27*$C$44*$C$34*$C$45*($C$35*(1-$C$36)^((X28-1)*$C$34*$C$44))*$C$29*$C$30/((1+$R$24)^X28) -> 1952060.2 | Y39: =$C$27*$C$44*$C$34*$C$45*($C$35*(1-$C$36)^((Y28-1)*$C$34*$C$44))*$C$29*$C$30/((1+$R$24)^Y28) -> 1904681.4 | Z39: =$C$27*$C$44*$C$34*$C$45*($C$35*(1-$C$36)^((Z28-1)*$C$34*$C$44))*$C$29*$C$30/((1+$R$24)^Z28) -> 1858452.5 | AA39: =$C$27*$C$44*$C$34*$C$45*($C$35*(1-$C$36)^((AA28-1)*$C$34*$C$44))*$C$29*$C$30/((1+$R$24)^AA28) -> 1813345.7
B40: 其它设备投资费用（升压变等） | C40: 350000 | E40: 充电成本现值和（Mn RMB） | F40: =SUM(G41:O41) -> 7.4414009 | Q40: 充电成本现值和（Mn RMB） | R40: =SUM(S41:AA41) -> 10.167261
B41: 其它成本：入网检测费、项目管理费等（元/Wh） | C41: 0.01 | E41: 充电成本现值（Mn RMB） | G41: =($C$21*$C$33*G37/($C$21+$C$22)+$C$22*$C$32*G37/($C$21+$C$22))/1000000 -> 1.1624855 | H41: =($C$21*$C$33*H37/($C$21+$C$22)+$C$22*$C$32*H37/($C$21+$C$22))/1000000 -> 1.060066 | I41: =($C$21*$C$33*I37/($C$21+$C$22)+$C$22*$C$32*I37/($C$21+$C$22))/1000000 -> 0.96667003 | J41: =($C$21*$C$33*J37/($C$21+$C$22)+$C$22*$C$32*J37/($C$21+$C$22))/1000000 -> 0.88150263 | K41: =($C$21*$C$33*K37/($C$21+$C$22)+$C$22*$C$32*K37/($C$21+$C$22))/1000000 -> 0.80383881 | L41: =($C$21*$C$33*L37/($C$21+$C$22)+$C$22*$C$32*L37/($C$21+$C$22))/1000000 -> 0.73301747 | M41: =($C$21*$C$33*M37/($C$21+$C$22)+$C$22*$C$32*M37/($C$21+$C$22))/1000000 -> 0.66843577 | N41: =($C$21*$C$33*N37/($C$21+$C$22)+$C$22*$C$32*N37/($C$21+$C$22))/1000000 -> 0.60954397 | O41: =($C$21*$C$33*O37/($C$21+$C$22)+$C$22*$C$32*O37/($C$21+$C$22))/1000000 -> 0.55584077 | Q41: 充电成本现值（Mn RMB） | S41: =($C$21*$C$33*S37/($C$21+$C$22)+$C$22*$C$32*S37/($C$21+$C$22))/1000000 -> 1.2438595 | T41: =($C$21*$C$33*T37/($C$21+$C$22)+$C$22*$C$32*T37/($C$21+$C$22))/1000000 -> 1.2136695 | U41: =($C$21*$C$33*U37/($C$21+$C$22)+$C$22*$C$32*U37/($C$21+$C$22))/1000000 -> 1.1842124 | V41: =($C$21*$C$33*V37/($C$21+$C$22)+$C$22*$C$32*V37/($C$21+$C$22))/1000000 -> 1.1554701 | W41: =($C$21*$C$33*W37/($C$21+$C$22)+$C$22*$C$32*W37/($C$21+$C$22))/1000000 -> 1.1274255 | X41: =($C$21*$C$33*X37/($C$21+$C$22)+$C$22*$C$32*X37/($C$21+$C$22))/1000000 -> 1.1000616 | Y41: =($C$21*$C$33*Y37/($C$21+$C$22)+$C$22*$C$32*Y37/($C$21+$C$22))/1000000 -> 1.0733618 | Z41: =($C$21*$C$33*Z37/($C$21+$C$22)+$C$22*$C$32*Z37/($C$21+$C$22))/1000000 -> 1.04731 | AA41: =($C$21*$C$33*AA37/($C$21+$C$22)+$C$22*$C$32*AA37/($C$21+$C$22))/1000000 -> 1.0218906
B42: 容量型储能电站运维费用 | C42: 0.001 | E42: 放电收益现值和（Mn RMB） | F42: =SUM(G43:O43) -> 12.216546 | Q42: 放电收益现值和（Mn RMB） | R42: =SUM(S43:AA43) -> 16.69159
B43: 储能系统残值 | C43: 0.05 | E43: 放电收益现值（Mn RMB） | G43: =(G39*$C$31/1000000) -> 1.9084521 | H43: =(H39*$C$31/1000000) -> 1.74031 | I43: =(I39*$C$31/1000000) -> 1.5869819 | J43: =(J39*$C$31/1000000) -> 1.4471626 | K43: =(K39*$C$31/1000000) -> 1.319662 | L43: =(L39*$C$31/1000000) -> 1.2033946 | M43: =(M39*$C$31/1000000) -> 1.0973708 | N43: =(N39*$C$31/1000000) -> 1.0006882 | O43: =(O39*$C$31/1000000) -> 0.91252364 | Q43: 放电收益现值（Mn RMB） | S43: =(S39*$C$31/1000000) -> 2.0420438 | T43: =(T39*$C$31/1000000) -> 1.992481 | U43: =(U39*$C$31/1000000) -> 1.9441211 | V43: =(V39*$C$31/1000000) -> 1.896935 | W43: =(W39*$C$31/1000000) -> 1.8508942 | X43: =(X39*$C$31/1000000) -> 1.8059708 | Y43: =(Y39*$C$31/1000000) -> 1.7621377 | Z43: =(Z39*$C$31/1000000) -> 1.7193686 | AA43: =(AA39*$C$31/1000000) -> 1.6776375
B44: 充放循环次数（1次为1充1放）(次/天） | C44: =C21+C22 -> 1.5 | E44: 所得税现值和（Mn RMB） | F44: =SUM(G45:O45) -> 0.25646109 | Q44: 所得税现值和（Mn RMB） | R44: =SUM(S45:AA45) -> 0.33628159
B45: 充放电效率RTE（%） | C45: 0.96 | E45: 所得税现值（Mn RMB） | G45: =(G43-G41-G34-G32)*$F$25 -> 0.052036769 | H45: =(H43-H41-H34-H32)*$F$25 -> 0.04440224 | I45: =(I43-I41-I34-I32)*$F$25 -> 0.037639869 | J45: =(J43-J41-J34-J32)*$F$25 -> 0.031659761 | K45: =(K43-K41-K34-K32)*$F$25 -> 0.026380797 | L45: =(L43-L41-L34-L32)*$F$25 -> 0.021729802 | M45: =(M43-M41-M34-M32)*$F$25 -> 0.017640795 | N45: =(N43-N41-N34-N32)*$F$25 -> 0.014054304 | O45: =(O43-O41-O34-O32)*$F$25 -> 0.01091675 | Q45: 所得税现值（Mn RMB） | S45: =(S43-S41-S34-S32)*$R$25 -> 0.055679343 | T45: =(T43-T41-T34-T32)*$R$25 -> 0.050836125 | U45: =(U43-U41-U34-U32)*$R$25 -> 0.046110458 | V45: =(V43-V41-V34-V32)*$R$25 -> 0.041499488 | W45: =(W43-W41-W34-W32)*$R$25 -> 0.037000432 | X45: =(X43-X41-X34-X32)*$R$25 -> 0.032610574 | Y45: =(Y43-Y41-Y34-Y32)*$R$25 -> 0.028327262 | Z45: =(Z43-Z41-Z34-Z32)*$R$25 -> 0.024147912 | AA45: =(AA43-AA41-AA34-AA32)*$R$25 -> 0.020069999
B46: 用户分成比例（%） | C46: 0.1 | E46: 增值税现值和（Mn RMB） | F46: =SUM(G47:O47) -> 0 | Q46: 增值税现值和（Mn RMB） | R46: =SUM(S47:AA47) -> 0
B47: 充放循环总次数（次数） | C47: =LOG(C37/C35,(1-C36)) -> 6525.0962 | E47: 增值税现值（Mn RMB） | G47: =(G43-G41)*$F$26 -> 0 | H47: =(H43-H41)*$F$26 -> 0 | I47: =(I43-I41)*$F$26 -> 0 | J47: =(J43-J41)*$F$26 -> 0 | K47: =(K43-K41)*$F$26 -> 0 | L47: =(L43-L41)*$F$26 -> 0 | M47: =(M43-M41)*$F$26 -> 0 | N47: =(N43-N41)*$F$26 -> 0 | O47: =(O43-O41)*$F$26 -> 0 | Q47: 增值税现值（Mn RMB） | S47: =(S43-S41)*$R$26 -> 0 | T47: =(T43-T41)*$R$26 -> 0 | U47: =(U43-U41)*$R$26 -> 0 | V47: =(V43-V41)*$R$26 -> 0 | W47: =(W43-W41)*$R$26 -> 0 | X47: =(X43-X41)*$R$26 -> 0 | Y47: =(Y43-Y41)*$R$26 -> 0 | Z47: =(Z43-Z41)*$R$26 -> 0 | AA47: =(AA43-AA41)*$R$26 -> 0
B48: 系统寿命（年） | C48: =C47/C44/C34 -> 12.428755 | E48: 放电利润现值和（Mn RMB） | F48: =SUM(G49:O49) -> 4.4694938 | Q48: 放电利润现值和（Mn RMB） | R48: =SUM(S49:AA49) -> 6.120097
B49: PCS总成本（元） | C49: =C26*C25 -> 360000 | E49: 放电利润现值和（Mn RMB） | G49: =G43-G41-G45-G47-G34 -> 0.68687378 | H49: =H43-H41-H45-H47-H34 -> 0.62924735 | I49: =I43-I41-I45-I47-I34 -> 0.57650898 | J49: =J43-J41-J45-J47-J34 -> 0.52824038 | K49: =K43-K41-K45-K47-K34 -> 0.4840593 | L49: =L43-L41-L45-L47-L34 -> 0.44361642 | M49: =M43-M41-M45-M47-M34 -> 0.4065925 | N49: =N43-N41-N45-N47-N34 -> 0.37269573 | O49: =O43-O41-O45-O47-O34 -> 0.34165942 | Q49: 放电利润现值和（Mn RMB） | S49: =S43-S41-S45-S47-S34 -> 0.73495494 | T49: =T43-T41-T45-T47-T34 -> 0.72042529 | U49: =U43-U41-U45-U47-U34 -> 0.70624829 | V49: =V43-V41-V45-V47-V34 -> 0.69241538 | W49: =W43-W41-W45-W47-W34 -> 0.67891821 | X49: =X43-X41-X45-X47-X34 -> 0.66574863 | Y49: =Y43-Y41-Y45-Y47-Y34 -> 0.6528987 | Z49: =Z43-Z41-Z45-Z47-Z34 -> 0.64036065 | AA49: =AA43-AA41-AA45-AA47-AA34 -> 0.62812691
B50: ESS总成本（元） | C50: =C27*C28 -> 6720000 | E50: 度电收益（元/kWh) | F50: =C31 -> 0.92516142 | Q50: 度电收益（元/kWh) | R50: =C31 -> 0.92516142
B51: 土建总投资（元） | C51: =C38*C27*1000 -> 72000 | E51: LCOS（元/kWh) | F51: =F30/F38*1000000 -> 0.57176298 | Q51: LCOS（元/kWh) | R51: =R30/R38*1000000 -> 0.41847235
B52: 其它投资（元） | C52: =C41*C27*1000 -> 48000 | E52: 充电成本（元/kWh) | F52: =F40*1000000/F38 -> 0.56353876 | Q52: 充电成本（元/kWh) | R52: =R40*1000000/R38 -> 0.56353876
B53: 设备购置补助（元） | C53: 0 | E53: 用户分成部分（元/kWh) | F53: =SUM(G54:O54) -> 0.44694938 | Q53: 用户分成部分（元/kWh) | R53: =SUM(S54:AA54) -> 0.6120097
B54: 设备总投资（元） | C54: =(C52+C51+C50+C49+C40-C53) -> 7550000 | E54: 用户分成部分现值 | G54: =G49*$C$46 -> 0.068687378 | H54: =H49*$C$46 -> 0.062924735 | I54: =I49*$C$46 -> 0.057650898 | J54: =J49*$C$46 -> 0.052824038 | K54: =K49*$C$46 -> 0.04840593 | L54: =L49*$C$46 -> 0.044361642 | M54: =M49*$C$46 -> 0.04065925 | N54: =N49*$C$46 -> 0.037269573 | O54: =O49*$C$46 -> 0.034165942 | Q54: 用户分成部分现值 | S54: =S49*$C$46 -> 0.073495494 | T54: =T49*$C$46 -> 0.072042529 | U54: =U49*$C$46 -> 0.070624829 | V54: =V49*$C$46 -> 0.069241538 | W54: =W49*$C$46 -> 0.067891821 | X54: =X49*$C$46 -> 0.066574863 | Y54: =Y49*$C$46 -> 0.06528987 | Z54: =Z49*$C$46 -> 0.064036065 | AA54: =AA49*$C$46 -> 0.062812691
B55: 投资回收年限 | C55: 9+ | E55: NPV | F55: =-(F30) -> -7.55 | G55: =G43-G41-G54-G45-G47-G34 -> 0.6181864 | H55: =H43-H41-H54-H45-H47-H34 -> 0.56632261 | I55: =I43-I41-I54-I45-I47-I34 -> 0.51885808 | J55: =J43-J41-J54-J45-J47-J34 -> 0.47541634 | K55: =K43-K41-K54-K45-K47-K34 -> 0.43565337 | L55: =L43-L41-L54-L45-L47-L34 -> 0.39925478 | M55: =M43-M41-M54-M45-M47-M34 -> 0.36593325 | N55: =N43-N41-N54-N45-N47-N34 -> 0.33542615 | O55: =O43-O41-O54-O45-O47-O34+O35 -> 0.50004602 | Q55: NPV | R55: =-(R30) -> -7.55 | S55: =S43-S41-S54-S45-S47-S34 -> 0.66145945 | T55: =T43-T41-T54-T45-T47-T34 -> 0.64838276 | U55: =U43-U41-U54-U45-U47-U34 -> 0.63562346 | V55: =V43-V41-V54-V45-V47-V34 -> 0.62317384 | W55: =W43-W41-W54-W45-W47-W34 -> 0.61102639 | X55: =X43-X41-X54-X45-X47-X34 -> 0.59917377 | Y55: =Y43-Y41-Y54-Y45-Y47-Y34 -> 0.58760883 | Z55: =Z43-Z41-Z54-Z45-Z47-Z34 -> 0.57632458 | AA55: =AA43-AA41-AA54-AA45-AA47-AA34+AA35 -> 0.91931422
B56: 投资回报率 | C56: =F56 -> -0.44170901 | E56: 投资回报率 | F56: =SUM(F55:O55)/F30 -> -0.44170901 | Q56: IRR | R56: =IRR(R55:AA55) -> -0.046699598

Sheet 广东
B1: xxx | C1: M2访谈数据/Assumption
B2: xxx | C2: 引用数据
B3: xxx | C3: 计算所得数据
C4: 自变量 | D4: *表后用户侧储能主要通过现货形式进行峰谷套利，收益部分由峰负荷时的用户分摊
C5: 支出项 | D5: 关键假设：
C6: 收入项 | D6: 1）电池充放电循环次数~6525次
D7: 2）PCS成本：0.3元/W；电池充放电循环次数~6525次；容量型储能电站运维费用：0.1%；PCS效率：98%；线损：98%；系统使用天数：350天；充放循环次数（1次为1充1放）(次/天）：2次
B8: 更新处：标绿色的单元格 | D8: 3）充放策略：两充两放（1*谷-0.5*峰，0.5*平-1*峰）
B10: 省份 | C10: 广东省（珠三角五市） | D10: 备注：分季度存在尖峰时段；实际IRR应大于模型测算
B11: 有无补贴政策 | C11: 有
B12: IRR：不含补贴 | C12: 0.063921609
B13: IRR：含补贴（1） | C13: 0.073511721
B14: 补贴（1）情况 | C14: 佛山市顺德区勒流街道
B15: IRR：含补贴（2） | C15: 0.069874942
B16: 补贴（2）情况 | C16: 佛山市顺德区容桂街道、龙江镇
B17: 该省 Best IRR | C17: =MAX(C12:C16) -> 0.073511721
B19: 基本数据 | E19: 计算结果
B20: 充放策略：两充两放（1*谷-0.5*峰，0.5*平-1*峰） | E20: LCOS（元/kWh) | F20: =F51 -> 0.57176298
B21: 谷 | C21: 1 | E21: 投资回报率 | F21: =F56 -> 0.0012355974
B22: 平 | C22: 0.5 | E22: NPV(折现率=7%） | F22: =SUM(F55:O55) -> 0.0093287601
B23: 峰 | C23: 1.5 | E23: IRR | F23: =R56 -> 0.069874942
B24: 基本数据 | E24: 折现率 | F24: 0.07 | Q24: 折现率 | R24: 0
B25: PCS(KW） | C25: 1200 | E25: 所得税率 | F25: 0.25 | Q25: 所得税率 | R25: 0.25
B26: PCS成本（元/kW) | C26: 300 | E26: 增值税率 | F26: 0 | G26: 暂不考虑 | Q26: 增值税率 | R26: 0 | S26: 暂不考虑
B27: ESS(KWh) | C27: 4800 | E27: 储能系统经济效益估算表（元） | Q27: 储能系统经济效益估算表（元）
B28: ESS成本（元/kWh) | C28: 1400 | E28: 储能平准化成本LCOS（Levelized Cost of Storage） | G28: 1 | H28: 2 | I28: 3 | J28: 4 | K28: 5 | L28: 6 | M28: 7 | N28: 8 | O28: 9 | Q28: 储能平准化成本LCOS（Levelized Cost of Storage） | S28: 1 | T28: 2 | U28: 3 | V28: 4 | W28: 5 | X28: 6 | Y28: 7 | Z28: 8 | AA28: 9
B29: PCS效率 | C29: 0.98 | F29: 基准年 | G29: 第1年 | H29: 第2年 | I29: 第3年 | J29: 第4年 | K29: 第5年 | L29: 第6年 | M29: 第7年 | N29: 第8年 | O29: 第9年 | R29: 基准年 | S29: 第1年 | T29: 第2年 | U29: 第3年 | V29: 第4年 | W29: 第5年 | X29: 第6年 | Y29: 第7年 | Z29: 第8年 | AA29: 第9年
B30: 线损 | C30: 0.98 | E30: 初始投资成本（Mn RMB） | F30: =C54/1000000 -> 7.55 | Q30: 初始投资成本（Mn RMB） | R30: =C54/1000000 -> 7.55
B31: 峰价（元/KWh) | C31: 1.2380088 | E31: 折旧现值和（Mn RMB） | F31: =SUM(G32:O32) -> 3.7001106 | Q31: 折旧现值和（Mn RMB） | R31: =SUM(S32:AA32) -> 5.1112522
B32: 平价（元/KWh) | C32: 0.73962877 | E32: 折旧现值（Mn RMB） | G32: =($C$49+$C$50+$C$40)*(1-$C$43)/$C$48/1000000/(1+$F$24)^G28 -> 0.53076347 | H32: =($C$49+$C$50+$C$40)*(1-$C$43)/$C$48/1000000/(1+$F$24)^H28 -> 0.49604063 | I32: =($C$49+$C$50+$C$40)*(1-$C$43)/$C$48/1000000/(1+$F$24)^I28 -> 0.46358937 | J32: =($C$49+$C$50+$C$40)*(1-$C$43)/$C$48/1000000/(1+$F$24)^J28 -> 0.43326109 | K32: =($C$49+$C$50+$C$40)*(1-$C$43)/$C$48/1000000/(1+$F$24)^K28 -> 0.40491691 | L32: =($C$49+$C$50+$C$40)*(1-$C$43)/$C$48/1000000/(1+$F$24)^L28 -> 0.37842702 | M32: =($C$49+$C$50+$C$40)*(1-$C$43)/$C$48/1000000/(1+$F$24)^M28 -> 0.35367011 | N32: =($C$49+$C$50+$C$40)*(1-$C$43)/$C$48/1000000/(1+$F$24)^N28 -> 0.33053281 | O32: =($C$49+$C$50+$C$40)*(1-$C$43)/$C$48/1000000/(1+$F$24)^O28 -> 0.30890917 | Q32: 折旧现值（Mn RMB） | S32: =($C$49+$C$50+$C$40)*(1-$C$43)/$C$48/1000000/(1+$R$24)^S28 -> 0.56791691 | T32: =($C$49+$C$50+$C$40)*(1-$C$43)/$C$48/1000000/(1+$R$24)^T28 -> 0.56791691 | U32: =($C$49+$C$50+$C$40)*(1-$C$43)/$C$48/1000000/(1+$R$24)^U28 -> 0.56791691 | V32: =($C$49+$C$50+$C$40)*(1-$C$43)/$C$48/1000000/(1+$R$24)^V28 -> 0.56791691 | W32: =($C$49+$C$50+$C$40)*(1-$C$43)/$C$48/1000000/(1+$R$24)^W28 -> 0.56791691 | X32: =($C$49+$C$50+$C$40)*(1-$C$43)/$C$48/1000000/(1+$R$24)^X28 -> 0.56791691 | Y32: =($C$49+$C$50+$C$40)*(1-$C$43)/$C$48/1000000/(1+$R$24)^Y28 -> 0.56791691 | Z32: =($C$49+$C$50+$C$40)*(1-$C$43)/$C$48/1000000/(1+$R$24)^Z28 -> 0.56791691 | AA32: =($C$49+$C$50+$C$40)*(1-$C$43)/$C$48/1000000/(1+$R$24)^AA28 -> 0.56791691
B33: 谷价（元/KWh) | C33: 0.29820877 | E33: 运行成本现值和（Mn RMB） | F33: =SUM(G34:O34) -> 0.049190003 | Q33: 运行成本现值和（Mn RMB） | R33: =SUM(S34:AA34) -> 0.06795
B34: 系统年使用天数 (天) | C34: 350 | E34: 运行成本现值（Mn RMB） | G34: =($C$42*$F$30)/((1+$F$24)^G28) -> 0.0070560748 | H34: =($C$42*$F$30)/((1+$F$24)^H28) -> 0.0065944624 | I34: =($C$42*$F$30)/((1+$F$24)^I28) -> 0.006163049 | J34: =($C$42*$F$30)/((1+$F$24)^J28) -> 0.0057598589 | K34: =($C$42*$F$30)/((1+$F$24)^K28) -> 0.0053830457 | L34: =($C$42*$F$30)/((1+$F$24)^L28) -> 0.0050308838 | M34: =($C$42*$F$30)/((1+$F$24)^M28) -> 0.0047017606 | N34: =($C$42*$F$30)/((1+$F$24)^N28) -> 0.0043941687 | O34: =($C$42*$F$30)/((1+$F$24)^O28) -> 0.0041066998 | Q34: 运行成本现值（Mn RMB） | S34: =($C$42*$R$30)/((1+$R$24)^S28) -> 0.00755 | T34: =($C$42*$R$30)/((1+$R$24)^T28) -> 0.00755 | U34: =($C$42*$R$30)/((1+$R$24)^U28) -> 0.00755 | V34: =($C$42*$R$30)/((1+$R$24)^V28) -> 0.00755 | W34: =($C$42*$R$30)/((1+$R$24)^W28) -> 0.00755 | X34: =($C$42*$R$30)/((1+$R$24)^X28) -> 0.00755 | Y34: =($C$42*$R$30)/((1+$R$24)^Y28) -> 0.00755 | Z34: =($C$42*$R$30)/((1+$R$24)^Z28) -> 0.00755 | AA34: =($C$42*$R$30)/((1+$R$24)^AA28) -> 0.00755
B35: DOD% | C35: 0.95 | E35: 固定资产残值现值 (Mn RMB) | O35: =(C49+C50)*C43/((1+F24)^O28)/1000000 -> 0.19255254 | Q35: 固定资产残值现值 (Mn RMB) | AA35: =(C49+C50)*C43/((1+R24)^AA28)/1000000 -> 0.354
B36: 单次循环衰减率 | C36: 4.68e-05 | E36: 充电电量现值和(KWh) | F36: =SUM(G37:O37) -> 15534030 | Q36: 充电电量现值和(KWh) | R36: =SUM(S37:AA37) -> 21224302
B37: 系统报废终止标准 | C37: 0.7 | E37: 充电电量现值(KWh) | G37: =$C$27*$C$44*$C$34/$C$45*($C$35*(1-$C$36)^((G28-1)*$C$34*$C$44))/$C$29/$C$30/((1+$F$24)^G28) -> 2426705 | H37: =$C$27*$C$44*$C$34/$C$45*($C$35*(1-$C$36)^((H28-1)*$C$34*$C$44))/$C$29/$C$30/((1+$F$24)^H28) -> 2212902.8 | I37: =$C$27*$C$44*$C$34/$C$45*($C$35*(1-$C$36)^((I28-1)*$C$34*$C$44))/$C$29/$C$30/((1+$F$24)^I28) -> 2017937.4 | J37: =$C$27*$C$44*$C$34/$C$45*($C$35*(1-$C$36)^((J28-1)*$C$34*$C$44))/$C$29/$C$30/((1+$F$24)^J28) -> 1840149.3 | K37: =$C$27*$C$44*$C$34/$C$45*($C$35*(1-$C$36)^((K28-1)*$C$34*$C$44))/$C$29/$C$30/((1+$F$24)^K28) -> 1678024.9 | L37: =$C$27*$C$44*$C$34/$C$45*($C$35*(1-$C$36)^((L28-1)*$C$34*$C$44))/$C$29/$C$30/((1+$F$24)^L28) -> 1530184.4 | M37: =$C$27*$C$44*$C$34/$C$45*($C$35*(1-$C$36)^((M28-1)*$C$34*$C$44))/$C$29/$C$30/((1+$F$24)^M28) -> 1395369.2 | N37: =$C$27*$C$44*$C$34/$C$45*($C$35*(1-$C$36)^((N28-1)*$C$34*$C$44))/$C$29/$C$30/((1+$F$24)^N28) -> 1272431.7 | O37: =$C$27*$C$44*$C$34/$C$45*($C$35*(1-$C$36)^((O28-1)*$C$34*$C$44))/$C$29/$C$30/((1+$F$24)^O28) -> 1160325.5 | Q37: 充电电量现值(KWh) | S37: =$C$27*$C$44*$C$34/$C$45*($C$35*(1-$C$36)^((S28-1)*$C$34*$C$44))/$C$29/$C$30/((1+$R$24)^S28) -> 2596574.3 | T37: =$C$27*$C$44*$C$34/$C$45*($C$35*(1-$C$36)^((T28-1)*$C$34*$C$44))/$C$29/$C$30/((1+$R$24)^T28) -> 2533552.4 | U37: =$C$27*$C$44*$C$34/$C$45*($C$35*(1-$C$36)^((U28-1)*$C$34*$C$44))/$C$29/$C$30/((1+$R$24)^U28) -> 2472060.1 | V37: =$C$27*$C$44*$C$34/$C$45*($C$35*(1-$C$36)^((V28-1)*$C$34*$C$44))/$C$29/$C$30/((1+$R$24)^V28) -> 2412060.3 | W37: =$C$27*$C$44*$C$34/$C$45*($C$35*(1-$C$36)^((W28-1)*$C$34*$C$44))/$C$29/$C$30/((1+$R$24)^W28) -> 2353516.8 | X37: =$C$27*$C$44*$C$34/$C$45*($C$35*(1-$C$36)^((X28-1)*$C$34*$C$44))/$C$29/$C$30/((1+$R$24)^X28) -> 2296394.2 | Y37: =$C$27*$C$44*$C$34/$C$45*($C$35*(1-$C$36)^((Y28-1)*$C$34*$C$44))/$C$29/$C$30/((1+$R$24)^Y28) -> 2240658 | Z37: =$C$27*$C$44*$C$34/$C$45*($C$35*(1-$C$36)^((Z28-1)*$C$34*$C$44))/$C$29/$C$30/((1+$R$24)^Z28) -> 2186274.6 | AA37: =$C$27*$C$44*$C$34/$C$45*($C$35*(1-$C$36)^((AA28-1)*$C$34*$C$44))/$C$29/$C$30/((1+$R$24)^AA28) -> 2133211.1
B38: 土建成本(元/Wh) | C38: 0.015 | E38: 放电电量现值和(KWh) | F38: =SUM(G39:O39) -> 13204772 | Q38: 放电电量现值和(KWh) | R38: =SUM(S39:AA39) -> 18041813
B39: 土建残值率（%） | C39: 0 | E39: 放电电量现值(KWh) | G39: =$C$27*$C$44*$C$34*$C$45*($C$35*(1-$C$36)^((G28-1)*$C$34*$C$44))*$C$29*$C$30/((1+$F$24)^G28) -> 2062831.5 | H39: =$C$27*$C$44*$C$34*$C$45*($C$35*(1-$C$36)^((H28-1)*$C$34*$C$44))*$C$29*$C$30/((1+$F$24)^H28) -> 1881088 | I39: =$C$27*$C$44*$C$34*$C$45*($C$35*(1-$C$36)^((I28-1)*$C$34*$C$44))*$C$29*$C$30/((1+$F$24)^I28) -> 1715356.8 | J39: =$C$27*$C$44*$C$34*$C$45*($C$35*(1-$C$36)^((J28-1)*$C$34*$C$44))*$C$29*$C$30/((1+$F$24)^J28) -> 1564227.2 | K39: =$C$27*$C$44*$C$34*$C$45*($C$35*(1-$C$36)^((K28-1)*$C$34*$C$44))*$C$29*$C$30/((1+$F$24)^K28) -> 1426412.6 | L39: =$C$27*$C$44*$C$34*$C$45*($C$35*(1-$C$36)^((L28-1)*$C$34*$C$44))*$C$29*$C$30/((1+$F$24)^L28) -> 1300740.1 | M39: =$C$27*$C$44*$C$34*$C$45*($C$35*(1-$C$36)^((M28-1)*$C$34*$C$44))*$C$29*$C$30/((1+$F$24)^M28) -> 1186139.8 | N39: =$C$27*$C$44*$C$34*$C$45*($C$35*(1-$C$36)^((N28-1)*$C$34*$C$44))*$C$29*$C$30/((1+$F$24)^N28) -> 1081636.3 | O39: =$C$27*$C$44*$C$34*$C$45*($C$35*(1-$C$36)^((O28-1)*$C$34*$C$44))*$C$29*$C$30/((1+$F$24)^O28) -> 986339.92 | Q39: 放电电量现值(KWh) | S39: =$C$27*$C$44*$C$34*$C$45*($C$35*(1-$C$36)^((S28-1)*$C$34*$C$44))*$C$29*$C$30/((1+$R$24)^S28) -> 2207229.7 | T39: =$C$27*$C$44*$C$34*$C$45*($C$35*(1-$C$36)^((T28-1)*$C$34*$C$44))*$C$29*$C$30/((1+$R$24)^T28) -> 2153657.6 | U39: =$C$27*$C$44*$C$34*$C$45*($C$35*(1-$C$36)^((U28-1)*$C$34*$C$44))*$C$29*$C$30/((1+$R$24)^U28) -> 2101385.8 | V39: =$C$27*$C$44*$C$34*$C$45*($C$35*(1-$C$36)^((V28-1)*$C$34*$C$44))*$C$29*$C$30/((1+$R$24)^V28) -> 2050382.7 | W39: =$C$27*$C$44*$C$34*$C$45*($C$35*(1-$C$36)^((W28-1)*$C$34*$C$44))*$C$29*$C$30/((1+$R$24)^W28) -> 2000617.5 | X39: =$C$27*$C$44*$C$34*$C$45*($C$35*(1-$C$36)^((X28-1)*$C$34*$C$44))*$C$29*$C$30/((1+$R$24)^X28) -> 1952060.2 | Y39: =$C$27*$C$44*$C$34*$C$45*($C$35*(1-$C$36)^((Y28-1)*$C$34*$C$44))*$C$29*$C$30/((1+$R$24)^Y28) -> 1904681.4 | Z39: =$C$27*$C$44*$C$34*$C$45*($C$35*(1-$C$36)^((Z28-1)*$C$34*$C$44))*$C$29*$C$30/((1+$R$24)^Z28) -> 1858452.5 | AA39: =$C$27*$C$44*$C$34*$C$45*($C$35*(1-$C$36)^((AA28-1)*$C$34*$C$44))*$C$29*$C$30/((1+$R$24)^AA28) -> 1813345.7
B40: 其它设备投资费用（升压变等） | C40: 350000 | E40: 充电成本现值和（Mn RMB） | F40: =SUM(G41:O41) -> 6.9180613 | Q40: 充电成本现值和（Mn RMB） | R40: =SUM(S41:AA41) -> 9.4522167
B41: 其它成本：入网检测费、项目管理费等（元/Wh） | C41: 0.01 | E41: 充电成本现值（Mn RMB） | G41: =($C$21*$C$33*G37/($C$21+$C$22)+$C$22*$C$32*G37/($C$21+$C$22))/1000000 -> 1.0807301 | H41: =($C$21*$C$33*H37/($C$21+$C$22)+$C$22*$C$32*H37/($C$21+$C$22))/1000000 -> 0.98551355 | I41: =($C$21*$C$33*I37/($C$21+$C$22)+$C$22*$C$32*I37/($C$21+$C$22))/1000000 -> 0.89868596 | J41: =($C$21*$C$33*J37/($C$21+$C$22)+$C$22*$C$32*J37/($C$21+$C$22))/1000000 -> 0.81950822 | K41: =($C$21*$C$33*K37/($C$21+$C$22)+$C$22*$C$32*K37/($C$21+$C$22))/1000000 -> 0.74730635 | L41: =($C$21*$C$33*L37/($C$21+$C$22)+$C$22*$C$32*L37/($C$21+$C$22))/1000000 -> 0.68146574 | M41: =($C$21*$C$33*M37/($C$21+$C$22)+$C$22*$C$32*M37/($C$21+$C$22))/1000000 -> 0.62142595 | N41: =($C$21*$C$33*N37/($C$21+$C$22)+$C$22*$C$32*N37/($C$21+$C$22))/1000000 -> 0.5666759 | O41: =($C$21*$C$33*O37/($C$21+$C$22)+$C$22*$C$32*O37/($C$21+$C$22))/1000000 -> 0.51674954 | Q41: 充电成本现值（Mn RMB） | S41: =($C$21*$C$33*S37/($C$21+$C$22)+$C$22*$C$32*S37/($C$21+$C$22))/1000000 -> 1.1563812 | T41: =($C$21*$C$33*T37/($C$21+$C$22)+$C$22*$C$32*T37/($C$21+$C$22))/1000000 -> 1.1283145 | U41: =($C$21*$C$33*U37/($C$21+$C$22)+$C$22*$C$32*U37/($C$21+$C$22))/1000000 -> 1.1009289 | V41: =($C$21*$C$33*V37/($C$21+$C$22)+$C$22*$C$32*V37/($C$21+$C$22))/1000000 -> 1.0742081 | W41: =($C$21*$C$33*W37/($C$21+$C$22)+$C$22*$C$32*W37/($C$21+$C$22))/1000000 -> 1.0481358 | X41: =($C$21*$C$33*X37/($C$21+$C$22)+$C$22*$C$32*X37/($C$21+$C$22))/1000000 -> 1.0226963 | Y41: =($C$21*$C$33*Y37/($C$21+$C$22)+$C$22*$C$32*Y37/($C$21+$C$22))/1000000 -> 0.99787428 | Z41: =($C$21*$C$33*Z37/($C$21+$C$22)+$C$22*$C$32*Z37/($C$21+$C$22))/1000000 -> 0.9736547 | AA41: =($C$21*$C$33*AA37/($C$21+$C$22)+$C$22*$C$32*AA37/($C$21+$C$22))/1000000 -> 0.95002295
B42: 容量型储能电站运维费用 | C42: 0.001 | E42: 放电收益现值和（Mn RMB） | F42: =SUM(G43:O43) -> 16.647624 | Q42: 放电收益现值和（Mn RMB） | R42: =SUM(S43:AA43) -> 22.635923
B43: 储能系统残值 | C43: 0.05 | E43: 放电收益现值（Mn RMB） | G43: =(G39*$C$31/1000000)+0.3 -> 2.8538034 | H43: =(H39*$C$31/1000000) -> 2.3288034 | I43: =(I39*$C$31/1000000) -> 2.1236267 | J43: =(J39*$C$31/1000000) -> 1.9365269 | K43: =(K39*$C$31/1000000) -> 1.7659113 | L43: =(L39*$C$31/1000000) -> 1.6103277 | M43: =(M39*$C$31/1000000) -> 1.4684515 | N43: =(N39*$C$31/1000000) -> 1.3390752 | O43: =(O39*$C$31/1000000) -> 1.2210975 | Q43: 放电收益现值（Mn RMB） | S43: =(S39*$C$31/1000000)+0.3 -> 3.0325697 | T43: =(T39*$C$31/1000000) -> 2.666247 | U43: =(U39*$C$31/1000000) -> 2.601534 | V43: =(V39*$C$31/1000000) -> 2.5383918 | W43: =(W39*$C$31/1000000) -> 2.476782 | X43: =(X39*$C$31/1000000) -> 2.4166676 | Y43: =(Y39*$C$31/1000000) -> 2.3580122 | Z43: =(Z39*$C$31/1000000) -> 2.3007805 | AA43: =(AA39*$C$31/1000000) -> 2.2449379
B44: 充放循环次数（1次为1充1放）(次/天） | C44: =C21+C22 -> 1.5 | E44: 所得税现值和（Mn RMB） | F44: =SUM(G45:O45) -> 1.4950654 | Q44: 所得税现值和（Mn RMB） | R44: =SUM(S45:AA45) -> 2.0011259
B45: 充放电效率RTE（%） | C45: 0.96 | E45: 所得税现值（Mn RMB） | G45: =(G43-G41-G34-G32)*$F$25 -> 0.30881345 | H45: =(H43-H41-H34-H32)*$F$25 -> 0.21016369 | I45: =(I43-I41-I34-I32)*$F$25 -> 0.18879709 | J45: =(J43-J41-J34-J32)*$F$25 -> 0.16949944 | K45: =(K43-K41-K34-K32)*$F$25 -> 0.15207626 | L45: =(L43-L41-L34-L32)*$F$25 -> 0.136351 | M45: =(M43-M41-M34-M32)*$F$25 -> 0.12216342 | N45: =(N43-N41-N34-N32)*$F$25 -> 0.10936808 | O45: =(O43-O41-O34-O32)*$F$25 -> 0.09783301 | Q45: 所得税现值（Mn RMB） | S45: =(S43-S41-S34-S32)*$R$25 -> 0.32518039 | T45: =(T43-T41-T34-T32)*$R$25 -> 0.24061641 | U45: =(U43-U41-U34-U32)*$R$25 -> 0.23128455 | V45: =(V43-V41-V34-V32)*$R$25 -> 0.22217919 | W45: =(W43-W41-W34-W32)*$R$25 -> 0.21329482 | X45: =(X43-X41-X34-X32)*$R$25 -> 0.20462609 | Y45: =(Y43-Y41-Y34-Y32)*$R$25 -> 0.19616776 | Z45: =(Z43-Z41-Z34-Z32)*$R$25 -> 0.18791472 | AA45: =(AA43-AA41-AA34-AA32)*$R$25 -> 0.179862
B46: 用户分成比例（%） | C46: 0.1 | E46: 增值税现值和（Mn RMB） | F46: =SUM(G47:O47) -> 0 | Q46: 增值税现值和（Mn RMB） | R46: =SUM(S47:AA47) -> 0
B47: 充放循环总次数（次数） | C47: =LOG(C37/C35,(1-C36)) -> 6525.0962 | E47: 增值税现值（Mn RMB） | G47: =(G43-G41)*$F$26 -> 0 | H47: =(H43-H41)*$F$26 -> 0 | I47: =(I43-I41)*$F$26 -> 0 | J47: =(J43-J41)*$F$26 -> 0 | K47: =(K43-K41)*$F$26 -> 0 | L47: =(L43-L41)*$F$26 -> 0 | M47: =(M43-M41)*$F$26 -> 0 | N47: =(N43-N41)*$F$26 -> 0 | O47: =(O43-O41)*$F$26 -> 0 | Q47: 增值税现值（Mn RMB） | S47: =(S43-S41)*$R$26 -> 0 | T47: =(T43-T41)*$R$26 -> 0 | U47: =(U43-U41)*$R$26 -> 0 | V47: =(V43-V41)*$R$26 -> 0 | W47: =(W43-W41)*$R$26 -> 0 | X47: =(X43-X41)*$R$26 -> 0 | Y47: =(Y43-Y41)*$R$26 -> 0 | Z47: =(Z43-Z41)*$R$26 -> 0 | AA47: =(AA43-AA41)*$R$26 -> 0
B48: 系统寿命（年） | C48: =C47/C44/C34 -> 12.428755 | E48: 放电利润现值和（Mn RMB） | F48: =SUM(G49:O49) -> 8.1853069 | Q48: 放电利润现值和（Mn RMB） | R48: =SUM(S49:AA49) -> 11.11463
B49: PCS总成本（元） | C49: =C26*C25 -> 360000 | E49: 放电利润现值和（Mn RMB） | G49: =G43-G41-G45-G47-G34 -> 1.4572038 | H49: =H43-H41-H45-H47-H34 -> 1.1265317 | I49: =I43-I41-I45-I47-I34 -> 1.0299806 | J49: =J43-J41-J45-J47-J34 -> 0.94175941 | K49: =K43-K41-K45-K47-K34 -> 0.86114569 | L49: =L43-L41-L45-L47-L34 -> 0.78748003 | M49: =M43-M41-M45-M47-M34 -> 0.72016038 | N49: =N43-N41-N45-N47-N34 -> 0.65863705 | O49: =O43-O41-O45-O47-O34 -> 0.6024082 | Q49: 放电利润现值和（Mn RMB） | S49: =S43-S41-S45-S47-S34 -> 1.5434581 | T49: =T43-T41-T45-T47-T34 -> 1.2897661 | U49: =U43-U41-U45-U47-U34 -> 1.2617706 | V49: =V43-V41-V45-V47-V34 -> 1.2344545 | W49: =W43-W41-W45-W47-W34 -> 1.2078014 | X49: =X43-X41-X45-X47-X34 -> 1.1817952 | Y49: =Y43-Y41-Y45-Y47-Y34 -> 1.1564202 | Z49: =Z43-Z41-Z45-Z47-Z34 -> 1.1316611 | AA49: =AA43-AA41-AA45-AA47-AA34 -> 1.1075029
B50: ESS总成本（元） | C50: =C27*C28 -> 6720000 | E50: 度电收益（元/kWh) | F50: =C31 -> 1.2380088 | Q50: 度电收益（元/kWh) | R50: =C31 -> 1.2380088
B51: 土建总投资（元） | C51: =C38*C27*1000 -> 72000 | E51: LCOS（元/kWh) | F51: =F30/F38*1000000 -> 0.57176298 | Q51: LCOS（元/kWh) | R51: =R30/R38*1000000 -> 0.41847235
B52: 其它投资（元） | C52: =C41*C27*1000 -> 48000 | E52: 充电成本（元/kWh) | F52: =F40*1000000/F38 -> 0.52390614 | Q52: 充电成本（元/kWh) | R52: =R40*1000000/R38 -> 0.52390614
B53: 设备购置补助（元） | C53: 0 | E53: 用户分成部分（元/kWh) | F53: =SUM(G54:O54) -> 0.81853069 | Q53: 用户分成部分（元/kWh) | R53: =SUM(S54:AA54) -> 1.111463
B54: 设备总投资（元） | C54: =(C52+C51+C50+C49+C40-C53) -> 7550000 | E54: 用户分成部分现值 | G54: =G49*$C$46 -> 0.14572038 | H54: =H49*$C$46 -> 0.11265317 | I54: =I49*$C$46 -> 0.10299806 | J54: =J49*$C$46 -> 0.094175941 | K54: =K49*$C$46 -> 0.086114569 | L54: =L49*$C$46 -> 0.078748003 | M54: =M49*$C$46 -> 0.072016038 | N54: =N49*$C$46 -> 0.065863705 | O54: =O49*$C$46 -> 0.06024082 | Q54: 用户分成部分现值 | S54: =S49*$C$46 -> 0.15434581 | T54: =T49*$C$46 -> 0.12897661 | U54: =U49*$C$46 -> 0.12617706 | V54: =V49*$C$46 -> 0.12344545 | W54: =W49*$C$46 -> 0.12078014 | X54: =X49*$C$46 -> 0.11817952 | Y54: =Y49*$C$46 -> 0.11564202 | Z54: =Z49*$C$46 -> 0.11316611 | AA54: =AA49*$C$46 -> 0.11075029
B55: 投资回收年限 | C55: 9+ | E55: NPV | F55: =-(F30) -> -7.55 | G55: =G43-G41-G54-G45-G47-G34 -> 1.3114834 | H55: =H43-H41-H54-H45-H47-H34 -> 1.0138785 | I55: =I43-I41-I54-I45-I47-I34 -> 0.92698257 | J55: =J43-J41-J54-J45-J47-J34 -> 0.84758347 | K55: =K43-K41-K54-K45-K47-K34 -> 0.77503112 | L55: =L43-L41-L54-L45-L47-L34 -> 0.70873203 | M55: =M43-M41-M54-M45-M47-M34 -> 0.64814434 | N55: =N43-N41-N54-N45-N47-N34 -> 0.59277335 | O55: =O43-O41-O54-O45-O47-O34+O35 -> 0.73471993 | Q55: NPV | R55: =-(R30) -> -7.55 | S55: =S43-S41-S54-S45-S47-S34 -> 1.3891123 | T55: =T43-T41-T54-T45-T47-T34 -> 1.1607895 | U55: =U43-U41-U54-U45-U47-U34 -> 1.1355935 | V55: =V43-V41-V54-V45-V47-V34 -> 1.111009 | W55: =W43-W41-W54-W45-W47-W34 -> 1.0870212 | X55: =X43-X41-X54-X45-X47-X34 -> 1.0636157 | Y55: =Y43-Y41-Y54-Y45-Y47-Y34 -> 1.0407782 | Z55: =Z43-Z41-Z54-Z45-Z47-Z34 -> 1.018495 | AA55: =AA43-AA41-AA54-AA45-AA47-AA34+AA35 -> 1.3507526
B56: 投资回报率 | C56: =F56 -> 0.0012355974 | E56: 投资回报率 | F56: =SUM(F55:O55)/F30 -> 0.0012355974 | Q56: IRR | R56: =IRR(R55:AA55) -> 0.069874942

Sheet 贵州
B1: xxx | C1: M2访谈数据/Assumption
B2: xxx | C2: 引用数据
B3: xxx | C3: 计算所得数据
C4: 自变量 | D4: *表后用户侧储能主要通过现货形式进行峰谷套利，收益部分由峰负荷时的用户分摊
C5: 支出项 | D5: 关键假设：
C6: 收入项 | D6: 1）电池充放电循环次数~6525次
D7: 2）PCS成本：0.3元/W；电池充放电循环次数~6525次；容量型储能电站运维费用：0.1%；PCS效率：98%；线损：98%；系统使用天数：350天；充放循环次数（1次为1充1放）(次/天）：2次
B8: 更新处：标绿色的单元格 | D8: 充放策略：两充两放（1*谷-0.75*峰，0.75*平-1*峰）
B10: 省份 | C10: 贵州省 | D10: 备注：
B11: 有无补贴政策 | C11: 有
B12: IRR：不含补贴 | C12: -0.044687664
B13: IRR：含补贴（1） | C13: N/A
B14: 补贴（1）情况 | C14: N/A
B15: IRR：含补贴（2） | C15: N/A
B16: 补贴（2）情况 | C16: N/A
B17: 该省 Best IRR | C17: =MAX(C12:C16) -> -0.044687664
B19: 基本数据 | E19: 计算结果
B20: 充放策略：两充两放（1*谷-0.75*峰，0.75*平-1*峰） | E20: LCOS（元/kWh) | F20: =F51 -> 0.49691112
B21: 谷 | C21: 1 | E21: 投资回报率 | F21: =F56 -> -0.43411542
B22: 平 | C22: 0.75 | E22: NPV(折现率=7%） | F22: =SUM(F55:O55) -> -3.2775715
B23: 峰 | C23: =C21+C22 -> 1.75 | E23: IRR | F23: =R56 -> -0.044687664
B24: 基本数据 | E24: 折现率 | F24: 0.07 | Q24: 折现率 | R24: 0
B25: PCS(KW） | C25: 1200 | E25: 所得税率 | F25: 0.25 | Q25: 所得税率 | R25: 0.25
B26: PCS成本（元/kW) | C26: 300 | E26: 增值税率 | F26: 0 | G26: 暂不考虑 | Q26: 增值税率 | R26: 0 | S26: 暂不考虑
B27: ESS(KWh) | C27: 4800 | E27: 储能系统经济效益估算表（元） | Q27: 储能系统经济效益估算表（元）
B28: ESS成本（元/kWh) | C28: 1400 | E28: 储能平准化成本LCOS（Levelized Cost of Storage） | G28: 1 | H28: 2 | I28: 3 | J28: 4 | K28: 5 | L28: 6 | M28: 7 | N28: 8 | O28: 9 | Q28: 储能平准化成本LCOS（Levelized Cost of Storage） | S28: 1 | T28: 2 | U28: 3 | V28: 4 | W28: 5 | X28: 6 | Y28: 7 | Z28: 8 | AA28: 9
B29: PCS效率 | C29: 0.98 | F29: 基准年 | G29: 第1年 | H29: 第2年 | I29: 第3年 | J29: 第4年 | K29: 第5年 | L29: 第6年 | M29: 第7年 | N29: 第8年 | O29: 第9年 | R29: 基准年 | S29: 第1年 | T29: 第2年 | U29: 第3年 | V29: 第4年 | W29: 第5年 | X29: 第6年 | Y29: 第7年 | Z29: 第8年 | AA29: 第9年
B30: 线损 | C30: 0.98 | E30: 初始投资成本（Mn RMB） | F30: =C54/1000000 -> 7.55 | Q30: 初始投资成本（Mn RMB） | R30: =C54/1000000 -> 7.55
B31: 峰价（元/KWh) | C31: 0.76762 | E31: 折旧现值和（Mn RMB） | F31: =SUM(G32:O32) -> 4.3167957 | Q31: 折旧现值和（Mn RMB） | R31: =SUM(S32:AA32) -> 5.9631276
B32: 平价（元/KWh) | C32: 0.52866 | E32: 折旧现值（Mn RMB） | G32: =($C$49+$C$50+$C$40)*(1-$C$43)/$C$48/1000000/(1+$F$24)^G28 -> 0.61922405 | H32: =($C$49+$C$50+$C$40)*(1-$C$43)/$C$48/1000000/(1+$F$24)^H28 -> 0.57871406 | I32: =($C$49+$C$50+$C$40)*(1-$C$43)/$C$48/1000000/(1+$F$24)^I28 -> 0.54085426 | J32: =($C$49+$C$50+$C$40)*(1-$C$43)/$C$48/1000000/(1+$F$24)^J28 -> 0.50547127 | K32: =($C$49+$C$50+$C$40)*(1-$C$43)/$C$48/1000000/(1+$F$24)^K28 -> 0.47240306 | L32: =($C$49+$C$50+$C$40)*(1-$C$43)/$C$48/1000000/(1+$F$24)^L28 -> 0.44149819 | M32: =($C$49+$C$50+$C$40)*(1-$C$43)/$C$48/1000000/(1+$F$24)^M28 -> 0.41261513 | N32: =($C$49+$C$50+$C$40)*(1-$C$43)/$C$48/1000000/(1+$F$24)^N28 -> 0.38562162 | O32: =($C$49+$C$50+$C$40)*(1-$C$43)/$C$48/1000000/(1+$F$24)^O28 -> 0.36039403 | Q32: 折旧现值（Mn RMB） | S32: =($C$49+$C$50+$C$40)*(1-$C$43)/$C$48/1000000/(1+$R$24)^S28 -> 0.66256973 | T32: =($C$49+$C$50+$C$40)*(1-$C$43)/$C$48/1000000/(1+$R$24)^T28 -> 0.66256973 | U32: =($C$49+$C$50+$C$40)*(1-$C$43)/$C$48/1000000/(1+$R$24)^U28 -> 0.66256973 | V32: =($C$49+$C$50+$C$40)*(1-$C$43)/$C$48/1000000/(1+$R$24)^V28 -> 0.66256973 | W32: =($C$49+$C$50+$C$40)*(1-$C$43)/$C$48/1000000/(1+$R$24)^W28 -> 0.66256973 | X32: =($C$49+$C$50+$C$40)*(1-$C$43)/$C$48/1000000/(1+$R$24)^X28 -> 0.66256973 | Y32: =($C$49+$C$50+$C$40)*(1-$C$43)/$C$48/1000000/(1+$R$24)^Y28 -> 0.66256973 | Z32: =($C$49+$C$50+$C$40)*(1-$C$43)/$C$48/1000000/(1+$R$24)^Z28 -> 0.66256973 | AA32: =($C$49+$C$50+$C$40)*(1-$C$43)/$C$48/1000000/(1+$R$24)^AA28 -> 0.66256973
B33: 谷价（元/KWh) | C33: 0.2897 | E33: 运行成本现值和（Mn RMB） | F33: =SUM(G34:O34) -> 0.049190003 | Q33: 运行成本现值和（Mn RMB） | R33: =SUM(S34:AA34) -> 0.06795
B34: 系统年使用天数 (天) | C34: 350 | E34: 运行成本现值（Mn RMB） | G34: =($C$42*$F$30)/((1+$F$24)^G28) -> 0.0070560748 | H34: =($C$42*$F$30)/((1+$F$24)^H28) -> 0.0065944624 | I34: =($C$42*$F$30)/((1+$F$24)^I28) -> 0.006163049 | J34: =($C$42*$F$30)/((1+$F$24)^J28) -> 0.0057598589 | K34: =($C$42*$F$30)/((1+$F$24)^K28) -> 0.0053830457 | L34: =($C$42*$F$30)/((1+$F$24)^L28) -> 0.0050308838 | M34: =($C$42*$F$30)/((1+$F$24)^M28) -> 0.0047017606 | N34: =($C$42*$F$30)/((1+$F$24)^N28) -> 0.0043941687 | O34: =($C$42*$F$30)/((1+$F$24)^O28) -> 0.0041066998 | Q34: 运行成本现值（Mn RMB） | S34: =($C$42*$R$30)/((1+$R$24)^S28) -> 0.00755 | T34: =($C$42*$R$30)/((1+$R$24)^T28) -> 0.00755 | U34: =($C$42*$R$30)/((1+$R$24)^U28) -> 0.00755 | V34: =($C$42*$R$30)/((1+$R$24)^V28) -> 0.00755 | W34: =($C$42*$R$30)/((1+$R$24)^W28) -> 0.00755 | X34: =($C$42*$R$30)/((1+$R$24)^X28) -> 0.00755 | Y34: =($C$42*$R$30)/((1+$R$24)^Y28) -> 0.00755 | Z34: =($C$42*$R$30)/((1+$R$24)^Z28) -> 0.00755 | AA34: =($C$42*$R$30)/((1+$R$24)^AA28) -> 0.00755
B35: DOD% | C35: 0.95 | E35: 固定资产残值现值 (Mn RMB) | O35: =(C49+C50)*C43/((1+F24)^O28)/1000000 -> 0.19255254 | Q35: 固定资产残值现值 (Mn RMB) | AA35: =(C49+C50)*C43/((1+R24)^AA28)/1000000 -> 0.354
B36: 单次循环衰减率 | C36: 4.68e-05 | E36: 充电电量现值和(KWh) | F36: =SUM(G37:O37) -> 17873988 | Q36: 充电电量现值和(KWh) | R36: =SUM(S37:AA37) -> 24377075
B37: 系统报废终止标准 | C37: 0.7 | E37: 充电电量现值(KWh) | G37: =$C$27*$C$44*$C$34/$C$45*($C$35*(1-$C$36)^((G28-1)*$C$34*$C$44))/$C$29/$C$30/((1+$F$24)^G28) -> 2831155.8 | H37: =$C$27*$C$44*$C$34/$C$45*($C$35*(1-$C$36)^((H28-1)*$C$34*$C$44))/$C$29/$C$30/((1+$F$24)^H28) -> 2571169.2 | I37: =$C$27*$C$44*$C$34/$C$45*($C$35*(1-$C$36)^((I28-1)*$C$34*$C$44))/$C$29/$C$30/((1+$F$24)^I28) -> 2335057.3 | J37: =$C$27*$C$44*$C$34/$C$45*($C$35*(1-$C$36)^((J28-1)*$C$34*$C$44))/$C$29/$C$30/((1+$F$24)^J28) -> 2120627.6 | K37: =$C$27*$C$44*$C$34/$C$45*($C$35*(1-$C$36)^((K28-1)*$C$34*$C$44))/$C$29/$C$30/((1+$F$24)^K28) -> 1925889.2 | L37: =$C$27*$C$44*$C$34/$C$45*($C$35*(1-$C$36)^((L28-1)*$C$34*$C$44))/$C$29/$C$30/((1+$F$24)^L28) -> 1749033.7 | M37: =$C$27*$C$44*$C$34/$C$45*($C$35*(1-$C$36)^((M28-1)*$C$34*$C$44))/$C$29/$C$30/((1+$F$24)^M28) -> 1588418.9 | N37: =$C$27*$C$44*$C$34/$C$45*($C$35*(1-$C$36)^((N28-1)*$C$34*$C$44))/$C$29/$C$30/((1+$F$24)^N28) -> 1442553.5 | O37: =$C$27*$C$44*$C$34/$C$45*($C$35*(1-$C$36)^((O28-1)*$C$34*$C$44))/$C$29/$C$30/((1+$F$24)^O28) -> 1310083 | Q37: 充电电量现值(KWh) | S37: =$C$27*$C$44*$C$34/$C$45*($C$35*(1-$C$36)^((S28-1)*$C$34*$C$44))/$C$29/$C$30/((1+$R$24)^S28) -> 3029336.7 | T37: =$C$27*$C$44*$C$34/$C$45*($C$35*(1-$C$36)^((T28-1)*$C$34*$C$44))/$C$29/$C$30/((1+$R$24)^T28) -> 2943731.6 | U37: =$C$27*$C$44*$C$34/$C$45*($C$35*(1-$C$36)^((U28-1)*$C$34*$C$44))/$C$29/$C$30/((1+$R$24)^U28) -> 2860545.5 | V37: =$C$27*$C$44*$C$34/$C$45*($C$35*(1-$C$36)^((V28-1)*$C$34*$C$44))/$C$29/$C$30/((1+$R$24)^V28) -> 2779710.2 | W37: =$C$27*$C$44*$C$34/$C$45*($C$35*(1-$C$36)^((W28-1)*$C$34*$C$44))/$C$29/$C$30/((1+$R$24)^W28) -> 2701159.2 | X37: =$C$27*$C$44*$C$34/$C$45*($C$35*(1-$C$36)^((X28-1)*$C$34*$C$44))/$C$29/$C$30/((1+$R$24)^X28) -> 2624827.9 | Y37: =$C$27*$C$44*$C$34/$C$45*($C$35*(1-$C$36)^((Y28-1)*$C$34*$C$44))/$C$29/$C$30/((1+$R$24)^Y28) -> 2550653.7 | Z37: =$C$27*$C$44*$C$34/$C$45*($C$35*(1-$C$36)^((Z28-1)*$C$34*$C$44))/$C$29/$C$30/((1+$R$24)^Z28) -> 2478575.5 | AA37: =$C$27*$C$44*$C$34/$C$45*($C$35*(1-$C$36)^((AA28-1)*$C$34*$C$44))/$C$29/$C$30/((1+$R$24)^AA28) -> 2408534.2
B38: 土建成本(元/Wh) | C38: 0.015 | E38: 放电电量现值和(KWh) | F38: =SUM(G39:O39) -> 15193864 | Q38: 放电电量现值和(KWh) | R38: =SUM(S39:AA39) -> 20721842
B39: 土建残值率（%） | C39: 0 | E39: 放电电量现值(KWh) | G39: =$C$27*$C$44*$C$34*$C$45*($C$35*(1-$C$36)^((G28-1)*$C$34*$C$44))*$C$29*$C$30/((1+$F$24)^G28) -> 2406636.7 | H39: =$C$27*$C$44*$C$34*$C$45*($C$35*(1-$C$36)^((H28-1)*$C$34*$C$44))*$C$29*$C$30/((1+$F$24)^H28) -> 2185633.9 | I39: =$C$27*$C$44*$C$34*$C$45*($C$35*(1-$C$36)^((I28-1)*$C$34*$C$44))*$C$29*$C$30/((1+$F$24)^I28) -> 1984925.9 | J39: =$C$27*$C$44*$C$34*$C$45*($C$35*(1-$C$36)^((J28-1)*$C$34*$C$44))*$C$29*$C$30/((1+$F$24)^J28) -> 1802649 | K39: =$C$27*$C$44*$C$34*$C$45*($C$35*(1-$C$36)^((K28-1)*$C$34*$C$44))*$C$29*$C$30/((1+$F$24)^K28) -> 1637110.8 | L39: =$C$27*$C$44*$C$34*$C$45*($C$35*(1-$C$36)^((L28-1)*$C$34*$C$44))*$C$29*$C$30/((1+$F$24)^L28) -> 1486773.9 | M39: =$C$27*$C$44*$C$34*$C$45*($C$35*(1-$C$36)^((M28-1)*$C$34*$C$44))*$C$29*$C$30/((1+$F$24)^M28) -> 1350242.6 | N39: =$C$27*$C$44*$C$34*$C$45*($C$35*(1-$C$36)^((N28-1)*$C$34*$C$44))*$C$29*$C$30/((1+$F$24)^N28) -> 1226249.1 | O39: =$C$27*$C$44*$C$34*$C$45*($C$35*(1-$C$36)^((O28-1)*$C$34*$C$44))*$C$29*$C$30/((1+$F$24)^O28) -> 1113641.9 | Q39: 放电电量现值(KWh) | S39: =$C$27*$C$44*$C$34*$C$45*($C$35*(1-$C$36)^((S28-1)*$C$34*$C$44))*$C$29*$C$30/((1+$R$24)^S28) -> 2575101.3 | T39: =$C$27*$C$44*$C$34*$C$45*($C$35*(1-$C$36)^((T28-1)*$C$34*$C$44))*$C$29*$C$30/((1+$R$24)^T28) -> 2502332.3 | U39: =$C$27*$C$44*$C$34*$C$45*($C$35*(1-$C$36)^((U28-1)*$C$34*$C$44))*$C$29*$C$30/((1+$R$24)^U28) -> 2431619.6 | V39: =$C$27*$C$44*$C$34*$C$45*($C$35*(1-$C$36)^((V28-1)*$C$34*$C$44))*$C$29*$C$30/((1+$R$24)^V28) -> 2362905.2 | W39: =$C$27*$C$44*$C$34*$C$45*($C$35*(1-$C$36)^((W28-1)*$C$34*$C$44))*$C$29*$C$30/((1+$R$24)^W28) -> 2296132.5 | X39: =$C$27*$C$44*$C$34*$C$45*($C$35*(1-$C$36)^((X28-1)*$C$34*$C$44))*$C$29*$C$30/((1+$R$24)^X28) -> 2231246.8 | Y39: =$C$27*$C$44*$C$34*$C$45*($C$35*(1-$C$36)^((Y28-1)*$C$34*$C$44))*$C$29*$C$30/((1+$R$24)^Y28) -> 2168194.6 | Z39: =$C$27*$C$44*$C$34*$C$45*($C$35*(1-$C$36)^((Z28-1)*$C$34*$C$44))*$C$29*$C$30/((1+$R$24)^Z28) -> 2106924.2 | AA39: =$C$27*$C$44*$C$34*$C$45*($C$35*(1-$C$36)^((AA28-1)*$C$34*$C$44))*$C$29*$C$30/((1+$R$24)^AA28) -> 2047385.3
B40: 其它设备投资费用（升压变等） | C40: 350000 | E40: 充电成本现值和（Mn RMB） | F40: =SUM(G41:O41) -> 7.008595 | Q40: 充电成本现值和（Mn RMB） | R40: =SUM(S41:AA41) -> 9.5585295
B41: 其它成本：入网检测费、项目管理费等（元/Wh） | C41: 0.01 | E41: 充电成本现值（Mn RMB） | G41: =($C$21*$C$33*G37/($C$21+$C$22)+$C$22*$C$32*G37/($C$21+$C$22))/1000000 -> 1.1101286 | H41: =($C$21*$C$33*H37/($C$21+$C$22)+$C$22*$C$32*H37/($C$21+$C$22))/1000000 -> 1.0081848 | I41: =($C$21*$C$33*I37/($C$21+$C$22)+$C$22*$C$32*I37/($C$21+$C$22))/1000000 -> 0.91560263 | J41: =($C$21*$C$33*J37/($C$21+$C$22)+$C$22*$C$32*J37/($C$21+$C$22))/1000000 -> 0.83152232 | K41: =($C$21*$C$33*K37/($C$21+$C$22)+$C$22*$C$32*K37/($C$21+$C$22))/1000000 -> 0.75516316 | L41: =($C$21*$C$33*L37/($C$21+$C$22)+$C$22*$C$32*L37/($C$21+$C$22))/1000000 -> 0.68581609 | M41: =($C$21*$C$33*M37/($C$21+$C$22)+$C$22*$C$32*M37/($C$21+$C$22))/1000000 -> 0.62283721 | N41: =($C$21*$C$33*N37/($C$21+$C$22)+$C$22*$C$32*N37/($C$21+$C$22))/1000000 -> 0.56564172 | O41: =($C$21*$C$33*O37/($C$21+$C$22)+$C$22*$C$32*O37/($C$21+$C$22))/1000000 -> 0.51369852 | Q41: 充电成本现值（Mn RMB） | S41: =($C$21*$C$33*S37/($C$21+$C$22)+$C$22*$C$32*S37/($C$21+$C$22))/1000000 -> 1.1878376 | T41: =($C$21*$C$33*T37/($C$21+$C$22)+$C$22*$C$32*T37/($C$21+$C$22))/1000000 -> 1.1542708 | U41: =($C$21*$C$33*U37/($C$21+$C$22)+$C$22*$C$32*U37/($C$21+$C$22))/1000000 -> 1.1216526 | V41: =($C$21*$C$33*V37/($C$21+$C$22)+$C$22*$C$32*V37/($C$21+$C$22))/1000000 -> 1.0899561 | W41: =($C$21*$C$33*W37/($C$21+$C$22)+$C$22*$C$32*W37/($C$21+$C$22))/1000000 -> 1.0591554 | X41: =($C$21*$C$33*X37/($C$21+$C$22)+$C$22*$C$32*X37/($C$21+$C$22))/1000000 -> 1.029225 | Y41: =($C$21*$C$33*Y37/($C$21+$C$22)+$C$22*$C$32*Y37/($C$21+$C$22))/1000000 -> 1.0001405 | Z41: =($C$21*$C$33*Z37/($C$21+$C$22)+$C$22*$C$32*Z37/($C$21+$C$22))/1000000 -> 0.97187778 | AA41: =($C$21*$C$33*AA37/($C$21+$C$22)+$C$22*$C$32*AA37/($C$21+$C$22))/1000000 -> 0.94441377
B42: 容量型储能电站运维费用 | C42: 0.001 | E42: 放电收益现值和（Mn RMB） | F42: =SUM(G43:O43) -> 11.663114 | Q42: 放电收益现值和（Mn RMB） | R42: =SUM(S43:AA43) -> 15.9065
B43: 储能系统残值 | C43: 0.05 | E43: 放电收益现值（Mn RMB） | G43: =(G39*$C$31/1000000) -> 1.8473825 | H43: =(H39*$C$31/1000000) -> 1.6777363 | I43: =(I39*$C$31/1000000) -> 1.5236688 | J43: =(J39*$C$31/1000000) -> 1.3837495 | K43: =(K39*$C$31/1000000) -> 1.256679 | L43: =(L39*$C$31/1000000) -> 1.1412774 | M43: =(M39*$C$31/1000000) -> 1.0364733 | N43: =(N39*$C$31/1000000) -> 0.94129333 | O43: =(O39*$C$31/1000000) -> 0.85485383 | Q43: 放电收益现值（Mn RMB） | S43: =(S39*$C$31/1000000) -> 1.9766993 | T43: =(T39*$C$31/1000000) -> 1.9208403 | U43: =(U39*$C$31/1000000) -> 1.8665598 | V43: =(V39*$C$31/1000000) -> 1.8138133 | W43: =(W39*$C$31/1000000) -> 1.7625572 | X43: =(X39*$C$31/1000000) -> 1.7127497 | Y43: =(Y39*$C$31/1000000) -> 1.6643496 | Z43: =(Z39*$C$31/1000000) -> 1.6173172 | AA43: =(AA39*$C$31/1000000) -> 1.5716139
B44: 充放循环次数（1次为1充1放）(次/天） | C44: =C21+C22 -> 1.75 | E44: 所得税现值和（Mn RMB） | F44: =SUM(G45:O45) -> 0.072133293 | Q44: 所得税现值和（Mn RMB） | R44: =SUM(S45:AA45) -> 0.079223281
B45: 充放电效率RTE（%） | C45: 0.96 | E45: 所得税现值（Mn RMB） | G45: =(G43-G41-G34-G32)*$F$25 -> 0.027743454 | H45: =(H43-H41-H34-H32)*$F$25 -> 0.021060741 | I45: =(I43-I41-I34-I32)*$F$25 -> 0.015262221 | J45: =(J43-J41-J34-J32)*$F$25 -> 0.010249 | K45: =(K43-K41-K34-K32)*$F$25 -> 0.0059324235 | L45: =(L43-L41-L34-L32)*$F$25 -> 0.002233062 | M45: =(M43-M41-M34-M32)*$F$25 -> -0.00092021044 | N45: =(N43-N41-N34-N32)*$F$25 -> -0.0035910426 | O45: =(O43-O41-O34-O32)*$F$25 -> -0.0058363551 | Q45: 所得税现值（Mn RMB） | S45: =(S43-S41-S34-S32)*$R$25 -> 0.029685496 | T45: =(T43-T41-T34-T32)*$R$25 -> 0.024112443 | U45: =(U43-U41-U34-U32)*$R$25 -> 0.018696877 | V45: =(V43-V41-V34-V32)*$R$25 -> 0.013434348 | W45: =(W43-W41-W34-W32)*$R$25 -> 0.0083205308 | X45: =(X43-X41-X34-X32)*$R$25 -> 0.0033512239 | Y45: =(Y43-Y41-Y34-Y32)*$R$25 -> -0.0014776569 | Z45: =(Z43-Z41-Z34-Z32)*$R$25 -> -0.0061700797 | AA45: =(AA43-AA41-AA34-AA32)*$R$25 -> -0.010729901
B46: 用户分成比例（%） | C46: 0.1 | E46: 增值税现值和（Mn RMB） | F46: =SUM(G47:O47) -> 0 | Q46: 增值税现值和（Mn RMB） | R46: =SUM(S47:AA47) -> 0
B47: 充放循环总次数（次数） | C47: =LOG(C37/C35,(1-C36)) -> 6525.0962 | E47: 增值税现值（Mn RMB） | G47: =(G43-G41)*$F$26 -> 0 | H47: =(H43-H41)*$F$26 -> 0 | I47: =(I43-I41)*$F$26 -> 0 | J47: =(J43-J41)*$F$26 -> 0 | K47: =(K43-K41)*$F$26 -> 0 | L47: =(L43-L41)*$F$26 -> 0 | M47: =(M43-M41)*$F$26 -> 0 | N47: =(N43-N41)*$F$26 -> 0 | O47: =(O43-O41)*$F$26 -> 0 | Q47: 增值税现值（Mn RMB） | S47: =(S43-S41)*$R$26 -> 0 | T47: =(T43-T41)*$R$26 -> 0 | U47: =(U43-U41)*$R$26 -> 0 | V47: =(V43-V41)*$R$26 -> 0 | W47: =(W43-W41)*$R$26 -> 0 | X47: =(X43-X41)*$R$26 -> 0 | Y47: =(Y43-Y41)*$R$26 -> 0 | Z47: =(Z43-Z41)*$R$26 -> 0 | AA47: =(AA43-AA41)*$R$26 -> 0
B48: 系统寿命（年） | C48: =C47/C44/C34 -> 10.653218 | E48: 放电利润现值和（Mn RMB） | F48: =SUM(G49:O49) -> 4.5331956 | Q48: 放电利润现值和（Mn RMB） | R48: =SUM(S49:AA49) -> 6.2007974
B49: PCS总成本（元） | C49: =C26*C25 -> 360000 | E49: 放电利润现值和（Mn RMB） | G49: =G43-G41-G45-G47-G34 -> 0.70245441 | H49: =H43-H41-H45-H47-H34 -> 0.64189629 | I49: =I43-I41-I45-I47-I34 -> 0.58664093 | J49: =J43-J41-J45-J47-J34 -> 0.53621827 | K49: =K43-K41-K45-K47-K34 -> 0.49020033 | L49: =L43-L41-L45-L47-L34 -> 0.44819737 | M49: =M43-M41-M45-M47-M34 -> 0.4098545 | N49: =N43-N41-N45-N47-N34 -> 0.37484849 | O49: =O43-O41-O45-O47-O34 -> 0.34288497 | Q49: 放电利润现值和（Mn RMB） | S49: =S43-S41-S45-S47-S34 -> 0.75162622 | T49: =T43-T41-T45-T47-T34 -> 0.73490706 | U49: =U43-U41-U45-U47-U34 -> 0.71866036 | V49: =V43-V41-V45-V47-V34 -> 0.70287277 | W49: =W43-W41-W45-W47-W34 -> 0.68753132 | X49: =X43-X41-X45-X47-X34 -> 0.6726234 | Y49: =Y43-Y41-Y45-Y47-Y34 -> 0.65813676 | Z49: =Z43-Z41-Z45-Z47-Z34 -> 0.64405949 | AA49: =AA43-AA41-AA45-AA47-AA34 -> 0.63038003
B50: ESS总成本（元） | C50: =C27*C28 -> 6720000 | E50: 度电收益（元/kWh) | F50: =C31 -> 0.76762 | Q50: 度电收益（元/kWh) | R50: =C31 -> 0.76762
B51: 土建总投资（元） | C51: =C38*C27*1000 -> 72000 | E51: LCOS（元/kWh) | F51: =F30/F38*1000000 -> 0.49691112 | Q51: LCOS（元/kWh) | R51: =R30/R38*1000000 -> 0.36434985
B52: 其它投资（元） | C52: =C41*C27*1000 -> 48000 | E52: 充电成本（元/kWh) | F52: =F40*1000000/F38 -> 0.46127799 | Q52: 充电成本（元/kWh) | R52: =R40*1000000/R38 -> 0.46127799
B53: 设备购置补助（元） | C53: 0 | E53: 用户分成部分（元/kWh) | F53: =SUM(G54:O54) -> 0.45331956 | Q53: 用户分成部分（元/kWh) | R53: =SUM(S54:AA54) -> 0.62007974
B54: 设备总投资（元） | C54: =(C52+C51+C50+C49+C40-C53) -> 7550000 | E54: 用户分成部分现值 | G54: =G49*$C$46 -> 0.070245441 | H54: =H49*$C$46 -> 0.064189629 | I54: =I49*$C$46 -> 0.058664093 | J54: =J49*$C$46 -> 0.053621827 | K54: =K49*$C$46 -> 0.049020033 | L54: =L49*$C$46 -> 0.044819737 | M54: =M49*$C$46 -> 0.04098545 | N54: =N49*$C$46 -> 0.037484849 | O54: =O49*$C$46 -> 0.034288497 | Q54: 用户分成部分现值 | S54: =S49*$C$46 -> 0.075162622 | T54: =T49*$C$46 -> 0.073490706 | U54: =U49*$C$46 -> 0.071866036 | V54: =V49*$C$46 -> 0.070287277 | W54: =W49*$C$46 -> 0.068753132 | X54: =X49*$C$46 -> 0.06726234 | Y54: =Y49*$C$46 -> 0.065813676 | Z54: =Z49*$C$46 -> 0.064405949 | AA54: =AA49*$C$46 -> 0.063038003
B55: 投资回收年限 | C55: 9+ | E55: NPV | F55: =-(F30) -> -7.55 | G55: =G43-G41-G54-G45-G47-G34 -> 0.63220897 | H55: =H43-H41-H54-H45-H47-H34 -> 0.57770666 | I55: =I43-I41-I54-I45-I47-I34 -> 0.52797683 | J55: =J43-J41-J54-J45-J47-J34 -> 0.48259645 | K55: =K43-K41-K54-K45-K47-K34 -> 0.4411803 | L55: =L43-L41-L54-L45-L47-L34 -> 0.40337764 | M55: =M43-M41-M54-M45-M47-M34 -> 0.36886905 | N55: =N43-N41-N54-N45-N47-N34 -> 0.33736364 | O55: =O43-O41-O54-O45-O47-O34+O35 -> 0.50114902 | Q55: NPV | R55: =-(R30) -> -7.55 | S55: =S43-S41-S54-S45-S47-S34 -> 0.6764636 | T55: =T43-T41-T54-T45-T47-T34 -> 0.66141635 | U55: =U43-U41-U54-U45-U47-U34 -> 0.64679432 | V55: =V43-V41-V54-V45-V47-V34 -> 0.6325855 | W55: =W43-W41-W54-W45-W47-W34 -> 0.61877819 | X55: =X43-X41-X54-X45-X47-X34 -> 0.60536106 | Y55: =Y43-Y41-Y54-Y45-Y47-Y34 -> 0.59232308 | Z55: =Z43-Z41-Z54-Z45-Z47-Z34 -> 0.57965354 | AA55: =AA43-AA41-AA54-AA45-AA47-AA34+AA35 -> 0.92134203
B56: 投资回报率 | C56: =F56 -> -0.43411542 | E56: 投资回报率 | F56: =SUM(F55:O55)/F30 -> -0.43411542 | Q56: IRR | R56: =IRR(R55:AA55) -> -0.044687664

Sheet 海南
B1: xxx | C1: M2访谈数据/Assumption
B2: xxx | C2: 引用数据
B3: xxx | C3: 计算所得数据
C4: 自变量 | D4: *表后用户侧储能主要通过现货形式进行峰谷套利，收益部分由峰负荷时的用户分摊
C5: 支出项 | D5: 关键假设：
C6: 收入项 | D6: 1）电池充放电循环次数~6525次
D7: 2）PCS成本：0.3元/W；电池充放电循环次数~6525次；容量型储能电站运维费用：0.1%；PCS效率：98%；线损：98%；系统使用天数：350天；充放循环次数（1次为1充1放）(次/天）：2次
B8: 更新处：标绿色的单元格 | D8: 3）充放策略：两充两放（1*谷-1*峰，1*平-1*峰）
B10: 省份 | C10: 海南省 | D10: 备注：
B11: 有无补贴政策 | C11: 有
B12: IRR：不含补贴 | C12: 0.016002933
B13: IRR：含补贴（1） | C13: N/A
B14: 补贴（1）情况 | C14: N/A
B15: IRR：含补贴（2） | C15: N/A
B16: 补贴（2）情况 | C16: N/A
B17: 该省 Best IRR | C17: =MAX(C12:C16) -> 0.016002933
B19: 基本数据 | E19: 计算结果
B20: 充放策略：两充两放（1*谷-0.5*峰，0.5*平-1*峰） | E20: LCOS（元/kWh) | F20: =F51 -> 0.57176298
B21: 谷 | C21: 1 | E21: 投资回报率 | F21: =F56 -> -0.21783336
B22: 平 | C22: 0.5 | E22: NPV(折现率=7%） | F22: =SUM(F55:O55) -> -1.6446418
B23: 峰 | C23: =C21+C22 -> 1.5 | E23: IRR | F23: =R56 -> 0.016002933
B24: 基本数据 | E24: 折现率 | F24: 0.07 | Q24: 折现率 | R24: 0
B25: PCS(KW） | C25: 1200 | E25: 所得税率 | F25: 0.25 | Q25: 所得税率 | R25: 0.25
B26: PCS成本（元/kW) | C26: 300 | E26: 增值税率 | F26: 0 | G26: 暂不考虑 | Q26: 增值税率 | R26: 0 | S26: 暂不考虑
B27: ESS(KWh) | C27: 4800 | E27: 储能系统经济效益估算表（元） | Q27: 储能系统经济效益估算表（元）
B28: ESS成本（元/kWh) | C28: 1400 | E28: 储能平准化成本LCOS（Levelized Cost of Storage） | G28: 1 | H28: 2 | I28: 3 | J28: 4 | K28: 5 | L28: 6 | M28: 7 | N28: 8 | O28: 9 | Q28: 储能平准化成本LCOS（Levelized Cost of Storage） | S28: 1 | T28: 2 | U28: 3 | V28: 4 | W28: 5 | X28: 6 | Y28: 7 | Z28: 8 | AA28: 9
B29: PCS效率 | C29: 0.98 | F29: 基准年 | G29: 第1年 | H29: 第2年 | I29: 第3年 | J29: 第4年 | K29: 第5年 | L29: 第6年 | M29: 第7年 | N29: 第8年 | O29: 第9年 | R29: 基准年 | S29: 第1年 | T29: 第2年 | U29: 第3年 | V29: 第4年 | W29: 第5年 | X29: 第6年 | Y29: 第7年 | Z29: 第8年 | AA29: 第9年
B30: 线损 | C30: 0.98 | E30: 初始投资成本（Mn RMB） | F30: =C54/1000000 -> 7.55 | Q30: 初始投资成本（Mn RMB） | R30: =C54/1000000 -> 7.55
B31: 峰价（元/KWh) | C31: 1.08182 | E31: 折旧现值和（Mn RMB） | F31: =SUM(G32:O32) -> 3.7001106 | Q31: 折旧现值和（Mn RMB） | R31: =SUM(S32:AA32) -> 5.1112522
B32: 平价（元/KWh) | C32: 0.67542 | E32: 折旧现值（Mn RMB） | G32: =($C$49+$C$50+$C$40)*(1-$C$43)/$C$48/1000000/(1+$F$24)^G28 -> 0.53076347 | H32: =($C$49+$C$50+$C$40)*(1-$C$43)/$C$48/1000000/(1+$F$24)^H28 -> 0.49604063 | I32: =($C$49+$C$50+$C$40)*(1-$C$43)/$C$48/1000000/(1+$F$24)^I28 -> 0.46358937 | J32: =($C$49+$C$50+$C$40)*(1-$C$43)/$C$48/1000000/(1+$F$24)^J28 -> 0.43326109 | K32: =($C$49+$C$50+$C$40)*(1-$C$43)/$C$48/1000000/(1+$F$24)^K28 -> 0.40491691 | L32: =($C$49+$C$50+$C$40)*(1-$C$43)/$C$48/1000000/(1+$F$24)^L28 -> 0.37842702 | M32: =($C$49+$C$50+$C$40)*(1-$C$43)/$C$48/1000000/(1+$F$24)^M28 -> 0.35367011 | N32: =($C$49+$C$50+$C$40)*(1-$C$43)/$C$48/1000000/(1+$F$24)^N28 -> 0.33053281 | O32: =($C$49+$C$50+$C$40)*(1-$C$43)/$C$48/1000000/(1+$F$24)^O28 -> 0.30890917 | Q32: 折旧现值（Mn RMB） | S32: =($C$49+$C$50+$C$40)*(1-$C$43)/$C$48/1000000/(1+$R$24)^S28 -> 0.56791691 | T32: =($C$49+$C$50+$C$40)*(1-$C$43)/$C$48/1000000/(1+$R$24)^T28 -> 0.56791691 | U32: =($C$49+$C$50+$C$40)*(1-$C$43)/$C$48/1000000/(1+$R$24)^U28 -> 0.56791691 | V32: =($C$49+$C$50+$C$40)*(1-$C$43)/$C$48/1000000/(1+$R$24)^V28 -> 0.56791691 | W32: =($C$49+$C$50+$C$40)*(1-$C$43)/$C$48/1000000/(1+$R$24)^W28 -> 0.56791691 | X32: =($C$49+$C$50+$C$40)*(1-$C$43)/$C$48/1000000/(1+$R$24)^X28 -> 0.56791691 | Y32: =($C$49+$C$50+$C$40)*(1-$C$43)/$C$48/1000000/(1+$R$24)^Y28 -> 0.56791691 | Z32: =($C$49+$C$50+$C$40)*(1-$C$43)/$C$48/1000000/(1+$R$24)^Z28 -> 0.56791691 | AA32: =($C$49+$C$50+$C$40)*(1-$C$43)/$C$48/1000000/(1+$R$24)^AA28 -> 0.56791691
B33: 谷价（元/KWh) | C33: 0.3388 | E33: 运行成本现值和（Mn RMB） | F33: =SUM(G34:O34) -> 0.049190003 | Q33: 运行成本现值和（Mn RMB） | R33: =SUM(S34:AA34) -> 0.06795
B34: 系统年使用天数 (天) | C34: 350 | E34: 运行成本现值（Mn RMB） | G34: =($C$42*$F$30)/((1+$F$24)^G28) -> 0.0070560748 | H34: =($C$42*$F$30)/((1+$F$24)^H28) -> 0.0065944624 | I34: =($C$42*$F$30)/((1+$F$24)^I28) -> 0.006163049 | J34: =($C$42*$F$30)/((1+$F$24)^J28) -> 0.0057598589 | K34: =($C$42*$F$30)/((1+$F$24)^K28) -> 0.0053830457 | L34: =($C$42*$F$30)/((1+$F$24)^L28) -> 0.0050308838 | M34: =($C$42*$F$30)/((1+$F$24)^M28) -> 0.0047017606 | N34: =($C$42*$F$30)/((1+$F$24)^N28) -> 0.0043941687 | O34: =($C$42*$F$30)/((1+$F$24)^O28) -> 0.0041066998 | Q34: 运行成本现值（Mn RMB） | S34: =($C$42*$R$30)/((1+$R$24)^S28) -> 0.00755 | T34: =($C$42*$R$30)/((1+$R$24)^T28) -> 0.00755 | U34: =($C$42*$R$30)/((1+$R$24)^U28) -> 0.00755 | V34: =($C$42*$R$30)/((1+$R$24)^V28) -> 0.00755 | W34: =($C$42*$R$30)/((1+$R$24)^W28) -> 0.00755 | X34: =($C$42*$R$30)/((1+$R$24)^X28) -> 0.00755 | Y34: =($C$42*$R$30)/((1+$R$24)^Y28) -> 0.00755 | Z34: =($C$42*$R$30)/((1+$R$24)^Z28) -> 0.00755 | AA34: =($C$42*$R$30)/((1+$R$24)^AA28) -> 0.00755
B35: DOD% | C35: 0.95 | E35: 固定资产残值现值 (Mn RMB) | O35: =(C49+C50)*C43/((1+F24)^O28)/1000000 -> 0.19255254 | Q35: 固定资产残值现值 (Mn RMB) | AA35: =(C49+C50)*C43/((1+R24)^AA28)/1000000 -> 0.354
B36: 单次循环衰减率 | C36: 4.68e-05 | E36: 充电电量现值和(KWh) | F36: =SUM(G37:O37) -> 15534030 | Q36: 充电电量现值和(KWh) | R36: =SUM(S37:AA37) -> 21224302
B37: 系统报废终止标准 | C37: 0.7 | E37: 充电电量现值(KWh) | G37: =$C$27*$C$44*$C$34/$C$45*($C$35*(1-$C$36)^((G28-1)*$C$34*$C$44))/$C$29/$C$30/((1+$F$24)^G28) -> 2426705 | H37: =$C$27*$C$44*$C$34/$C$45*($C$35*(1-$C$36)^((H28-1)*$C$34*$C$44))/$C$29/$C$30/((1+$F$24)^H28) -> 2212902.8 | I37: =$C$27*$C$44*$C$34/$C$45*($C$35*(1-$C$36)^((I28-1)*$C$34*$C$44))/$C$29/$C$30/((1+$F$24)^I28) -> 2017937.4 | J37: =$C$27*$C$44*$C$34/$C$45*($C$35*(1-$C$36)^((J28-1)*$C$34*$C$44))/$C$29/$C$30/((1+$F$24)^J28) -> 1840149.3 | K37: =$C$27*$C$44*$C$34/$C$45*($C$35*(1-$C$36)^((K28-1)*$C$34*$C$44))/$C$29/$C$30/((1+$F$24)^K28) -> 1678024.9 | L37: =$C$27*$C$44*$C$34/$C$45*($C$35*(1-$C$36)^((L28-1)*$C$34*$C$44))/$C$29/$C$30/((1+$F$24)^L28) -> 1530184.4 | M37: =$C$27*$C$44*$C$34/$C$45*($C$35*(1-$C$36)^((M28-1)*$C$34*$C$44))/$C$29/$C$30/((1+$F$24)^M28) -> 1395369.2 | N37: =$C$27*$C$44*$C$34/$C$45*($C$35*(1-$C$36)^((N28-1)*$C$34*$C$44))/$C$29/$C$30/((1+$F$24)^N28) -> 1272431.7 | O37: =$C$27*$C$44*$C$34/$C$45*($C$35*(1-$C$36)^((O28-1)*$C$34*$C$44))/$C$29/$C$30/((1+$F$24)^O28) -> 1160325.5 | Q37: 充电电量现值(KWh) | S37: =$C$27*$C$44*$C$34/$C$45*($C$35*(1-$C$36)^((S28-1)*$C$34*$C$44))/$C$29/$C$30/((1+$R$24)^S28) -> 2596574.3 | T37: =$C$27*$C$44*$C$34/$C$45*($C$35*(1-$C$36)^((T28-1)*$C$34*$C$44))/$C$29/$C$30/((1+$R$24)^T28) -> 2533552.4 | U37: =$C$27*$C$44*$C$34/$C$45*($C$35*(1-$C$36)^((U28-1)*$C$34*$C$44))/$C$29/$C$30/((1+$R$24)^U28) -> 2472060.1 | V37: =$C$27*$C$44*$C$34/$C$45*($C$35*(1-$C$36)^((V28-1)*$C$34*$C$44))/$C$29/$C$30/((1+$R$24)^V28) -> 2412060.3 | W37: =$C$27*$C$44*$C$34/$C$45*($C$35*(1-$C$36)^((W28-1)*$C$34*$C$44))/$C$29/$C$30/((1+$R$24)^W28) -> 2353516.8 | X37: =$C$27*$C$44*$C$34/$C$45*($C$35*(1-$C$36)^((X28-1)*$C$34*$C$44))/$C$29/$C$30/((1+$R$24)^X28) -> 2296394.2 | Y37: =$C$27*$C$44*$C$34/$C$45*($C$35*(1-$C$36)^((Y28-1)*$C$34*$C$44))/$C$29/$C$30/((1+$R$24)^Y28) -> 2240658 | Z37: =$C$27*$C$44*$C$34/$C$45*($C$35*(1-$C$36)^((Z28-1)*$C$34*$C$44))/$C$29/$C$30/((1+$R$24)^Z28) -> 2186274.6 | AA37: =$C$27*$C$44*$C$34/$C$45*($C$35*(1-$C$36)^((AA28-1)*$C$34*$C$44))/$C$29/$C$30/((1+$R$24)^AA28) -> 2133211.1
B38: 土建成本(元/Wh) | C38: 0.015 | E38: 放电电量现值和(KWh) | F38: =SUM(G39:O39) -> 13204772 | Q38: 放电电量现值和(KWh) | R38: =SUM(S39:AA39) -> 18041813
B39: 土建残值率（%） | C39: 0 | E39: 放电电量现值(KWh) | G39: =$C$27*$C$44*$C$34*$C$45*($C$35*(1-$C$36)^((G28-1)*$C$34*$C$44))*$C$29*$C$30/((1+$F$24)^G28) -> 2062831.5 | H39: =$C$27*$C$44*$C$34*$C$45*($C$35*(1-$C$36)^((H28-1)*$C$34*$C$44))*$C$29*$C$30/((1+$F$24)^H28) -> 1881088 | I39: =$C$27*$C$44*$C$34*$C$45*($C$35*(1-$C$36)^((I28-1)*$C$34*$C$44))*$C$29*$C$30/((1+$F$24)^I28) -> 1715356.8 | J39: =$C$27*$C$44*$C$34*$C$45*($C$35*(1-$C$36)^((J28-1)*$C$34*$C$44))*$C$29*$C$30/((1+$F$24)^J28) -> 1564227.2 | K39: =$C$27*$C$44*$C$34*$C$45*($C$35*(1-$C$36)^((K28-1)*$C$34*$C$44))*$C$29*$C$30/((1+$F$24)^K28) -> 1426412.6 | L39: =$C$27*$C$44*$C$34*$C$45*($C$35*(1-$C$36)^((L28-1)*$C$34*$C$44))*$C$29*$C$30/((1+$F$24)^L28) -> 1300740.1 | M39: =$C$27*$C$44*$C$34*$C$45*($C$35*(1-$C$36)^((M28-1)*$C$34*$C$44))*$C$29*$C$30/((1+$F$24)^M28) -> 1186139.8 | N39: =$C$27*$C$44*$C$34*$C$45*($C$35*(1-$C$36)^((N28-1)*$C$34*$C$44))*$C$29*$C$30/((1+$F$24)^N28) -> 1081636.3 | O39: =$C$27*$C$44*$C$34*$C$45*($C$35*(1-$C$36)^((O28-1)*$C$34*$C$44))*$C$29*$C$30/((1+$F$24)^O28) -> 986339.92 | Q39: 放电电量现值(KWh) | S39: =$C$27*$C$44*$C$34*$C$45*($C$35*(1-$C$36)^((S28-1)*$C$34*$C$44))*$C$29*$C$30/((1+$R$24)^S28) -> 2207229.7 | T39: =$C$27*$C$44*$C$34*$C$45*($C$35*(1-$C$36)^((T28-1)*$C$34*$C$44))*$C$29*$C$30/((1+$R$24)^T28) -> 2153657.6 | U39: =$C$27*$C$44*$C$34*$C$45*($C$35*(1-$C$36)^((U28-1)*$C$34*$C$44))*$C$29*$C$30/((1+$R$24)^U28) -> 2101385.8 | V39: =$C$27*$C$44*$C$34*$C$45*($C$35*(1-$C$36)^((V28-1)*$C$34*$C$44))*$C$29*$C$30/((1+$R$24)^V28) -> 2050382.7 | W39: =$C$27*$C$44*$C$34*$C$45*($C$35*(1-$C$36)^((W28-1)*$C$34*$C$44))*$C$29*$C$30/((1+$R$24)^W28) -> 2000617.5 | X39: =$C$27*$C$44*$C$34*$C$45*($C$35*(1-$C$36)^((X28-1)*$C$34*$C$44))*$C$29*$C$30/((1+$R$24)^X28) -> 1952060.2 | Y39: =$C$27*$C$44*$C$34*$C$45*($C$35*(1-$C$36)^((Y28-1)*$C$34*$C$44))*$C$29*$C$30/((1+$R$24)^Y28) -> 1904681.4 | Z39: =$C$27*$C$44*$C$34*$C$45*($C$35*(1-$C$36)^((Z28-1)*$C$34*$C$44))*$C$29*$C$30/((1+$R$24)^Z28) -> 1858452.5 | AA39: =$C$27*$C$44*$C$34*$C$45*($C$35*(1-$C$36)^((AA28-1)*$C$34*$C$44))*$C$29*$C$30/((1+$R$24)^AA28) -> 1813345.7
B40: 其它设备投资费用（升压变等） | C40: 350000 | E40: 充电成本现值和（Mn RMB） | F40: =SUM(G41:O41) -> 7.0059512 | Q40: 充电成本现值和（Mn RMB） | R40: =SUM(S41:AA41) -> 9.5723017
B41: 其它成本：入网检测费、项目管理费等（元/Wh） | C41: 0.01 | E41: 充电成本现值（Mn RMB） | G41: =($C$21*$C$33*G37/($C$21+$C$22)+$C$22*$C$32*G37/($C$21+$C$22))/1000000 -> 1.0944601 | H41: =($C$21*$C$33*H37/($C$21+$C$22)+$C$22*$C$32*H37/($C$21+$C$22))/1000000 -> 0.99803392 | I41: =($C$21*$C$33*I37/($C$21+$C$22)+$C$22*$C$32*I37/($C$21+$C$22))/1000000 -> 0.91010324 | J41: =($C$21*$C$33*J37/($C$21+$C$22)+$C$22*$C$32*J37/($C$21+$C$22))/1000000 -> 0.82991959 | K41: =($C$21*$C$33*K37/($C$21+$C$22)+$C$22*$C$32*K37/($C$21+$C$22))/1000000 -> 0.75680044 | L41: =($C$21*$C$33*L37/($C$21+$C$22)+$C$22*$C$32*L37/($C$21+$C$22))/1000000 -> 0.69012337 | M41: =($C$21*$C$33*M37/($C$21+$C$22)+$C$22*$C$32*M37/($C$21+$C$22))/1000000 -> 0.6293208 | N41: =($C$21*$C$33*N37/($C$21+$C$22)+$C$22*$C$32*N37/($C$21+$C$22))/1000000 -> 0.57387519 | O41: =($C$21*$C$33*O37/($C$21+$C$22)+$C$22*$C$32*O37/($C$21+$C$22))/1000000 -> 0.52331454 | Q41: 充电成本现值（Mn RMB） | S41: =($C$21*$C$33*S37/($C$21+$C$22)+$C$22*$C$32*S37/($C$21+$C$22))/1000000 -> 1.1710723 | T41: =($C$21*$C$33*T37/($C$21+$C$22)+$C$22*$C$32*T37/($C$21+$C$22))/1000000 -> 1.142649 | U41: =($C$21*$C$33*U37/($C$21+$C$22)+$C$22*$C$32*U37/($C$21+$C$22))/1000000 -> 1.1149156 | V41: =($C$21*$C$33*V37/($C$21+$C$22)+$C$22*$C$32*V37/($C$21+$C$22))/1000000 -> 1.0878553 | W41: =($C$21*$C$33*W37/($C$21+$C$22)+$C$22*$C$32*W37/($C$21+$C$22))/1000000 -> 1.0614518 | X41: =($C$21*$C$33*X37/($C$21+$C$22)+$C$22*$C$32*X37/($C$21+$C$22))/1000000 -> 1.0356891 | Y41: =($C$21*$C$33*Y37/($C$21+$C$22)+$C$22*$C$32*Y37/($C$21+$C$22))/1000000 -> 1.0105517 | Z41: =($C$21*$C$33*Z37/($C$21+$C$22)+$C$22*$C$32*Z37/($C$21+$C$22))/1000000 -> 0.98602441 | AA41: =($C$21*$C$33*AA37/($C$21+$C$22)+$C$22*$C$32*AA37/($C$21+$C$22))/1000000 -> 0.96209244
B42: 容量型储能电站运维费用 | C42: 0.001 | E42: 放电收益现值和（Mn RMB） | F42: =SUM(G43:O43) -> 14.285187 | Q42: 放电收益现值和（Mn RMB） | R42: =SUM(S43:AA43) -> 19.517994
B43: 储能系统残值 | C43: 0.05 | E43: 放电收益现值（Mn RMB） | G43: =(G39*$C$31/1000000) -> 2.2316124 | H43: =(H39*$C$31/1000000) -> 2.0349986 | I43: =(I39*$C$31/1000000) -> 1.8557073 | J43: =(J39*$C$31/1000000) -> 1.6922122 | K43: =(K39*$C$31/1000000) -> 1.5431217 | L43: =(L39*$C$31/1000000) -> 1.4071667 | M43: =(M39*$C$31/1000000) -> 1.2831898 | N43: =(N39*$C$31/1000000) -> 1.1701358 | O43: =(O39*$C$31/1000000) -> 1.0670423 | Q43: 放电收益现值（Mn RMB） | S43: =(S39*$C$31/1000000) -> 2.3878252 | T43: =(T39*$C$31/1000000) -> 2.3298699 | U43: =(U39*$C$31/1000000) -> 2.2733212 | V43: =(V39*$C$31/1000000) -> 2.218145 | W43: =(W39*$C$31/1000000) -> 2.1643081 | X43: =(X39*$C$31/1000000) -> 2.1117778 | Y43: =(Y39*$C$31/1000000) -> 2.0605224 | Z43: =(Z39*$C$31/1000000) -> 2.0105111 | AA43: =(AA39*$C$31/1000000) -> 1.9617137
B44: 充放循环次数（1次为1充1放）(次/天） | C44: =C21+C22 -> 1.5 | E44: 所得税现值和（Mn RMB） | F44: =SUM(G45:O45) -> 0.88248374 | Q44: 所得税现值和（Mn RMB） | R44: =SUM(S45:AA45) -> 1.1916226
B45: 充放电效率RTE（%） | C45: 0.96 | E45: 所得税现值（Mn RMB） | G45: =(G43-G41-G34-G32)*$F$25 -> 0.14983317 | H45: =(H43-H41-H34-H32)*$F$25 -> 0.1335824 | I45: =(I43-I41-I34-I32)*$F$25 -> 0.11896291 | J45: =(J43-J41-J34-J32)*$F$25 -> 0.10581792 | K45: =(K43-K41-K34-K32)*$F$25 -> 0.094005335 | L45: =(L43-L41-L34-L32)*$F$25 -> 0.083396355 | M45: =(M43-M41-M34-M32)*$F$25 -> 0.073874284 | N45: =(N43-N41-N34-N32)*$F$25 -> 0.065333403 | O45: =(O43-O41-O34-O32)*$F$25 -> 0.05767796 | Q45: 所得税现值（Mn RMB） | S45: =(S43-S41-S34-S32)*$R$25 -> 0.16032149 | T45: =(T43-T41-T34-T32)*$R$25 -> 0.15293849 | U45: =(U43-U41-U34-U32)*$R$25 -> 0.14573468 | V45: =(V43-V41-V34-V32)*$R$25 -> 0.13870571 | W45: =(W43-W41-W34-W32)*$R$25 -> 0.13184735 | X45: =(X43-X41-X34-X32)*$R$25 -> 0.12515544 | Y45: =(Y43-Y41-Y34-Y32)*$R$25 -> 0.11862596 | Z45: =(Z43-Z41-Z34-Z32)*$R$25 -> 0.11225495 | AA45: =(AA43-AA41-AA34-AA32)*$R$25 -> 0.10603858
B46: 用户分成比例（%） | C46: 0.1 | E46: 增值税现值和（Mn RMB） | F46: =SUM(G47:O47) -> 0 | Q46: 增值税现值和（Mn RMB） | R46: =SUM(S47:AA47) -> 0
B47: 充放循环总次数（次数） | C47: =LOG(C37/C35,(1-C36)) -> 6525.0962 | E47: 增值税现值（Mn RMB） | G47: =(G43-G41)*$F$26 -> 0 | H47: =(H43-H41)*$F$26 -> 0 | I47: =(I43-I41)*$F$26 -> 0 | J47: =(J43-J41)*$F$26 -> 0 | K47: =(K43-K41)*$F$26 -> 0 | L47: =(L43-L41)*$F$26 -> 0 | M47: =(M43-M41)*$F$26 -> 0 | N47: =(N43-N41)*$F$26 -> 0 | O47: =(O43-O41)*$F$26 -> 0 | Q47: 增值税现值（Mn RMB） | S47: =(S43-S41)*$R$26 -> 0 | T47: =(T43-T41)*$R$26 -> 0 | U47: =(U43-U41)*$R$26 -> 0 | V47: =(V43-V41)*$R$26 -> 0 | W47: =(W43-W41)*$R$26 -> 0 | X47: =(X43-X41)*$R$26 -> 0 | Y47: =(Y43-Y41)*$R$26 -> 0 | Z47: =(Z43-Z41)*$R$26 -> 0 | AA47: =(AA43-AA41)*$R$26 -> 0
B48: 系统寿命（年） | C48: =C47/C44/C34 -> 12.428755 | E48: 放电利润现值和（Mn RMB） | F48: =SUM(G49:O49) -> 6.3475618 | Q48: 放电利润现值和（Mn RMB） | R48: =SUM(S49:AA49) -> 8.6861201
B49: PCS总成本（元） | C49: =C26*C25 -> 360000 | E49: 放电利润现值和（Mn RMB） | G49: =G43-G41-G45-G47-G34 -> 0.98026299 | H49: =H43-H41-H45-H47-H34 -> 0.89678782 | I49: =I43-I41-I45-I47-I34 -> 0.82047809 | J49: =J43-J41-J45-J47-J34 -> 0.75071486 | K49: =K43-K41-K45-K47-K34 -> 0.68693291 | L49: =L43-L41-L45-L47-L34 -> 0.62861608 | M49: =M43-M41-M45-M47-M34 -> 0.57529296 | N49: =N43-N41-N45-N47-N34 -> 0.52653302 | O49: =O43-O41-O45-O47-O34 -> 0.48194305 | Q49: 放电利润现值和（Mn RMB） | S49: =S43-S41-S45-S47-S34 -> 1.0488814 | T49: =T43-T41-T45-T47-T34 -> 1.0267324 | U49: =U43-U41-U45-U47-U34 -> 1.0051209 | V49: =V43-V41-V45-V47-V34 -> 0.98403404 | W49: =W43-W41-W45-W47-W34 -> 0.96345895 | X49: =X43-X41-X45-X47-X34 -> 0.94338323 | Y49: =Y43-Y41-Y45-Y47-Y34 -> 0.92379478 | Z49: =Z43-Z41-Z45-Z47-Z34 -> 0.90468176 | AA49: =AA43-AA41-AA45-AA47-AA34 -> 0.88603264
B50: ESS总成本（元） | C50: =C27*C28 -> 6720000 | E50: 度电收益（元/kWh) | F50: =C31 -> 1.08182 | Q50: 度电收益（元/kWh) | R50: =C31 -> 1.08182
B51: 土建总投资（元） | C51: =C38*C27*1000 -> 72000 | E51: LCOS（元/kWh) | F51: =F30/F38*1000000 -> 0.57176298 | Q51: LCOS（元/kWh) | R51: =R30/R38*1000000 -> 0.41847235
B52: 其它投资（元） | C52: =C41*C27*1000 -> 48000 | E52: 充电成本（元/kWh) | F52: =F40*1000000/F38 -> 0.53056206 | Q52: 充电成本（元/kWh) | R52: =R40*1000000/R38 -> 0.53056206
B53: 设备购置补助（元） | C53: 0 | E53: 用户分成部分（元/kWh) | F53: =SUM(G54:O54) -> 0.63475618 | Q53: 用户分成部分（元/kWh) | R53: =SUM(S54:AA54) -> 0.86861201
B54: 设备总投资（元） | C54: =(C52+C51+C50+C49+C40-C53) -> 7550000 | E54: 用户分成部分现值 | G54: =G49*$C$46 -> 0.098026299 | H54: =H49*$C$46 -> 0.089678782 | I54: =I49*$C$46 -> 0.082047809 | J54: =J49*$C$46 -> 0.075071486 | K54: =K49*$C$46 -> 0.068693291 | L54: =L49*$C$46 -> 0.062861608 | M54: =M49*$C$46 -> 0.057529296 | N54: =N49*$C$46 -> 0.052653302 | O54: =O49*$C$46 -> 0.048194305 | Q54: 用户分成部分现值 | S54: =S49*$C$46 -> 0.10488814 | T54: =T49*$C$46 -> 0.10267324 | U54: =U49*$C$46 -> 0.10051209 | V54: =V49*$C$46 -> 0.098403404 | W54: =W49*$C$46 -> 0.096345895 | X54: =X49*$C$46 -> 0.094338323 | Y54: =Y49*$C$46 -> 0.092379478 | Z54: =Z49*$C$46 -> 0.090468176 | AA54: =AA49*$C$46 -> 0.088603264
B55: 投资回收年限 | C55: 9+ | E55: NPV | F55: =-(F30) -> -7.55 | G55: =G43-G41-G54-G45-G47-G34 -> 0.88223669 | H55: =H43-H41-H54-H45-H47-H34 -> 0.80710904 | I55: =I43-I41-I54-I45-I47-I34 -> 0.73843028 | J55: =J43-J41-J54-J45-J47-J34 -> 0.67564337 | K55: =K43-K41-K54-K45-K47-K34 -> 0.61823962 | L55: =L43-L41-L54-L45-L47-L34 -> 0.56575447 | M55: =M43-M41-M54-M45-M47-M34 -> 0.51776367 | N55: =N43-N41-N54-N45-N47-N34 -> 0.47387972 | O55: =O43-O41-O54-O45-O47-O34+O35 -> 0.62630129 | Q55: NPV | R55: =-(R30) -> -7.55 | S55: =S43-S41-S54-S45-S47-S34 -> 0.94399326 | T55: =T43-T41-T54-T45-T47-T34 -> 0.92405914 | U55: =U43-U41-U54-U45-U47-U34 -> 0.90460885 | V55: =V43-V41-V54-V45-V47-V34 -> 0.88563064 | W55: =W43-W41-W54-W45-W47-W34 -> 0.86711305 | X55: =X43-X41-X54-X45-X47-X34 -> 0.84904491 | Y55: =Y43-Y41-Y54-Y45-Y47-Y34 -> 0.8314153 | Z55: =Z43-Z41-Z54-Z45-Z47-Z34 -> 0.81421359 | AA55: =AA43-AA41-AA54-AA45-AA47-AA34+AA35 -> 1.1514294
B56: 投资回报率 | C56: =F56 -> -0.21783336 | E56: 投资回报率 | F56: =SUM(F55:O55)/F30 -> -0.21783336 | Q56: IRR | R56: =IRR(R55:AA55) -> 0.016002933

Sheet 云南
B1: xxx | C1: M2访谈数据/Assumption
B2: xxx | C2: 引用数据
B3: xxx | C3: 计算所得数据
C4: 自变量 | D4: *表后用户侧储能主要通过现货形式进行峰谷套利，收益部分由峰负荷时的用户分摊
C5: 支出项 | D5: 关键假设：
C6: 收入项 | D6: 1）电池充放电循环次数~6525次
D7: 2）PCS成本：0.3元/W；电池充放电循环次数~6525次；容量型储能电站运维费用：0.1%；PCS效率：98%；线损：98%；系统使用天数：350天；充放循环次数（1次为1充1放）(次/天）：2次
B8: 更新处：标绿色的单元格 | D8: 3）充放策略：两充两放（1*谷-1*峰，1*平-1*峰）
B10: 省份 | C10: 河南省 | D10: 备注：
B11: 有无补贴政策 | C11: 有
B12: IRR：不含补贴 | C12: -0.048324058
B13: IRR：含补贴（1） | C13: N/A
B14: 补贴（1）情况 | C14: N/A
B15: IRR：含补贴（2） | C15: N/A
B16: 补贴（2）情况 | C16: N/A
B17: 该省 Best IRR | C17: =MAX(C12:C16) -> -0.048324058
B19: 基本数据 | E19: 计算结果
B20: 充放策略：两充两放（1*谷-0.75*峰，0.75*平-1*峰） | E20: LCOS（元/kWh) | F20: =F51 -> 0.49691112
B21: 谷 | C21: 1 | E21: 投资回报率 | F21: =F56 -> -0.44613799
B22: 平 | C22: 0.75 | E22: NPV(折现率=7%） | F22: =SUM(F55:O55) -> -3.3683419
B23: 峰 | C23: =C21+C22 -> 1.75 | E23: IRR | F23: =R56 -> -0.048324058
B24: 基本数据 | E24: 折现率 | F24: 0.07 | Q24: 折现率 | R24: 0
B25: PCS(KW） | C25: 1200 | E25: 所得税率 | F25: 0.25 | Q25: 所得税率 | R25: 0.25
B26: PCS成本（元/kW) | C26: 300 | E26: 增值税率 | F26: 0 | G26: 暂不考虑 | Q26: 增值税率 | R26: 0 | S26: 暂不考虑
B27: ESS(KWh) | C27: 4800 | E27: 储能系统经济效益估算表（元） | Q27: 储能系统经济效益估算表（元）
B28: ESS成本（元/kWh) | C28: 1400 | E28: 储能平准化成本LCOS（Levelized Cost of Storage） | G28: 1 | H28: 2 | I28: 3 | J28: 4 | K28: 5 | L28: 6 | M28: 7 | N28: 8 | O28: 9 | Q28: 储能平准化成本LCOS（Levelized Cost of Storage） | S28: 1 | T28: 2 | U28: 3 | V28: 4 | W28: 5 | X28: 6 | Y28: 7 | Z28: 8 | AA28: 9
B29: PCS效率 | C29: 0.98 | F29: 基准年 | G29: 第1年 | H29: 第2年 | I29: 第3年 | J29: 第4年 | K29: 第5年 | L29: 第6年 | M29: 第7年 | N29: 第8年 | O29: 第9年 | R29: 基准年 | S29: 第1年 | T29: 第2年 | U29: 第3年 | V29: 第4年 | W29: 第5年 | X29: 第6年 | Y29: 第7年 | Z29: 第8年 | AA29: 第9年
B30: 线损 | C30: 0.98 | E30: 初始投资成本（Mn RMB） | F30: =C54/1000000 -> 7.55 | Q30: 初始投资成本（Mn RMB） | R30: =C54/1000000 -> 7.55
B31: 峰价（元/KWh) | C31: 0.7666 | E31: 折旧现值和（Mn RMB） | F31: =SUM(G32:O32) -> 4.3167957 | Q31: 折旧现值和（Mn RMB） | R31: =SUM(S32:AA32) -> 5.9631276
B32: 平价（元/KWh) | C32: 0.532525 | E32: 折旧现值（Mn RMB） | G32: =($C$49+$C$50+$C$40)*(1-$C$43)/$C$48/1000000/(1+$F$24)^G28 -> 0.61922405 | H32: =($C$49+$C$50+$C$40)*(1-$C$43)/$C$48/1000000/(1+$F$24)^H28 -> 0.57871406 | I32: =($C$49+$C$50+$C$40)*(1-$C$43)/$C$48/1000000/(1+$F$24)^I28 -> 0.54085426 | J32: =($C$49+$C$50+$C$40)*(1-$C$43)/$C$48/1000000/(1+$F$24)^J28 -> 0.50547127 | K32: =($C$49+$C$50+$C$40)*(1-$C$43)/$C$48/1000000/(1+$F$24)^K28 -> 0.47240306 | L32: =($C$49+$C$50+$C$40)*(1-$C$43)/$C$48/1000000/(1+$F$24)^L28 -> 0.44149819 | M32: =($C$49+$C$50+$C$40)*(1-$C$43)/$C$48/1000000/(1+$F$24)^M28 -> 0.41261513 | N32: =($C$49+$C$50+$C$40)*(1-$C$43)/$C$48/1000000/(1+$F$24)^N28 -> 0.38562162 | O32: =($C$49+$C$50+$C$40)*(1-$C$43)/$C$48/1000000/(1+$F$24)^O28 -> 0.36039403 | Q32: 折旧现值（Mn RMB） | S32: =($C$49+$C$50+$C$40)*(1-$C$43)/$C$48/1000000/(1+$R$24)^S28 -> 0.66256973 | T32: =($C$49+$C$50+$C$40)*(1-$C$43)/$C$48/1000000/(1+$R$24)^T28 -> 0.66256973 | U32: =($C$49+$C$50+$C$40)*(1-$C$43)/$C$48/1000000/(1+$R$24)^U28 -> 0.66256973 | V32: =($C$49+$C$50+$C$40)*(1-$C$43)/$C$48/1000000/(1+$R$24)^V28 -> 0.66256973 | W32: =($C$49+$C$50+$C$40)*(1-$C$43)/$C$48/1000000/(1+$R$24)^W28 -> 0.66256973 | X32: =($C$49+$C$50+$C$40)*(1-$C$43)/$C$48/1000000/(1+$R$24)^X28 -> 0.66256973 | Y32: =($C$49+$C$50+$C$40)*(1-$C$43)/$C$48/1000000/(1+$R$24)^Y28 -> 0.66256973 | Z32: =($C$49+$C$50+$C$40)*(1-$C$43)/$C$48/1000000/(1+$R$24)^Z28 -> 0.66256973 | AA32: =($C$49+$C$50+$C$40)*(1-$C$43)/$C$48/1000000/(1+$R$24)^AA28 -> 0.66256973
B33: 谷价（元/KWh) | C33: 0.29845 | E33: 运行成本现值和（Mn RMB） | F33: =SUM(G34:O34) -> 0.049190003 | Q33: 运行成本现值和（Mn RMB） | R33: =SUM(S34:AA34) -> 0.06795
B34: 系统年使用天数 (天) | C34: 350 | E34: 运行成本现值（Mn RMB） | G34: =($C$42*$F$30)/((1+$F$24)^G28) -> 0.0070560748 | H34: =($C$42*$F$30)/((1+$F$24)^H28) -> 0.0065944624 | I34: =($C$42*$F$30)/((1+$F$24)^I28) -> 0.006163049 | J34: =($C$42*$F$30)/((1+$F$24)^J28) -> 0.0057598589 | K34: =($C$42*$F$30)/((1+$F$24)^K28) -> 0.0053830457 | L34: =($C$42*$F$30)/((1+$F$24)^L28) -> 0.0050308838 | M34: =($C$42*$F$30)/((1+$F$24)^M28) -> 0.0047017606 | N34: =($C$42*$F$30)/((1+$F$24)^N28) -> 0.0043941687 | O34: =($C$42*$F$30)/((1+$F$24)^O28) -> 0.0041066998 | Q34: 运行成本现值（Mn RMB） | S34: =($C$42*$R$30)/((1+$R$24)^S28) -> 0.00755 | T34: =($C$42*$R$30)/((1+$R$24)^T28) -> 0.00755 | U34: =($C$42*$R$30)/((1+$R$24)^U28) -> 0.00755 | V34: =($C$42*$R$30)/((1+$R$24)^V28) -> 0.00755 | W34: =($C$42*$R$30)/((1+$R$24)^W28) -> 0.00755 | X34: =($C$42*$R$30)/((1+$R$24)^X28) -> 0.00755 | Y34: =($C$42*$R$30)/((1+$R$24)^Y28) -> 0.00755 | Z34: =($C$42*$R$30)/((1+$R$24)^Z28) -> 0.00755 | AA34: =($C$42*$R$30)/((1+$R$24)^AA28) -> 0.00755
B35: DOD% | C35: 0.95 | E35: 固定资产残值现值 (Mn RMB) | O35: =(C49+C50)*C43/((1+F24)^O28)/1000000 -> 0.19255254 | Q35: 固定资产残值现值 (Mn RMB) | AA35: =(C49+C50)*C43/((1+R24)^AA28)/1000000 -> 0.354
B36: 单次循环衰减率 | C36: 4.68e-05 | E36: 充电电量现值和(KWh) | F36: =SUM(G37:O37) -> 17873988 | Q36: 充电电量现值和(KWh) | R36: =SUM(S37:AA37) -> 24377075
B37: 系统报废终止标准 | C37: 0.7 | E37: 充电电量现值(KWh) | G37: =$C$27*$C$44*$C$34/$C$45*($C$35*(1-$C$36)^((G28-1)*$C$34*$C$44))/$C$29/$C$30/((1+$F$24)^G28) -> 2831155.8 | H37: =$C$27*$C$44*$C$34/$C$45*($C$35*(1-$C$36)^((H28-1)*$C$34*$C$44))/$C$29/$C$30/((1+$F$24)^H28) -> 2571169.2 | I37: =$C$27*$C$44*$C$34/$C$45*($C$35*(1-$C$36)^((I28-1)*$C$34*$C$44))/$C$29/$C$30/((1+$F$24)^I28) -> 2335057.3 | J37: =$C$27*$C$44*$C$34/$C$45*($C$35*(1-$C$36)^((J28-1)*$C$34*$C$44))/$C$29/$C$30/((1+$F$24)^J28) -> 2120627.6 | K37: =$C$27*$C$44*$C$34/$C$45*($C$35*(1-$C$36)^((K28-1)*$C$34*$C$44))/$C$29/$C$30/((1+$F$24)^K28) -> 1925889.2 | L37: =$C$27*$C$44*$C$34/$C$45*($C$35*(1-$C$36)^((L28-1)*$C$34*$C$44))/$C$29/$C$30/((1+$F$24)^L28) -> 1749033.7 | M37: =$C$27*$C$44*$C$34/$C$45*($C$35*(1-$C$36)^((M28-1)*$C$34*$C$44))/$C$29/$C$30/((1+$F$24)^M28) -> 1588418.9 | N37: =$C$27*$C$44*$C$34/$C$45*($C$35*(1-$C$36)^((N28-1)*$C$34*$C$44))/$C$29/$C$30/((1+$F$24)^N28) -> 1442553.5 | O37: =$C$27*$C$44*$C$34/$C$45*($C$35*(1-$C$36)^((O28-1)*$C$34*$C$44))/$C$29/$C$30/((1+$F$24)^O28) -> 1310083 | Q37: 充电电量现值(KWh) | S37: =$C$27*$C$44*$C$34/$C$45*($C$35*(1-$C$36)^((S28-1)*$C$34*$C$44))/$C$29/$C$30/((1+$R$24)^S28) -> 3029336.7 | T37: =$C$27*$C$44*$C$34/$C$45*($C$35*(1-$C$36)^((T28-1)*$C$34*$C$44))/$C$29/$C$30/((1+$R$24)^T28) -> 2943731.6 | U37: =$C$27*$C$44*$C$34/$C$45*($C$35*(1-$C$36)^((U28-1)*$C$34*$C$44))/$C$29/$C$30/((1+$R$24)^U28) -> 2860545.5 | V37: =$C$27*$C$44*$C$34/$C$45*($C$35*(1-$C$36)^((V28-1)*$C$34*$C$44))/$C$29/$C$30/((1+$R$24)^V28) -> 2779710.2 | W37: =$C$27*$C$44*$C$34/$C$45*($C$35*(1-$C$36)^((W28-1)*$C$34*$C$44))/$C$29/$C$30/((1+$R$24)^W28) -> 2701159.2 | X37: =$C$27*$C$44*$C$34/$C$45*($C$35*(1-$C$36)^((X28-1)*$C$34*$C$44))/$C$29/$C$30/((1+$R$24)^X28) -> 2624827.9 | Y37: =$C$27*$C$44*$C$34/$C$45*($C$35*(1-$C$36)^((Y28-1)*$C$34*$C$44))/$C$29/$C$30/((1+$R$24)^Y28) -> 2550653.7 | Z37: =$C$27*$C$44*$C$34/$C$45*($C$35*(1-$C$36)^((Z28-1)*$C$34*$C$44))/$C$29/$C$30/((1+$R$24)^Z28) -> 2478575.5 | AA37: =$C$27*$C$44*$C$34/$C$45*($C$35*(1-$C$36)^((AA28-1)*$C$34*$C$44))/$C$29/$C$30/((1+$R$24)^AA28) -> 2408534.2
B38: 土建成本(元/Wh) | C38: 0.015 | E38: 放电电量现值和(KWh) | F38: =SUM(G39:O39) -> 15193864 | Q38: 放电电量现值和(KWh) | R38: =SUM(S39:AA39) -> 20721842
B39: 土建残值率（%） | C39: 0 | E39: 放电电量现值(KWh) | G39: =$C$27*$C$44*$C$34*$C$45*($C$35*(1-$C$36)^((G28-1)*$C$34*$C$44))*$C$29*$C$30/((1+$F$24)^G28) -> 2406636.7 | H39: =$C$27*$C$44*$C$34*$C$45*($C$35*(1-$C$36)^((H28-1)*$C$34*$C$44))*$C$29*$C$30/((1+$F$24)^H28) -> 2185633.9 | I39: =$C$27*$C$44*$C$34*$C$45*($C$35*(1-$C$36)^((I28-1)*$C$34*$C$44))*$C$29*$C$30/((1+$F$24)^I28) -> 1984925.9 | J39: =$C$27*$C$44*$C$34*$C$45*($C$35*(1-$C$36)^((J28-1)*$C$34*$C$44))*$C$29*$C$30/((1+$F$24)^J28) -> 1802649 | K39: =$C$27*$C$44*$C$34*$C$45*($C$35*(1-$C$36)^((K28-1)*$C$34*$C$44))*$C$29*$C$30/((1+$F$24)^K28) -> 1637110.8 | L39: =$C$27*$C$44*$C$34*$C$45*($C$35*(1-$C$36)^((L28-1)*$C$34*$C$44))*$C$29*$C$30/((1+$F$24)^L28) -> 1486773.9 | M39: =$C$27*$C$44*$C$34*$C$45*($C$35*(1-$C$36)^((M28-1)*$C$34*$C$44))*$C$29*$C$30/((1+$F$24)^M28) -> 1350242.6 | N39: =$C$27*$C$44*$C$34*$C$45*($C$35*(1-$C$36)^((N28-1)*$C$34*$C$44))*$C$29*$C$30/((1+$F$24)^N28) -> 1226249.1 | O39: =$C$27*$C$44*$C$34*$C$45*($C$35*(1-$C$36)^((O28-1)*$C$34*$C$44))*$C$29*$C$30/((1+$F$24)^O28) -> 1113641.9 | Q39: 放电电量现值(KWh) | S39: =$C$27*$C$44*$C$34*$C$45*($C$35*(1-$C$36)^((S28-1)*$C$34*$C$44))*$C$29*$C$30/((1+$R$24)^S28) -> 2575101.3 | T39: =$C$27*$C$44*$C$34*$C$45*($C$35*(1-$C$36)^((T28-1)*$C$34*$C$44))*$C$29*$C$30/((1+$R$24)^T28) -> 2502332.3 | U39: =$C$27*$C$44*$C$34*$C$45*($C$35*(1-$C$36)^((U28-1)*$C$34*$C$44))*$C$29*$C$30/((1+$R$24)^U28) -> 2431619.6 | V39: =$C$27*$C$44*$C$34*$C$45*($C$35*(1-$C$36)^((V28-1)*$C$34*$C$44))*$C$29*$C$30/((1+$R$24)^V28) -> 2362905.2 | W39: =$C$27*$C$44*$C$34*$C$45*($C$35*(1-$C$36)^((W28-1)*$C$34*$C$44))*$C$29*$C$30/((1+$R$24)^W28) -> 2296132.5 | X39: =$C$27*$C$44*$C$34*$C$45*($C$35*(1-$C$36)^((X28-1)*$C$34*$C$44))*$C$29*$C$30/((1+$R$24)^X28) -> 2231246.8 | Y39: =$C$27*$C$44*$C$34*$C$45*($C$35*(1-$C$36)^((Y28-1)*$C$34*$C$44))*$C$29*$C$30/((1+$R$24)^Y28) -> 2168194.6 | Z39: =$C$27*$C$44*$C$34*$C$45*($C$35*(1-$C$36)^((Z28-1)*$C$34*$C$44))*$C$29*$C$30/((1+$R$24)^Z28) -> 2106924.2 | AA39: =$C$27*$C$44*$C$34*$C$45*($C$35*(1-$C$36)^((AA28-1)*$C$34*$C$44))*$C$29*$C$30/((1+$R$24)^AA28) -> 2047385.3
B40: 其它设备投资费用（升压变等） | C40: 350000 | E40: 充电成本现值和（Mn RMB） | F40: =SUM(G41:O41) -> 7.127572 | Q40: 充电成本现值和（Mn RMB） | R40: =SUM(S41:AA41) -> 9.7207938
B41: 其它成本：入网检测费、项目管理费等（元/Wh） | C41: 0.01 | E41: 充电成本现值（Mn RMB） | G41: =($C$21*$C$33*G37/($C$21+$C$22)+$C$22*$C$32*G37/($C$21+$C$22))/1000000 -> 1.1289739 | H41: =($C$21*$C$33*H37/($C$21+$C$22)+$C$22*$C$32*H37/($C$21+$C$22))/1000000 -> 1.0252996 | I41: =($C$21*$C$33*I37/($C$21+$C$22)+$C$22*$C$32*I37/($C$21+$C$22))/1000000 -> 0.93114578 | J41: =($C$21*$C$33*J37/($C$21+$C$22)+$C$22*$C$32*J37/($C$21+$C$22))/1000000 -> 0.84563813 | K41: =($C$21*$C$33*K37/($C$21+$C$22)+$C$22*$C$32*K37/($C$21+$C$22))/1000000 -> 0.7679827 | L41: =($C$21*$C$33*L37/($C$21+$C$22)+$C$22*$C$32*L37/($C$21+$C$22))/1000000 -> 0.69745841 | M41: =($C$21*$C$33*M37/($C$21+$C$22)+$C$22*$C$32*M37/($C$21+$C$22))/1000000 -> 0.63341041 | N41: =($C$21*$C$33*N37/($C$21+$C$22)+$C$22*$C$32*N37/($C$21+$C$22))/1000000 -> 0.57524397 | O41: =($C$21*$C$33*O37/($C$21+$C$22)+$C$22*$C$32*O37/($C$21+$C$22))/1000000 -> 0.52241899 | Q41: 充电成本现值（Mn RMB） | S41: =($C$21*$C$33*S37/($C$21+$C$22)+$C$22*$C$32*S37/($C$21+$C$22))/1000000 -> 1.2080021 | T41: =($C$21*$C$33*T37/($C$21+$C$22)+$C$22*$C$32*T37/($C$21+$C$22))/1000000 -> 1.1738655 | U41: =($C$21*$C$33*U37/($C$21+$C$22)+$C$22*$C$32*U37/($C$21+$C$22))/1000000 -> 1.1406936 | V41: =($C$21*$C$33*V37/($C$21+$C$22)+$C$22*$C$32*V37/($C$21+$C$22))/1000000 -> 1.1084591 | W41: =($C$21*$C$33*W37/($C$21+$C$22)+$C$22*$C$32*W37/($C$21+$C$22))/1000000 -> 1.0771355 | X41: =($C$21*$C$33*X37/($C$21+$C$22)+$C$22*$C$32*X37/($C$21+$C$22))/1000000 -> 1.046697 | Y41: =($C$21*$C$33*Y37/($C$21+$C$22)+$C$22*$C$32*Y37/($C$21+$C$22))/1000000 -> 1.0171187 | Z41: =($C$21*$C$33*Z37/($C$21+$C$22)+$C$22*$C$32*Z37/($C$21+$C$22))/1000000 -> 0.98837624 | AA41: =($C$21*$C$33*AA37/($C$21+$C$22)+$C$22*$C$32*AA37/($C$21+$C$22))/1000000 -> 0.96044601
B42: 容量型储能电站运维费用 | C42: 0.001 | E42: 放电收益现值和（Mn RMB） | F42: =SUM(G43:O43) -> 11.647616 | Q42: 放电收益现值和（Mn RMB） | R42: =SUM(S43:AA43) -> 15.885364
B43: 储能系统残值 | C43: 0.05 | E43: 放电收益现值（Mn RMB） | G43: =(G39*$C$31/1000000) -> 1.8449277 | H43: =(H39*$C$31/1000000) -> 1.675507 | I43: =(I39*$C$31/1000000) -> 1.5216442 | J43: =(J39*$C$31/1000000) -> 1.3819108 | K43: =(K39*$C$31/1000000) -> 1.2550091 | L43: =(L39*$C$31/1000000) -> 1.1397609 | M43: =(M39*$C$31/1000000) -> 1.035096 | N43: =(N39*$C$31/1000000) -> 0.94004256 | O43: =(O39*$C$31/1000000) -> 0.85371791 | Q43: 放电收益现值（Mn RMB） | S43: =(S39*$C$31/1000000) -> 1.9740727 | T43: =(T39*$C$31/1000000) -> 1.9182879 | U43: =(U39*$C$31/1000000) -> 1.8640796 | V43: =(V39*$C$31/1000000) -> 1.8114031 | W43: =(W39*$C$31/1000000) -> 1.7602152 | X43: =(X39*$C$31/1000000) -> 1.7104738 | Y43: =(Y39*$C$31/1000000) -> 1.662138 | Z43: =(Z39*$C$31/1000000) -> 1.6151681 | AA43: =(AA39*$C$31/1000000) -> 1.5695256
B44: 充放循环次数（1次为1充1放）(次/天） | C44: =C21+C22 -> 1.75 | E44: 所得税现值和（Mn RMB） | F44: =SUM(G45:O45) -> 0.038514627 | Q44: 所得税现值和（Mn RMB） | R44: =SUM(S45:AA45) -> 0.033373147
B45: 充放电效率RTE（%） | C45: 0.96 | E45: 所得税现值（Mn RMB） | G45: =(G43-G41-G34-G32)*$F$25 -> 0.022418415 | H45: =(H43-H41-H34-H32)*$F$25 -> 0.016224704 | I45: =(I43-I41-I34-I32)*$F$25 -> 0.010870279 | J45: =(J43-J41-J34-J32)*$F$25 -> 0.0062603724 | K45: =(K43-K41-K34-K32)*$F$25 -> 0.0023100743 | L45: =(L43-L41-L34-L32)*$F$25 -> -0.0010566448 | M45: =(M43-M41-M34-M32)*$F$25 -> -0.0039078216 | N45: =(N43-N41-N34-N32)*$F$25 -> -0.0063042997 | O45: =(O43-O41-O34-O32)*$F$25 -> -0.0083004522 | Q45: 所得税现值（Mn RMB） | S45: =(S43-S41-S34-S32)*$R$25 -> 0.023987704 | T45: =(T43-T41-T34-T32)*$R$25 -> 0.018575663 | U45: =(U43-U41-U34-U32)*$R$25 -> 0.013316559 | V45: =(V43-V41-V34-V32)*$R$25 -> 0.0082060712 | W45: =(W43-W41-W34-W32)*$R$25 -> 0.0032399987 | X45: =(X43-X41-X34-X32)*$R$25 -> -0.0015857389 | Y45: =(Y43-Y41-Y34-Y32)*$R$25 -> -0.0062751075 | Z45: =(Z43-Z41-Z34-Z32)*$R$25 -> -0.010831961 | AA45: =(AA43-AA41-AA34-AA32)*$R$25 -> -0.015260043
B46: 用户分成比例（%） | C46: 0.1 | E46: 增值税现值和（Mn RMB） | F46: =SUM(G47:O47) -> 0 | Q46: 增值税现值和（Mn RMB） | R46: =SUM(S47:AA47) -> 0
B47: 充放循环总次数（次数） | C47: =LOG(C37/C35,(1-C36)) -> 6525.0962 | E47: 增值税现值（Mn RMB） | G47: =(G43-G41)*$F$26 -> 0 | H47: =(H43-H41)*$F$26 -> 0 | I47: =(I43-I41)*$F$26 -> 0 | J47: =(J43-J41)*$F$26 -> 0 | K47: =(K43-K41)*$F$26 -> 0 | L47: =(L43-L41)*$F$26 -> 0 | M47: =(M43-M41)*$F$26 -> 0 | N47: =(N43-N41)*$F$26 -> 0 | O47: =(O43-O41)*$F$26 -> 0 | Q47: 增值税现值（Mn RMB） | S47: =(S43-S41)*$R$26 -> 0 | T47: =(T43-T41)*$R$26 -> 0 | U47: =(U43-U41)*$R$26 -> 0 | V47: =(V43-V41)*$R$26 -> 0 | W47: =(W43-W41)*$R$26 -> 0 | X47: =(X43-X41)*$R$26 -> 0 | Y47: =(Y43-Y41)*$R$26 -> 0 | Z47: =(Z43-Z41)*$R$26 -> 0 | AA47: =(AA43-AA41)*$R$26 -> 0
B48: 系统寿命（年） | C48: =C47/C44/C34 -> 10.653218 | E48: 放电利润现值和（Mn RMB） | F48: =SUM(G49:O49) -> 4.4323396 | Q48: 放电利润现值和（Mn RMB） | R48: =SUM(S49:AA49) -> 6.063247
B49: PCS总成本（元） | C49: =C26*C25 -> 360000 | E49: 放电利润现值和（Mn RMB） | G49: =G43-G41-G45-G47-G34 -> 0.68647929 | H49: =H43-H41-H45-H47-H34 -> 0.62738817 | I49: =I43-I41-I45-I47-I34 -> 0.5734651 | J49: =J43-J41-J45-J47-J34 -> 0.52425239 | K49: =K43-K41-K45-K47-K34 -> 0.47933328 | L49: =L43-L41-L45-L47-L34 -> 0.43832825 | M49: =M43-M41-M45-M47-M34 -> 0.40089166 | N49: =N43-N41-N45-N47-N34 -> 0.36670872 | O49: =O43-O41-O45-O47-O34 -> 0.33549268 | Q49: 放电利润现值和（Mn RMB） | S49: =S43-S41-S45-S47-S34 -> 0.73453284 | T49: =T43-T41-T45-T47-T34 -> 0.71829672 | U49: =U43-U41-U45-U47-U34 -> 0.70251941 | V49: =V43-V41-V45-V47-V34 -> 0.68718794 | W49: =W43-W41-W45-W47-W34 -> 0.67228973 | X49: =X43-X41-X45-X47-X34 -> 0.65781251 | Y49: =Y43-Y41-Y45-Y47-Y34 -> 0.64374441 | Z49: =Z43-Z41-Z45-Z47-Z34 -> 0.63007385 | AA49: =AA43-AA41-AA45-AA47-AA34 -> 0.6167896
B50: ESS总成本（元） | C50: =C27*C28 -> 6720000 | E50: 度电收益（元/kWh) | F50: =C31 -> 0.7666 | Q50: 度电收益（元/kWh) | R50: =C31 -> 0.7666
B51: 土建总投资（元） | C51: =C38*C27*1000 -> 72000 | E51: LCOS（元/kWh) | F51: =F30/F38*1000000 -> 0.49691112 | Q51: LCOS（元/kWh) | R51: =R30/R38*1000000 -> 0.36434985
B52: 其它投资（元） | C52: =C41*C27*1000 -> 48000 | E52: 充电成本（元/kWh) | F52: =F40*1000000/F38 -> 0.46910858 | Q52: 充电成本（元/kWh) | R52: =R40*1000000/R38 -> 0.46910858
B53: 设备购置补助（元） | C53: 0 | E53: 用户分成部分（元/kWh) | F53: =SUM(G54:O54) -> 0.44323396 | Q53: 用户分成部分（元/kWh) | R53: =SUM(S54:AA54) -> 0.6063247
B54: 设备总投资（元） | C54: =(C52+C51+C50+C49+C40-C53) -> 7550000 | E54: 用户分成部分现值 | G54: =G49*$C$46 -> 0.068647929 | H54: =H49*$C$46 -> 0.062738817 | I54: =I49*$C$46 -> 0.05734651 | J54: =J49*$C$46 -> 0.052425239 | K54: =K49*$C$46 -> 0.047933328 | L54: =L49*$C$46 -> 0.043832825 | M54: =M49*$C$46 -> 0.040089166 | N54: =N49*$C$46 -> 0.036670872 | O54: =O49*$C$46 -> 0.033549268 | Q54: 用户分成部分现值 | S54: =S49*$C$46 -> 0.073453284 | T54: =T49*$C$46 -> 0.071829672 | U54: =U49*$C$46 -> 0.070251941 | V54: =V49*$C$46 -> 0.068718794 | W54: =W49*$C$46 -> 0.067228973 | X54: =X49*$C$46 -> 0.065781251 | Y54: =Y49*$C$46 -> 0.064374441 | Z54: =Z49*$C$46 -> 0.063007385 | AA54: =AA49*$C$46 -> 0.06167896
B55: 投资回收年限 | C55: 9+ | E55: NPV | F55: =-(F30) -> -7.55 | G55: =G43-G41-G54-G45-G47-G34 -> 0.61783136 | H55: =H43-H41-H54-H45-H47-H34 -> 0.56464936 | I55: =I43-I41-I54-I45-I47-I34 -> 0.51611859 | J55: =J43-J41-J54-J45-J47-J34 -> 0.47182715 | K55: =K43-K41-K54-K45-K47-K34 -> 0.43139996 | L55: =L43-L41-L54-L45-L47-L34 -> 0.39449543 | M55: =M43-M41-M54-M45-M47-M34 -> 0.3608025 | N55: =N43-N41-N54-N45-N47-N34 -> 0.33003784 | O55: =O43-O41-O54-O45-O47-O34+O35 -> 0.49449595 | Q55: NPV | R55: =-(R30) -> -7.55 | S55: =S43-S41-S54-S45-S47-S34 -> 0.66107956 | T55: =T43-T41-T54-T45-T47-T34 -> 0.64646705 | U55: =U43-U41-U54-U45-U47-U34 -> 0.63226747 | V55: =V43-V41-V54-V45-V47-V34 -> 0.61846915 | W55: =W43-W41-W54-W45-W47-W34 -> 0.60506075 | X55: =X43-X41-X54-X45-X47-X34 -> 0.59203126 | Y55: =Y43-Y41-Y54-Y45-Y47-Y34 -> 0.57936997 | Z55: =Z43-Z41-Z54-Z45-Z47-Z34 -> 0.56706646 | AA55: =AA43-AA41-AA54-AA45-AA47-AA34+AA35 -> 0.90911064
B56: 投资回报率 | C56: =F56 -> -0.44613799 | E56: 投资回报率 | F56: =SUM(F55:O55)/F30 -> -0.44613799 | Q56: IRR | R56: =IRR(R55:AA55) -> -0.048324058

Sheet >华中
B2: 部分省份的测算模型需要根据不同季节、时段的分时曲线进行下一阶段的优化：

Sheet 湖北
B1: xxx | C1: M2访谈数据/Assumption
B2: xxx | C2: 引用数据
B3: xxx | C3: 计算所得数据
C4: 自变量 | D4: *表后用户侧储能主要通过现货形式进行峰谷套利，收益部分由峰负荷时的用户分摊
C5: 支出项 | D5: 关键假设：
C6: 收入项 | D6: 1）电池充放电循环次数~6525次
D7: 2）PCS成本：0.3元/W；电池充放电循环次数~6525次；容量型储能电站运维费用：0.1%；PCS效率：98%；线损：98%；系统使用天数：350天；充放循环次数（1次为1充1放）(次/天）：2次
B8: 更新处：标绿色的单元格 | D8: 3）充放策略：两充两放（1*谷-1*峰，0.5*平-0.5*峰）
B10: 省份 | C10: 湖北省 | D10: 备注： | E10: 湖北存在尖峰时段，全年执行；已在模型中计算体现
B11: 有无补贴政策 | C11: 有
B12: IRR：不含补贴 | C12: 0.019012542
B13: IRR：含补贴（1） | C13: N/A
B14: 补贴（1）情况 | C14: N/A
B15: IRR：含补贴（2） | C15: N/A | E15: ’
B16: 补贴（2）情况 | C16: N/A
B17: 该省 Best IRR | C17: =MAX(C12:C16) -> 0.019012542
B19: 基本数据 | E19: 计算结果
B20: 充放策略：两充两放（1*谷-1*峰，0.5*平-0.5*峰） | E20: LCOS（元/kWh) | F20: =F51 -> 0.57176298
B21: 谷 | C21: 1 | E21: 投资回报率 | F21: =F56 -> -0.2062739
B22: 平 | C22: 0.5 | E22: NPV(折现率=7%） | F22: =SUM(F55:O55) -> -1.557368
B23: 峰 | C23: =C21+C22 -> 1.5 | E23: IRR | F23: =R56 -> 0.019012542
B24: 基本数据 | E24: 折现率 | F24: 0.07 | Q24: 折现率 | R24: 0
B25: PCS(KW） | C25: 1200 | E25: 所得税率 | F25: 0.25 | Q25: 所得税率 | R25: 0.25
B26: PCS成本（元/kW) | C26: 300 | E26: 增值税率 | F26: 0 | G26: 暂不考虑 | Q26: 增值税率 | R26: 0 | S26: 暂不考虑
B27: ESS(KWh) | C27: 4800 | E27: 储能系统经济效益估算表（元） | Q27: 储能系统经济效益估算表（元）
B28: ESS成本（元/kWh) | C28: 1400 | E28: 储能平准化成本LCOS（Levelized Cost of Storage） | G28: 1 | H28: 2 | I28: 3 | J28: 4 | K28: 5 | L28: 6 | M28: 7 | N28: 8 | O28: 9 | Q28: 储能平准化成本LCOS（Levelized Cost of Storage） | S28: 1 | T28: 2 | U28: 3 | V28: 4 | W28: 5 | X28: 6 | Y28: 7 | Z28: 8 | AA28: 9
B29: PCS效率 | C29: 0.98 | F29: 基准年 | G29: 第1年 | H29: 第2年 | I29: 第3年 | J29: 第4年 | K29: 第5年 | L29: 第6年 | M29: 第7年 | N29: 第8年 | O29: 第9年 | R29: 基准年 | S29: 第1年 | T29: 第2年 | U29: 第3年 | V29: 第4年 | W29: 第5年 | X29: 第6年 | Y29: 第7年 | Z29: 第8年 | AA29: 第9年
B30: 线损 | C30: 0.98 | E30: 初始投资成本（Mn RMB） | F30: =C54/1000000 -> 7.55 | Q30: 初始投资成本（Mn RMB） | R30: =C54/1000000 -> 7.55
B31: 峰价（元/KWh) | C31: 1.0727338 | E31: 折旧现值和（Mn RMB） | F31: =SUM(G32:O32) -> 3.7001106 | Q31: 折旧现值和（Mn RMB） | R31: =SUM(S32:AA32) -> 5.1112522
B32: 平价（元/KWh) | C32: 0.73482 | E32: 折旧现值（Mn RMB） | G32: =($C$49+$C$50+$C$40)*(1-$C$43)/$C$48/1000000/(1+$F$24)^G28 -> 0.53076347 | H32: =($C$49+$C$50+$C$40)*(1-$C$43)/$C$48/1000000/(1+$F$24)^H28 -> 0.49604063 | I32: =($C$49+$C$50+$C$40)*(1-$C$43)/$C$48/1000000/(1+$F$24)^I28 -> 0.46358937 | J32: =($C$49+$C$50+$C$40)*(1-$C$43)/$C$48/1000000/(1+$F$24)^J28 -> 0.43326109 | K32: =($C$49+$C$50+$C$40)*(1-$C$43)/$C$48/1000000/(1+$F$24)^K28 -> 0.40491691 | L32: =($C$49+$C$50+$C$40)*(1-$C$43)/$C$48/1000000/(1+$F$24)^L28 -> 0.37842702 | M32: =($C$49+$C$50+$C$40)*(1-$C$43)/$C$48/1000000/(1+$F$24)^M28 -> 0.35367011 | N32: =($C$49+$C$50+$C$40)*(1-$C$43)/$C$48/1000000/(1+$F$24)^N28 -> 0.33053281 | O32: =($C$49+$C$50+$C$40)*(1-$C$43)/$C$48/1000000/(1+$F$24)^O28 -> 0.30890917 | Q32: 折旧现值（Mn RMB） | S32: =($C$49+$C$50+$C$40)*(1-$C$43)/$C$48/1000000/(1+$R$24)^S28 -> 0.56791691 | T32: =($C$49+$C$50+$C$40)*(1-$C$43)/$C$48/1000000/(1+$R$24)^T28 -> 0.56791691 | U32: =($C$49+$C$50+$C$40)*(1-$C$43)/$C$48/1000000/(1+$R$24)^U28 -> 0.56791691 | V32: =($C$49+$C$50+$C$40)*(1-$C$43)/$C$48/1000000/(1+$R$24)^V28 -> 0.56791691 | W32: =($C$49+$C$50+$C$40)*(1-$C$43)/$C$48/1000000/(1+$R$24)^W28 -> 0.56791691 | X32: =($C$49+$C$50+$C$40)*(1-$C$43)/$C$48/1000000/(1+$R$24)^X28 -> 0.56791691 | Y32: =($C$49+$C$50+$C$40)*(1-$C$43)/$C$48/1000000/(1+$R$24)^Y28 -> 0.56791691 | Z32: =($C$49+$C$50+$C$40)*(1-$C$43)/$C$48/1000000/(1+$R$24)^Z28 -> 0.56791691 | AA32: =($C$49+$C$50+$C$40)*(1-$C$43)/$C$48/1000000/(1+$R$24)^AA28 -> 0.56791691
B33: 谷价（元/KWh) | C33: 0.3762176 | E33: 运行成本现值和（Mn RMB） | F33: =SUM(G34:O34) -> 0.049190003 | Q33: 运行成本现值和（Mn RMB） | R33: =SUM(S34:AA34) -> 0.06795
B34: 系统年使用天数 (天) | C34: 350 | E34: 运行成本现值（Mn RMB） | G34: =($C$42*$F$30)/((1+$F$24)^G28) -> 0.0070560748 | H34: =($C$42*$F$30)/((1+$F$24)^H28) -> 0.0065944624 | I34: =($C$42*$F$30)/((1+$F$24)^I28) -> 0.006163049 | J34: =($C$42*$F$30)/((1+$F$24)^J28) -> 0.0057598589 | K34: =($C$42*$F$30)/((1+$F$24)^K28) -> 0.0053830457 | L34: =($C$42*$F$30)/((1+$F$24)^L28) -> 0.0050308838 | M34: =($C$42*$F$30)/((1+$F$24)^M28) -> 0.0047017606 | N34: =($C$42*$F$30)/((1+$F$24)^N28) -> 0.0043941687 | O34: =($C$42*$F$30)/((1+$F$24)^O28) -> 0.0041066998 | Q34: 运行成本现值（Mn RMB） | S34: =($C$42*$R$30)/((1+$R$24)^S28) -> 0.00755 | T34: =($C$42*$R$30)/((1+$R$24)^T28) -> 0.00755 | U34: =($C$42*$R$30)/((1+$R$24)^U28) -> 0.00755 | V34: =($C$42*$R$30)/((1+$R$24)^V28) -> 0.00755 | W34: =($C$42*$R$30)/((1+$R$24)^W28) -> 0.00755 | X34: =($C$42*$R$30)/((1+$R$24)^X28) -> 0.00755 | Y34: =($C$42*$R$30)/((1+$R$24)^Y28) -> 0.00755 | Z34: =($C$42*$R$30)/((1+$R$24)^Z28) -> 0.00755 | AA34: =($C$42*$R$30)/((1+$R$24)^AA28) -> 0.00755
B35: DOD% | C35: 0.95 | E35: 固定资产残值现值 (Mn RMB) | O35: =(C49+C50)*C43/((1+F24)^O28)/1000000 -> 0.19255254 | Q35: 固定资产残值现值 (Mn RMB) | AA35: =(C49+C50)*C43/((1+R24)^AA28)/1000000 -> 0.354
B36: 单次循环衰减率 | C36: 4.68e-05 | E36: 充电电量现值和(KWh) | F36: =SUM(G37:O37) -> 15534030 | Q36: 充电电量现值和(KWh) | R36: =SUM(S37:AA37) -> 21224302
B37: 系统报废终止标准 | C37: 0.7 | E37: 充电电量现值(KWh) | G37: =$C$27*$C$44*$C$34/$C$45*($C$35*(1-$C$36)^((G28-1)*$C$34*$C$44))/$C$29/$C$30/((1+$F$24)^G28) -> 2426705 | H37: =$C$27*$C$44*$C$34/$C$45*($C$35*(1-$C$36)^((H28-1)*$C$34*$C$44))/$C$29/$C$30/((1+$F$24)^H28) -> 2212902.8 | I37: =$C$27*$C$44*$C$34/$C$45*($C$35*(1-$C$36)^((I28-1)*$C$34*$C$44))/$C$29/$C$30/((1+$F$24)^I28) -> 2017937.4 | J37: =$C$27*$C$44*$C$34/$C$45*($C$35*(1-$C$36)^((J28-1)*$C$34*$C$44))/$C$29/$C$30/((1+$F$24)^J28) -> 1840149.3 | K37: =$C$27*$C$44*$C$34/$C$45*($C$35*(1-$C$36)^((K28-1)*$C$34*$C$44))/$C$29/$C$30/((1+$F$24)^K28) -> 1678024.9 | L37: =$C$27*$C$44*$C$34/$C$45*($C$35*(1-$C$36)^((L28-1)*$C$34*$C$44))/$C$29/$C$30/((1+$F$24)^L28) -> 1530184.4 | M37: =$C$27*$C$44*$C$34/$C$45*($C$35*(1-$C$36)^((M28-1)*$C$34*$C$44))/$C$29/$C$30/((1+$F$24)^M28) -> 1395369.2 | N37: =$C$27*$C$44*$C$34/$C$45*($C$35*(1-$C$36)^((N28-1)*$C$34*$C$44))/$C$29/$C$30/((1+$F$24)^N28) -> 1272431.7 | O37: =$C$27*$C$44*$C$34/$C$45*($C$35*(1-$C$36)^((O28-1)*$C$34*$C$44))/$C$29/$C$30/((1+$F$24)^O28) -> 1160325.5 | Q37: 充电电量现值(KWh) | S37: =$C$27*$C$44*$C$34/$C$45*($C$35*(1-$C$36)^((S28-1)*$C$34*$C$44))/$C$29/$C$30/((1+$R$24)^S28) -> 2596574.3 | T37: =$C$27*$C$44*$C$34/$C$45*($C$35*(1-$C$36)^((T28-1)*$C$34*$C$44))/$C$29/$C$30/((1+$R$24)^T28) -> 2533552.4 | U37: =$C$27*$C$44*$C$34/$C$45*($C$35*(1-$C$36)^((U28-1)*$C$34*$C$44))/$C$29/$C$30/((1+$R$24)^U28) -> 2472060.1 | V37: =$C$27*$C$44*$C$34/$C$45*($C$35*(1-$C$36)^((V28-1)*$C$34*$C$44))/$C$29/$C$30/((1+$R$24)^V28) -> 2412060.3 | W37: =$C$27*$C$44*$C$34/$C$45*($C$35*(1-$C$36)^((W28-1)*$C$34*$C$44))/$C$29/$C$30/((1+$R$24)^W28) -> 2353516.8 | X37: =$C$27*$C$44*$C$34/$C$45*($C$35*(1-$C$36)^((X28-1)*$C$34*$C$44))/$C$29/$C$30/((1+$R$24)^X28) -> 2296394.2 | Y37: =$C$27*$C$44*$C$34/$C$45*($C$35*(1-$C$36)^((Y28-1)*$C$34*$C$44))/$C$29/$C$30/((1+$R$24)^Y28) -> 2240658 | Z37: =$C$27*$C$44*$C$34/$C$45*($C$35*(1-$C$36)^((Z28-1)*$C$34*$C$44))/$C$29/$C$30/((1+$R$24)^Z28) -> 2186274.6 | AA37: =$C$27*$C$44*$C$34/$C$45*($C$35*(1-$C$36)^((AA28-1)*$C$34*$C$44))/$C$29/$C$30/((1+$R$24)^AA28) -> 2133211.1
B38: 土建成本(元/Wh) | C38: 0.015 | E38: 放电电量现值和(KWh) | F38: =SUM(G39:O39) -> 13204772 | Q38: 放电电量现值和(KWh) | R38: =SUM(S39:AA39) -> 18041813
B39: 土建残值率（%） | C39: 0 | E39: 放电电量现值(KWh) | G39: =$C$27*$C$44*$C$34*$C$45*($C$35*(1-$C$36)^((G28-1)*$C$34*$C$44))*$C$29*$C$30/((1+$F$24)^G28) -> 2062831.5 | H39: =$C$27*$C$44*$C$34*$C$45*($C$35*(1-$C$36)^((H28-1)*$C$34*$C$44))*$C$29*$C$30/((1+$F$24)^H28) -> 1881088 | I39: =$C$27*$C$44*$C$34*$C$45*($C$35*(1-$C$36)^((I28-1)*$C$34*$C$44))*$C$29*$C$30/((1+$F$24)^I28) -> 1715356.8 | J39: =$C$27*$C$44*$C$34*$C$45*($C$35*(1-$C$36)^((J28-1)*$C$34*$C$44))*$C$29*$C$30/((1+$F$24)^J28) -> 1564227.2 | K39: =$C$27*$C$44*$C$34*$C$45*($C$35*(1-$C$36)^((K28-1)*$C$34*$C$44))*$C$29*$C$30/((1+$F$24)^K28) -> 1426412.6 | L39: =$C$27*$C$44*$C$34*$C$45*($C$35*(1-$C$36)^((L28-1)*$C$34*$C$44))*$C$29*$C$30/((1+$F$24)^L28) -> 1300740.1 | M39: =$C$27*$C$44*$C$34*$C$45*($C$35*(1-$C$36)^((M28-1)*$C$34*$C$44))*$C$29*$C$30/((1+$F$24)^M28) -> 1186139.8 | N39: =$C$27*$C$44*$C$34*$C$45*($C$35*(1-$C$36)^((N28-1)*$C$34*$C$44))*$C$29*$C$30/((1+$F$24)^N28) -> 1081636.3 | O39: =$C$27*$C$44*$C$34*$C$45*($C$35*(1-$C$36)^((O28-1)*$C$34*$C$44))*$C$29*$C$30/((1+$F$24)^O28) -> 986339.92 | Q39: 放电电量现值(KWh) | S39: =$C$27*$C$44*$C$34*$C$45*($C$35*(1-$C$36)^((S28-1)*$C$34*$C$44))*$C$29*$C$30/((1+$R$24)^S28) -> 2207229.7 | T39: =$C$27*$C$44*$C$34*$C$45*($C$35*(1-$C$36)^((T28-1)*$C$34*$C$44))*$C$29*$C$30/((1+$R$24)^T28) -> 2153657.6 | U39: =$C$27*$C$44*$C$34*$C$45*($C$35*(1-$C$36)^((U28-1)*$C$34*$C$44))*$C$29*$C$30/((1+$R$24)^U28) -> 2101385.8 | V39: =$C$27*$C$44*$C$34*$C$45*($C$35*(1-$C$36)^((V28-1)*$C$34*$C$44))*$C$29*$C$30/((1+$R$24)^V28) -> 2050382.7 | W39: =$C$27*$C$44*$C$34*$C$45*($C$35*(1-$C$36)^((W28-1)*$C$34*$C$44))*$C$29*$C$30/((1+$R$24)^W28) -> 2000617.5 | X39: =$C$27*$C$44*$C$34*$C$45*($C$35*(1-$C$36)^((X28-1)*$C$34*$C$44))*$C$29*$C$30/((1+$R$24)^X28) -> 1952060.2 | Y39: =$C$27*$C$44*$C$34*$C$45*($C$35*(1-$C$36)^((Y28-1)*$C$34*$C$44))*$C$29*$C$30/((1+$R$24)^Y28) -> 1904681.4 | Z39: =$C$27*$C$44*$C$34*$C$45*($C$35*(1-$C$36)^((Z28-1)*$C$34*$C$44))*$C$29*$C$30/((1+$R$24)^Z28) -> 1858452.5 | AA39: =$C$27*$C$44*$C$34*$C$45*($C$35*(1-$C$36)^((AA28-1)*$C$34*$C$44))*$C$29*$C$30/((1+$R$24)^AA28) -> 1813345.7
B40: 其它设备投资费用（升压变等） | C40: 350000 | E40: 充电成本现值和（Mn RMB） | F40: =SUM(G41:O41) -> 7.7010224 | Q40: 充电成本现值和（Mn RMB） | R40: =SUM(S41:AA41) -> 10.521984
B41: 其它成本：入网检测费、项目管理费等（元/Wh） | C41: 0.01 | E41: 充电成本现值（Mn RMB） | G41: =($C$21*$C$33*G37/($C$21+$C$22)+$C$22*$C$32*G37/($C$21+$C$22))/1000000 -> 1.2030432 | H41: =($C$21*$C$33*H37/($C$21+$C$22)+$C$22*$C$32*H37/($C$21+$C$22))/1000000 -> 1.0970504 | I41: =($C$21*$C$33*I37/($C$21+$C$22)+$C$22*$C$32*I37/($C$21+$C$22))/1000000 -> 1.000396 | J41: =($C$21*$C$33*J37/($C$21+$C$22)+$C$22*$C$32*J37/($C$21+$C$22))/1000000 -> 0.91225719 | K41: =($C$21*$C$33*K37/($C$21+$C$22)+$C$22*$C$32*K37/($C$21+$C$22))/1000000 -> 0.83188378 | L41: =($C$21*$C$33*L37/($C$21+$C$22)+$C$22*$C$32*L37/($C$21+$C$22))/1000000 -> 0.75859157 | M41: =($C$21*$C$33*M37/($C$21+$C$22)+$C$22*$C$32*M37/($C$21+$C$22))/1000000 -> 0.69175669 | N41: =($C$21*$C$33*N37/($C$21+$C$22)+$C$22*$C$32*N37/($C$21+$C$22))/1000000 -> 0.63081023 | O41: =($C$21*$C$33*O37/($C$21+$C$22)+$C$22*$C$32*O37/($C$21+$C$22))/1000000 -> 0.57523338 | Q41: 充电成本现值（Mn RMB） | S41: =($C$21*$C$33*S37/($C$21+$C$22)+$C$22*$C$32*S37/($C$21+$C$22))/1000000 -> 1.2872562 | T41: =($C$21*$C$33*T37/($C$21+$C$22)+$C$22*$C$32*T37/($C$21+$C$22))/1000000 -> 1.256013 | U41: =($C$21*$C$33*U37/($C$21+$C$22)+$C$22*$C$32*U37/($C$21+$C$22))/1000000 -> 1.2255281 | V41: =($C$21*$C$33*V37/($C$21+$C$22)+$C$22*$C$32*V37/($C$21+$C$22))/1000000 -> 1.1957831 | W41: =($C$21*$C$33*W37/($C$21+$C$22)+$C$22*$C$32*W37/($C$21+$C$22))/1000000 -> 1.16676 | X41: =($C$21*$C$33*X37/($C$21+$C$22)+$C$22*$C$32*X37/($C$21+$C$22))/1000000 -> 1.1384414 | Y41: =($C$21*$C$33*Y37/($C$21+$C$22)+$C$22*$C$32*Y37/($C$21+$C$22))/1000000 -> 1.1108101 | Z41: =($C$21*$C$33*Z37/($C$21+$C$22)+$C$22*$C$32*Z37/($C$21+$C$22))/1000000 -> 1.0838494 | AA41: =($C$21*$C$33*AA37/($C$21+$C$22)+$C$22*$C$32*AA37/($C$21+$C$22))/1000000 -> 1.0575431
B42: 容量型储能电站运维费用 | C42: 0.001 | E42: 放电收益现值和（Mn RMB） | F42: =SUM(G43:O43) -> 15.109553 | Q42: 放电收益现值和（Mn RMB） | R42: =SUM(S43:AA43) -> 20.644334
B43: 储能系统残值 | C43: 0.05 | E43: 放电收益现值（Mn RMB） | G43: =G39*($C$31+$C$57)/1000000+G39*($C$31+$C$57)/1000000*0.5/1.5*0.2 -> 2.3603937 | H43: =H39*($C$31+$C$57)/1000000+H39*($C$31+$C$57)/1000000*0.5/1.5*0.2 -> 2.1524338 | I43: =I39*($C$31+$C$57)/1000000+I39*($C$31+$C$57)/1000000*0.5/1.5*0.2 -> 1.962796 | J43: =J39*($C$31+$C$57)/1000000+J39*($C$31+$C$57)/1000000*0.5/1.5*0.2 -> 1.789866 | K43: =K39*($C$31+$C$57)/1000000+K39*($C$31+$C$57)/1000000*0.5/1.5*0.2 -> 1.6321718 | L43: =L39*($C$31+$C$57)/1000000+L39*($C$31+$C$57)/1000000*0.5/1.5*0.2 -> 1.4883711 | M43: =M39*($C$31+$C$57)/1000000+M39*($C$31+$C$57)/1000000*0.5/1.5*0.2 -> 1.3572398 | N43: =N39*($C$31+$C$57)/1000000+N39*($C$31+$C$57)/1000000*0.5/1.5*0.2 -> 1.2376617 | O43: =O39*($C$31+$C$57)/1000000+O39*($C$31+$C$57)/1000000*0.5/1.5*0.2 -> 1.1286188 | Q43: 放电收益现值（Mn RMB） | S43: =S39*($C$31+$C$57)/1000000+S39*($C$31+$C$57)/1000000*0.5/1.5*0.2 -> 2.5256212 | T43: =T39*($C$31+$C$57)/1000000+T39*($C$31+$C$57)/1000000*0.5/1.5*0.2 -> 2.4643214 | U43: =U39*($C$31+$C$57)/1000000+U39*($C$31+$C$57)/1000000*0.5/1.5*0.2 -> 2.4045095 | V43: =V39*($C$31+$C$57)/1000000+V39*($C$31+$C$57)/1000000*0.5/1.5*0.2 -> 2.3461492 | W43: =W39*($C$31+$C$57)/1000000+W39*($C$31+$C$57)/1000000*0.5/1.5*0.2 -> 2.2892054 | X43: =X39*($C$31+$C$57)/1000000+X39*($C$31+$C$57)/1000000*0.5/1.5*0.2 -> 2.2336437 | Y43: =Y39*($C$31+$C$57)/1000000+Y39*($C$31+$C$57)/1000000*0.5/1.5*0.2 -> 2.1794305 | Z43: =Z39*($C$31+$C$57)/1000000+Z39*($C$31+$C$57)/1000000*0.5/1.5*0.2 -> 2.1265332 | AA43: =AA39*($C$31+$C$57)/1000000+AA39*($C$31+$C$57)/1000000*0.5/1.5*0.2 -> 2.0749197
B44: 充放循环次数（1次为1充1放）(次/天） | C44: =C21+C22 -> 1.5 | E44: 所得税现值和（Mn RMB） | F44: =SUM(G45:O45) -> 0.91480739 | Q44: 所得税现值和（Mn RMB） | R44: =SUM(S45:AA45) -> 1.2357868
B45: 充放电效率RTE（%） | C45: 0.96 | E45: 所得税现值（Mn RMB） | G45: =(G43-G41-G34-G32)*$F$25 -> 0.15488273 | H45: =(H43-H41-H34-H32)*$F$25 -> 0.13818707 | I45: =(I43-I41-I34-I32)*$F$25 -> 0.12316189 | J45: =(J43-J41-J34-J32)*$F$25 -> 0.10964696 | K45: =(K43-K41-K34-K32)*$F$25 -> 0.097497017 | L45: =(L43-L41-L34-L32)*$F$25 -> 0.086580406 | M45: =(M43-M41-M34-M32)*$F$25 -> 0.076777808 | N45: =(N43-N41-N34-N32)*$F$25 -> 0.067981115 | O45: =(O43-O41-O34-O32)*$F$25 -> 0.060092398 | Q45: 所得税现值（Mn RMB） | S45: =(S43-S41-S34-S32)*$R$25 -> 0.16572452 | T45: =(T43-T41-T34-T32)*$R$25 -> 0.15821038 | U45: =(U43-U41-U34-U32)*$R$25 -> 0.15087861 | V45: =(V43-V41-V34-V32)*$R$25 -> 0.14372479 | W45: =(W43-W41-W34-W32)*$R$25 -> 0.13674461 | X45: =(X43-X41-X34-X32)*$R$25 -> 0.12993384 | Y45: =(Y43-Y41-Y34-Y32)*$R$25 -> 0.12328838 | Z45: =(Z43-Z41-Z34-Z32)*$R$25 -> 0.11680421 | AA45: =(AA43-AA41-AA34-AA32)*$R$25 -> 0.11047742
B46: 用户分成比例（%） | C46: 0.1 | E46: 增值税现值和（Mn RMB） | F46: =SUM(G47:O47) -> 0 | Q46: 增值税现值和（Mn RMB） | R46: =SUM(S47:AA47) -> 0
B47: 充放循环总次数（次数） | C47: =LOG(C37/C35,(1-C36)) -> 6525.0962 | E47: 增值税现值（Mn RMB） | G47: =(G43-G41)*$F$26 -> 0 | H47: =(H43-H41)*$F$26 -> 0 | I47: =(I43-I41)*$F$26 -> 0 | J47: =(J43-J41)*$F$26 -> 0 | K47: =(K43-K41)*$F$26 -> 0 | L47: =(L43-L41)*$F$26 -> 0 | M47: =(M43-M41)*$F$26 -> 0 | N47: =(N43-N41)*$F$26 -> 0 | O47: =(O43-O41)*$F$26 -> 0 | Q47: 增值税现值（Mn RMB） | S47: =(S43-S41)*$R$26 -> 0 | T47: =(T43-T41)*$R$26 -> 0 | U47: =(U43-U41)*$R$26 -> 0 | V47: =(V43-V41)*$R$26 -> 0 | W47: =(W43-W41)*$R$26 -> 0 | X47: =(X43-X41)*$R$26 -> 0 | Y47: =(Y43-Y41)*$R$26 -> 0 | Z47: =(Z43-Z41)*$R$26 -> 0 | AA47: =(AA43-AA41)*$R$26 -> 0
B48: 系统寿命（年） | C48: =C47/C44/C34 -> 12.428755 | E48: 放电利润现值和（Mn RMB） | F48: =SUM(G49:O49) -> 6.4445328 | Q48: 放电利润现值和（Mn RMB） | R48: =SUM(S49:AA49) -> 8.8186125
B49: PCS总成本（元） | C49: =C26*C25 -> 360000 | E49: 放电利润现值和（Mn RMB） | G49: =G43-G41-G45-G47-G34 -> 0.99541166 | H49: =H43-H41-H45-H47-H34 -> 0.91060184 | I49: =I43-I41-I45-I47-I34 -> 0.83307504 | J49: =J43-J41-J45-J47-J34 -> 0.76220197 | K49: =K43-K41-K45-K47-K34 -> 0.69740796 | L49: =L43-L41-L45-L47-L34 -> 0.63816824 | M49: =M43-M41-M45-M47-M34 -> 0.58400353 | N49: =N43-N41-N45-N47-N34 -> 0.53447616 | O49: =O43-O41-O45-O47-O34 -> 0.48918637 | Q49: 放电利润现值和（Mn RMB） | S49: =S43-S41-S45-S47-S34 -> 1.0650905 | T49: =T43-T41-T45-T47-T34 -> 1.042548 | U49: =U43-U41-U45-U47-U34 -> 1.0205527 | V49: =V43-V41-V45-V47-V34 -> 0.9990913 | W49: =W43-W41-W45-W47-W34 -> 0.97815074 | X49: =X43-X41-X45-X47-X34 -> 0.95771844 | Y49: =Y43-Y41-Y45-Y47-Y34 -> 0.93778206 | Z49: =Z43-Z41-Z45-Z47-Z34 -> 0.91832955 | AA49: =AA43-AA41-AA45-AA47-AA34 -> 0.89934918
B50: ESS总成本（元） | C50: =C27*C28 -> 6720000 | E50: 度电收益（元/kWh) | F50: =C31 -> 1.0727338 | Q50: 度电收益（元/kWh) | R50: =C31 -> 1.0727338
B51: 土建总投资（元） | C51: =C38*C27*1000 -> 72000 | E51: LCOS（元/kWh) | F51: =F30/F38*1000000 -> 0.57176298 | Q51: LCOS（元/kWh) | R51: =R30/R38*1000000 -> 0.41847235
B52: 其它投资（元） | C52: =C41*C27*1000 -> 48000 | E52: 充电成本（元/kWh) | F52: =F40*1000000/F38 -> 0.58319994 | Q52: 充电成本（元/kWh) | R52: =R40*1000000/R38 -> 0.58319994
B53: 设备购置补助（元） | C53: 0 | E53: 用户分成部分（元/kWh) | F53: =SUM(G54:O54) -> 0.64445328 | Q53: 用户分成部分（元/kWh) | R53: =SUM(S54:AA54) -> 0.88186125
B54: 设备总投资（元） | C54: =(C52+C51+C50+C49+C40-C53) -> 7550000 | E54: 用户分成部分现值 | G54: =G49*$C$46 -> 0.099541166 | H54: =H49*$C$46 -> 0.091060184 | I54: =I49*$C$46 -> 0.083307504 | J54: =J49*$C$46 -> 0.076220197 | K54: =K49*$C$46 -> 0.069740796 | L54: =L49*$C$46 -> 0.063816824 | M54: =M49*$C$46 -> 0.058400353 | N54: =N49*$C$46 -> 0.053447616 | O54: =O49*$C$46 -> 0.048918637 | Q54: 用户分成部分现值 | S54: =S49*$C$46 -> 0.10650905 | T54: =T49*$C$46 -> 0.1042548 | U54: =U49*$C$46 -> 0.10205527 | V54: =V49*$C$46 -> 0.09990913 | W54: =W49*$C$46 -> 0.097815074 | X54: =X49*$C$46 -> 0.095771844 | Y54: =Y49*$C$46 -> 0.093778206 | Z54: =Z49*$C$46 -> 0.091832955 | AA54: =AA49*$C$46 -> 0.089934918
B55: 投资回收年限 | C55: 9+ | E55: NPV | F55: =-(F30) -> -7.55 | G55: =G43-G41-G54-G45-G47-G34 -> 0.89587049 | H55: =H43-H41-H54-H45-H47-H34 -> 0.81954165 | I55: =I43-I41-I54-I45-I47-I34 -> 0.74976753 | J55: =J43-J41-J54-J45-J47-J34 -> 0.68598177 | K55: =K43-K41-K54-K45-K47-K34 -> 0.62766717 | L55: =L43-L41-L54-L45-L47-L34 -> 0.57435141 | M55: =M43-M41-M54-M45-M47-M34 -> 0.52560318 | N55: =N43-N41-N54-N45-N47-N34 -> 0.48102854 | O55: =O43-O41-O54-O45-O47-O34+O35 -> 0.63282027 | Q55: NPV | R55: =-(R30) -> -7.55 | S55: =S43-S41-S54-S45-S47-S34 -> 0.95858143 | T55: =T43-T41-T54-T45-T47-T34 -> 0.93829324 | U55: =U43-U41-U54-U45-U47-U34 -> 0.91849747 | V55: =V43-V41-V54-V45-V47-V34 -> 0.89918217 | W55: =W43-W41-W54-W45-W47-W34 -> 0.88033567 | X55: =X43-X41-X54-X45-X47-X34 -> 0.8619466 | Y55: =Y43-Y41-Y54-Y45-Y47-Y34 -> 0.84400385 | Z55: =Z43-Z41-Z54-Z45-Z47-Z34 -> 0.8264966 | AA55: =AA43-AA41-AA54-AA45-AA47-AA34+AA35 -> 1.1634143
B56: 投资回报率 | C56: =F56 -> -0.2062739 | E56: 投资回报率 | F56: =SUM(F55:O55)/F30 -> -0.2062739 | Q56: IRR | R56: =IRR(R55:AA55) -> 0.019012542
B57: 放电补贴（元/kWh) | C57: 0

Sheet 湖南
B1: xxx | C1: M2访谈数据/Assumption
B2: xxx | C2: 引用数据
B3: xxx | C3: 计算所得数据
C4: 自变量 | D4: *表后用户侧储能主要通过现货形式进行峰谷套利，收益部分由峰负荷时的用户分摊
C5: 支出项 | D5: 关键假设：
C6: 收入项 | D6: 1）电池充放电循环次数~6525次
D7: 2）PCS成本：0.3元/W；电池充放电循环次数~6525次；容量型储能电站运维费用：0.1%；PCS效率：98%；线损：98%；系统使用天数：350天；充放循环次数（1次为1充1放）(次/天）：2次
B8: 更新处：标绿色的单元格 | D8: 3）充放策略：两充两放（1*谷-0.75*峰，0.75*平-1*峰）
B10: 省份 | C10: 湖南省 | D10: 备注：
B11: 有无补贴政策 | C11: 有
B12: IRR：不含补贴 | C12: 0.036886496
B13: IRR：含补贴（1） | C13: N/A
B14: 补贴（1）情况 | C14: N/A
B15: IRR：含补贴（2） | C15: N/A
B16: 补贴（2）情况 | C16: N/A
B17: 该省 Best IRR | C17: =MAX(C12:C16) -> 0.036886496
B19: 基本数据 | E19: 计算结果
B20: 充放策略：两充两放（1*谷-0.75*峰，0.75*平-1*峰） | E20: LCOS（元/kWh) | F20: =F51 -> 0.49691112
B21: 谷 | C21: 1 | E21: 投资回报率 | F21: =F56 -> -0.13566592
B22: 平 | C22: 0.75 | E22: NPV(折现率=7%） | F22: =SUM(F55:O55) -> -1.0242777
B23: 峰 | C23: =C21+C22 -> 1.75 | E23: IRR | F23: =R56 -> 0.036886496
B24: 基本数据 | E24: 折现率 | F24: 0.07 | Q24: 折现率 | R24: 0
B25: PCS(KW） | C25: 1200 | E25: 所得税率 | F25: 0.25 | Q25: 所得税率 | R25: 0.25
B26: PCS成本（元/kW) | C26: 300 | E26: 增值税率 | F26: 0 | G26: 暂不考虑 | Q26: 增值税率 | R26: 0 | S26: 暂不考虑
B27: ESS(KWh) | C27: 4800 | E27: 储能系统经济效益估算表（元） | Q27: 储能系统经济效益估算表（元）
